Workbook

Sheet Resumen
A1: RESUMEN EJECUTIVO
A2: =+Detalle!A1
A4: ESTADO DE LIQUIDEZ | B4: TOTAL A PAGAR (US$) | C4: SALDO DISPONIBLE (US$) | D4: SALDO PROYECTADO (US$ )
A5: =IF(AND(D35<0,OR(D36<0,D37<0)),"SE NECESITA VENDER Y TRANSFERIR DÓLARES",IF(D35<0,"SE NECESITA VENDER DÓLARES",IF(OR(D36<0,D37<0),"SE NECESITA TRANSFERIR DÓLARES","LIQUIDEZ SUFICIENTE"))) | B5: =ROUNDUP(D18/10000,0)*10000 | C5: =+D25 | D5: =+C31
A7: I. PAGOS A REALIZAR — RESUMEN POR BANCO Y TOTAL
A8: Banco | B8: Operación | C8: Moneda | D8: Importe
A9: BCP | B9: Operación 1 - Pago masivo proveedores | C9: S/ | D9: =+Detalle!O9
A10: BCP | B10: Operación 2 - Pago masivo proveedores | C10: US$ | D10: =+Detalle!O15
A11: BCP | B11: Operación 3 - Pagos varios | C11: S/ | D11: =+Detalle!O33
A12: BCP | B12: Operación 4 - Pagos varios | C12: US$ | D12: =+Detalle!O39
A13: BCP | B13: Operación 5 - Pagos servicios | C13: S/ | D13: =+Detalle!O45
A14: Interbank | B14: Operación 6 - Materia Prima Exterior | C14: US$ | D14: =+Detalle!O84+Detalle!O84
A15: BCP | B15: Operación 7 - Materia Prima Nacional | C15: US$ | D15: =+Detalle!O91
A16: TOTAL SOLES (S/) | D16: =+D9+D11+D13
A17: TOTAL DÓLARES (US$) | D17: =+D10+D12+D14
A18: TOTAL CONSOLIDADO (US$) | B18: Tipo de Cambio | C18: 3.5 | D18: =+(D16/C18)+D17
A20: II. SALDOS DISPONIBLES POR BANCO
A21: Banco | B21: Saldo US$ | C21: Saldo S/ | D21: Total equiv. US$
A22: BCP | D22: =+B22+(C22/C18)
A23: BBVA | D23: =+B23+(C23/C18)
A24: IBK | D24: =+B24+(C24/C18)
A25: TOTAL | B25: =+SUM(B22:B24) | C25: =+SUM(C22:C24) | D25: =+B25+(C25/C18)
A27: III. SALDO PROYECTADO (US$)
A28: Saldo disponible actual | C28: =+D25
A29: (+) Ingreso estimado
A30: (-) Pagos programados semana | C30: =+D18
A31: (=) Nuevo saldo proyectado | C31: =+C28+C29-C30
A33: IV. ESTADO DE LIQUIDEZ
A34: Cuenta | B34: Pagos a Realizar | C34: Saldo Disponible Para Pagos | D34: Excedente / (Déficit)
A35: BCP SOLES | B35: =+D16 | C35: =+C22 | D35: =C35-B35
A36: BCP DÓLARES | B36: =+D10+D12 | C36: =+B22 | D36: =C36-B36
A37: INTERBANK DÓLARES | B37: =+D14 | C37: =+B24 | D37: =C37-B37
A39: V. ALERTAS Y ACCIONES REQUERIDAS
A40: Cuenta | B40: Excedente / (Déficit) | C40: Acción | D40: Monto Venta/Transferencia
A41: BCP SOLES | B41: =C35-B35 | C41: =IF(D35<0,"SE NECESITA VENDER DÓLARES","LIQUIDEZ SUFICIENTE") | D41: =IF(D35<0,-D35/C18,0)
A42: BCP DÓLARES | B42: =+D36 | C42: =IF(D36<0,"SE NECESITA TRANSFERIR DÓLARES","LIQUIDEZ SUFICIENTE") | D42: =IF(D36<0,-D36,0)
A43: INTERBANK DÓLARES | B43: =+D37 | C43: =IF(D37<0,"SE NECESITA TRANSFERIR DÓLARES","LIQUIDEZ SUFICIENTE") | D43: =IF(D37<0,-D37,0)

Sheet Detalle
A1: PAGOS PROVEEDORES 06/07/2026
A3: I. DETALLE DE DOCUMENTOS
A5: Operación 1 - Pago masivo proveedores - Soles
A6: PROVEEDOR | B6: TIPO | C6: N° DOCUMENTO | D6: FEC. REGISTRO | E6: FEC.DOC | F6: FEC.VCTO | G6: IMPORTE | H6: PAGADO | I6: SALDO | J6: PLAZO | K6: % DET | L6: DET | M6: % RET | N6: RET | O6: Neto | P6: DETALLE | Q6: N° O/C-O/S | R6: N° Registro | S6: SUSTENTO
J7: =F7-E7 | O7: =I7-L7-N7
J8: =F8-E8 | O8: =I8-L8-N8
A9: TOTAL | O9: =SUM(O7:O8)
A11: Operación 2 - Pago masivo proveedores - Dólares
A12: PROVEEDOR | B12: TIPO | C12: N° DOCUMENTO | D12: FEC. REGISTRO | E12: FEC.DOC | F12: FEC.VCTO | G12: IMPORTE | H12: PAGADO | I12: SALDO | J12: PLAZO | K12: % DET | L12: DET | M12: % RET | N12: RET | O12: Neto | P12: DETALLE | Q12: N° O/C-O/S | R12: N° Registro | S12: SUSTENTO
J13: =F13-E13 | O13: =I13-L13-N13
J14: =F14-E14 | O14: =I14-L14-N14
A15: TOTAL | O15: =SUM(O13:O14)
A17: AGENTES DE ADUANAS SOLES
A18: PROVEEDOR | B18: TIPO | C18: N° DOCUMENTO | D18: FEC. REGISTRO | E18: FEC.DOC | F18: FEC.VCTO | G18: IMPORTE | H18: PAGADO | I18: SALDO | K18: % DET | L18: DET | M18: % RET | N18: RET | P18: AGENTE ADUANERO | Q18: N° O/C-O/S | S18: LINK FACTURA
J19: =F19-E19 | O19: =I19-L19-N19
J20: =F20-E20 | O20: =I20-L20-N20
A21: TOTAL
A23: AGENTES DE ADUANAS DOLARES
A24: PROVEEDOR | B24: TIPO | C24: N° DOCUMENTO | D24: FEC. REGISTRO | E24: FEC.DOC | F24: FEC.VCTO | G24: IMPORTE | H24: PAGADO | I24: SALDO | K24: % DET | L24: DET | M24: % RET | N24: RET | P24: AGENTE ADUANERO | Q24: N° O/C-O/S | S24: LINK FACTURA
J25: =F25-E25 | O25: =I25-L25-N25
J26: =F26-E26 | O26: =I26-L26-N26
A27: TOTAL
A29: Operación 3 - Pagos varios - Soles
A30: PROVEEDOR | B30: TIPO | C30: N° DOCUMENTO | D30: FEC. REGISTRO | E30: FEC.DOC | F30: FEC.VCTO | G30: IMPORTE | H30: PAGADO | I30: SALDO | J30: PLAZO | K30: % DET | L30: DET | M30: % RET | N30: RET | O30: Neto | P30: DETALLE | Q30: N° O/C-O/S | R30: N° Registro | S30: LINK FACTURA
J31: =F31-E31 | O31: =I31-L31-N31
J32: =F32-E32 | O32: =I32-L32-N32
A33: TOTAL | O33: =SUM(O31:O32)
A35: Operación 4 - Pagos varios - Dólares
A36: PROVEEDOR | B36: TIPO | C36: N° DOCUMENTO | D36: FEC. REGISTRO | E36: FEC.DOC | F36: FEC.VCTO | G36: IMPORTE | H36: PAGADO | I36: SALDO | J36: PLAZO | K36: % DET | L36: DET | M36: % RET | N36: RET | O36: Neto | P36: DETALLE | Q36: N° O/C-O/S | R36: N° Registro | S36: LINK FACTURA
J37: =F37-E37 | O37: =I37-L37-N37
J38: =F38-E38 | O38: =I38-L38-N38
A39: TOTAL | O39: =SUM(#REF!)
A41: Operación 5 - Pagos servicios - Soles
A42: PROVEEDOR | B42: TIPO | C42: N° DOCUMENTO | D42: FEC. REGISTRO | E42: FEC.DOC | F42: FEC.VCTO | G42: IMPORTE | H42: PAGADO | I42: SALDO | J42: PLAZO | K42: % DET | L42: DET | M42: % RET | N42: RET | O42: Neto | P42: DETALLE | Q42: N° O/C-O/S | R42: N° Registro | S42: LINK FACTURA
J43: =F43-E43 | O43: =I43-L43-N43
J44: =F44-E44 | O44: =I44-L44-N44
A45: TOTAL | O45: =SUM(O43:P44)
A47: PAGOS AL PERSONAL SOLES
A48: PROVEEDOR | B48: TIPO | C48: N° DOCUMENTO | D48: FEC. REGISTRO | E48: FEC.DOC | F48: FEC.VCTO | G48: IMPORTE | H48: PAGADO | I48: SALDO | K48: % DET | L48: DET | M48: % RET | N48: RET | P48: DETALLE | Q48: N° O/C-O/S | S48: LINK FACTURA
A49: BANCO BCP | J49: =F49-E49 | O49: =I49
A50: BANCO BBVA | J50: =F50-E50 | O50: =I50
A51: BANCO INTERBANK | J51: =F51-E51 | O51: =I51
A52: BANCO SCOTIABANK | J52: =F52-E52 | O52: =I52
A53: BANCO FALABELLA | J53: =F53-E53 | O53: =I53
A54: BANCO COMERCIO | J54: =F54-E54 | O54: =I54
A55: CAJA HUANCAYO | J55: =F55-E55 | O55: =I55
A56: CAJA PIURA | J56: =F56-E56 | O56: =I56
A57: VARIOS | J57: =F57-E57 | O57: =I57
A58: MARY OLGA SAICO ICHPAS | J58: =F58-E58 | O58: =I58
A59: TOTAL | O59: =SUM(O49:O58)
A61: PAGOS SEGUROS SOLES
A62: PROVEEDOR | B62: TIPO | C62: N° DOCUMENTO | D62: FEC. REGISTRO | E62: FEC.DOC | F62: FEC.VCTO | G62: IMPORTE | H62: PAGADO | I62: SALDO | K62: % DET | L62: DET | M62: % RET | N62: RET | P62: DETALLE | Q62: N° O/C-O/S | S62: LINK FACTURA
A63: MAPFRE
A64: MAPFRE
A65: MAPFRE
A66: MAPFRE
A67: MAPFRE-EPS
A68: PROTECTA S.A. COMPAÑIA DE SEGUROS
A69: PROTECTA S.A. COMPAÑIA DE SEGUROS
A70: PROTECTA S.A. COMPAÑIA DE SEGUROS
A71: PROTECTA S.A. COMPAÑIA DE SEGUROS | X71: 218.95 | AC71: =+Y71-AA71-AC71 | AE71: SEGUROS | AF71: RIMAC SEGUROS | AH71: 1086478942 | AK71: 45341 | AN71: 218.95 | AS71: =+AO71-AQ71-AS71 | AU71: SEGUROS | AV71: RIMAC SEGUROS | AX71: 1086478942 | BA71: 45341 | BD71: 218.95 | BI71: =+BE71-BG71-BI71 | BK71: SEGUROS | BL71: RIMAC SEGUROS | BN71: 1086478942 | BQ71: 45341 | BT71: 218.95 | BY71: =+BU71-BW71-BY71 | CA71: SEGUROS | CB71: RIMAC SEGUROS | CD71: 1086478942 | CG71: 45341 | CJ71: 218.95 | CO71: =+CK71-CM71-CO71 | CQ71: SEGUROS | CR71: RIMAC SEGUROS | CT71: 1086478942 | CW71: 45341 | CZ71: 218.95 | DE71: =+DA71-DC71-DE71 | DG71: SEGUROS | DH71: RIMAC SEGUROS | DJ71: 1086478942 | DM71: 45341 | DP71: 218.95 | DU71: =+DQ71-DS71-DU71 | DW71: SEGUROS | DX71: RIMAC SEGUROS | DZ71: 1086478942 | EC71: 45341 | EF71: 218.95 | EK71: =+EG71-EI71-EK71 | EM71: SEGUROS | EN71: RIMAC SEGUROS | EP71: 1086478942 | ES71: 45341 | EV71: 218.95 | FA71: =+EW71-EY71-FA71 | FC71: SEGUROS | FD71: RIMAC SEGUROS | FF71: 1086478942 | FI71: 45341 | FL71: 218.95 | FQ71: =+FM71-FO71-FQ71 | FS71: SEGUROS | FT71: RIMAC SEGUROS | FV71: 1086478942 | FY71: 45341 | GB71: 218.95 | GG71: =+GC71-GE71-GG71 | GI71: SEGUROS | GJ71: RIMAC SEGUROS | GL71: 1086478942 | GO71: 45341 | GR71: 218.95 | GW71: =+GS71-GU71-GW71 | GY71: SEGUROS | GZ71: RIMAC SEGUROS | HB71: 1086478942 | HE71: 45341 | HH71: 218.95 | HM71: =+HI71-HK71-HM71 | HO71: SEGUROS | HP71: RIMAC SEGUROS | HR71: 1086478942 | HU71: 45341 | HX71: 218.95 | IC71: =+HY71-IA71-IC71 | IE71: SEGUROS | IF71: RIMAC SEGUROS | IH71: 1086478942 | IK71: 45341 | IN71: 218.95 | IS71: =+IO71-IQ71-IS71 | IU71: SEGUROS | IV71: RIMAC SEGUROS | IX71: 1086478942 | JA71: 45341 | JD71: 218.95 | JI71: =+JE71-JG71-JI71 | JK71: SEGUROS | JL71: RIMAC SEGUROS | JN71: 1086478942 | JQ71: 45341 | JT71: 218.95 | JY71: =+JU71-JW71-JY71 | KA71: SEGUROS | KB71: RIMAC SEGUROS | KD71: 1086478942 | KG71: 45341 | KJ71: 218.95 | KO71: =+KK71-KM71-KO71 | KQ71: SEGUROS | KR71: RIMAC SEGUROS | KT71: 1086478942 | KW71: 45341 | KZ71: 218.95 | LE71: =+LA71-LC71-LE71 | LG71: SEGUROS | LH71: RIMAC SEGUROS | LJ71: 1086478942 | LM71: 45341 | LP71: 218.95 | LU71: =+LQ71-LS71-LU71 | LW71: SEGUROS | LX71: RIMAC SEGUROS | LZ71: 1086478942 | MC71: 45341 | MF71: 218.95 | MK71: =+MG71-MI71-MK71 | MM71: SEGUROS | MN71: RIMAC SEGUROS | MP71: 1086478942 | MS71: 45341 | MV71: 218.95 | NA71: =+MW71-MY71-NA71 | NC71: SEGUROS | ND71: RIMAC SEGUROS | NF71: 1086478942 | NI71: 45341 | NL71: 218.95 | NQ71: =+NM71-NO71-NQ71 | NS71: SEGUROS | NT71: RIMAC SEGUROS | NV71: 1086478942 | NY71: 45341 | OB71: 218.95 | OG71: =+OC71-OE71-OG71 | OI71: SEGUROS | OJ71: RIMAC SEGUROS | OL71: 1086478942 | OO71: 45341 | OR71: 218.95 | OW71: =+OS71-OU71-OW71 | OY71: SEGUROS | OZ71: RIMAC SEGUROS | PB71: 1086478942 | PE71: 45341 | PH71: 218.95 | PM71: =+PI71-PK71-PM71 | PO71: SEGUROS | PP71: RIMAC SEGUROS | PR71: 1086478942 | PU71: 45341 | PX71: 218.95 | QC71: =+PY71-QA71-QC71 | QE71: SEGUROS | QF71: RIMAC SEGUROS | QH71: 1086478942 | QK71: 45341 | QN71: 218.95 | QS71: =+QO71-QQ71-QS71 | QU71: SEGUROS | QV71: RIMAC SEGUROS | QX71: 1086478942 | RA71: 45341 | RD71: 218.95 | RI71: =+RE71-RG71-RI71 | RK71: SEGUROS | RL71: RIMAC SEGUROS | RN71: 1086478942 | RQ71: 45341 | RT71: 218.95 | RY71: =+RU71-RW71-RY71 | SA71: SEGUROS | SB71: RIMAC SEGUROS | SD71: 1086478942 | SG71: 45341 | SJ71: 218.95 | SO71: =+SK71-SM71-SO71 | SQ71: SEGUROS | SR71: RIMAC SEGUROS | ST71: 1086478942 | SW71: 45341 | SZ71: 218.95 | TE71: =+TA71-TC71-TE71 | TG71: SEGUROS | TH71: RIMAC SEGUROS | TJ71: 1086478942 | TM71: 45341 | TP71: 218.95 | TU71: =+TQ71-TS71-TU71 | TW71: SEGUROS | TX71: RIMAC SEGUROS | TZ71: 1086478942 | UC71: 45341 | UF71: 218.95 | UK71: =+UG71-UI71-UK71 | UM71: SEGUROS | UN71: RIMAC SEGUROS | UP71: 1086478942 | US71: 45341 | UV71: 218.95 | VA71: =+UW71-UY71-VA71 | VC71: SEGUROS | VD71: RIMAC SEGUROS | VF71: 1086478942 | VI71: 45341 | VL71: 218.95 | VQ71: =+VM71-VO71-VQ71 | VS71: SEGUROS | VT71: RIMAC SEGUROS | VV71: 1086478942 | VY71: 45341 | WB71: 218.95 | WG71: =+WC71-WE71-WG71 | WI71: SEGUROS | WJ71: RIMAC SEGUROS | WL71: 1086478942 | WO71: 45341 | WR71: 218.95 | WW71: =+WS71-WU71-WW71 | WY71: SEGUROS | WZ71: RIMAC SEGUROS | XB71: 1086478942 | XE71: 45341 | XH71: 218.95 | XM71: =+XI71-XK71-XM71 | XO71: SEGUROS | XP71: RIMAC SEGUROS | XR71: 1086478942 | XU71: 45341 | XX71: 218.95 | YC71: =+XY71-YA71-YC71 | YE71: SEGUROS | YF71: RIMAC SEGUROS | YH71: 1086478942 | YK71: 45341 | YN71: 218.95 | YS71: =+YO71-YQ71-YS71 | YU71: SEGUROS | YV71: RIMAC SEGUROS | YX71: 1086478942 | ZA71: 45341 | ZD71: 218.95 | ZI71: =+ZE71-ZG71-ZI71 | ZK71: SEGUROS | ZL71: RIMAC SEGUROS | ZN71: 1086478942 | ZQ71: 45341 | ZT71: 218.95 | ZY71: =+ZU71-ZW71-ZY71 | AAA71: SEGUROS | AAB71: RIMAC SEGUROS | AAD71: 1086478942 | AAG71: 45341 | AAJ71: 218.95 | AAO71: =+AAK71-AAM71-AAO71 | AAQ71: SEGUROS | AAR71: RIMAC SEGUROS | AAT71: 1086478942 | AAW71: 45341 | AAZ71: 218.95 | ABE71: =+ABA71-ABC71-ABE71 | ABG71: SEGUROS | ABH71: RIMAC SEGUROS | ABJ71: 1086478942 | ABM71: 45341 | ABP71: 218.95 | ABU71: =+ABQ71-ABS71-ABU71 | ABW71: SEGUROS | ABX71: RIMAC SEGUROS | ABZ71: 1086478942 | ACC71: 45341 | ACF71: 218.95 | ACK71: =+ACG71-ACI71-ACK71 | ACM71: SEGUROS | ACN71: RIMAC SEGUROS | ACP71: 1086478942 | ACS71: 45341 | ACV71: 218.95 | ADA71: =+ACW71-ACY71-ADA71 | ADC71: SEGUROS | ADD71: RIMAC SEGUROS | ADF71: 1086478942 | ADI71: 45341 | ADL71: 218.95 | ADQ71: =+ADM71-ADO71-ADQ71 | ADS71: SEGUROS | ADT71: RIMAC SEGUROS | ADV71: 1086478942 | ADY71: 45341 | AEB71: 218.95 | AEG71: =+AEC71-AEE71-AEG71 | AEI71: SEGUROS | AEJ71: RIMAC SEGUROS | AEL71: 1086478942 | AEO71: 45341 | AER71: 218.95 | AEW71: =+AES71-AEU71-AEW71 | AEY71: SEGUROS | AEZ71: RIMAC SEGUROS | AFB71: 1086478942 | AFE71: 45341 | AFH71: 218.95 | AFM71: =+AFI71-AFK71-AFM71 | AFO71: SEGUROS | AFP71: RIMAC SEGUROS | AFR71: 1086478942 | AFU71: 45341 | AFX71: 218.95 | AGC71: =+AFY71-AGA71-AGC71 | AGE71: SEGUROS | AGF71: RIMAC SEGUROS | AGH71: 1086478942 | AGK71: 45341 | AGN71: 218.95 | AGS71: =+AGO71-AGQ71-AGS71 | AGU71: SEGUROS | AGV71: RIMAC SEGUROS | AGX71: 1086478942 | AHA71: 45341 | AHD71: 218.95 | AHI71: =+AHE71-AHG71-AHI71 | AHK71: SEGUROS | AHL71: RIMAC SEGUROS | AHN71: 1086478942 | AHQ71: 45341 | AHT71: 218.95 | AHY71: =+AHU71-AHW71-AHY71 | AIA71: SEGUROS | AIB71: RIMAC SEGUROS | AID71: 1086478942 | AIG71: 45341 | AIJ71: 218.95 | AIO71: =+AIK71-AIM71-AIO71 | AIQ71: SEGUROS | AIR71: RIMAC SEGUROS | AIT71: 1086478942 | AIW71: 45341 | AIZ71: 218.95 | AJE71: =+AJA71-AJC71-AJE71 | AJG71: SEGUROS | AJH71: RIMAC SEGUROS | AJJ71: 1086478942 | AJM71: 45341 | AJP71: 218.95 | AJU71: =+AJQ71-AJS71-AJU71 | AJW71: SEGUROS | AJX71: RIMAC SEGUROS | AJZ71: 1086478942 | AKC71: 45341 | AKF71: 218.95 | AKK71: =+AKG71-AKI71-AKK71 | AKM71: SEGUROS | AKN71: RIMAC SEGUROS | AKP71: 1086478942 | AKS71: 45341 | AKV71: 218.95 | ALA71: =+AKW71-AKY71-ALA71 | ALC71: SEGUROS | ALD71: RIMAC SEGUROS | ALF71: 1086478942 | ALI71: 45341 | ALL71: 218.95 | ALQ71: =+ALM71-ALO71-ALQ71 | ALS71: SEGUROS | ALT71: RIMAC SEGUROS | ALV71: 1086478942 | ALY71: 45341 | AMB71: 218.95 | AMG71: =+AMC71-AME71-AMG71 | AMI71: SEGUROS | AMJ71: RIMAC SEGUROS | AML71: 1086478942 | AMO71: 45341 | AMR71: 218.95 | AMW71: =+AMS71-AMU71-AMW71 | AMY71: SEGUROS | AMZ71: RIMAC SEGUROS | ANB71: 1086478942 | ANE71: 45341 | ANH71: 218.95 | ANM71: =+ANI71-ANK71-ANM71 | ANO71: SEGUROS | ANP71: RIMAC SEGUROS | ANR71: 1086478942 | ANU71: 45341 | ANX71: 218.95 | AOC71: =+ANY71-AOA71-AOC71 | AOE71: SEGUROS | AOF71: RIMAC SEGUROS | AOH71: 1086478942 | AOK71: 45341 | AON71: 218.95 | AOS71: =+AOO71-AOQ71-AOS71 | AOU71: SEGUROS | AOV71: RIMAC SEGUROS | AOX71: 1086478942 | APA71: 45341 | APD71: 218.95 | API71: =+APE71-APG71-API71 | APK71: SEGUROS | APL71: RIMAC SEGUROS | APN71: 1086478942 | APQ71: 45341 | APT71: 218.95 | APY71: =+APU71-APW71-APY71 | AQA71: SEGUROS | AQB71: RIMAC SEGUROS | AQD71: 1086478942 | AQG71: 45341 | AQJ71: 218.95 | AQO71: =+AQK71-AQM71-AQO71 | AQQ71: SEGUROS | AQR71: RIMAC SEGUROS | AQT71: 1086478942 | AQW71: 45341 | AQZ71: 218.95 | ARE71: =+ARA71-ARC71-ARE71 | ARG71: SEGUROS | ARH71: RIMAC SEGUROS | ARJ71: 1086478942 | ARM71: 45341 | ARP71: 218.95 | ARU71: =+ARQ71-ARS71-ARU71 | ARW71: SEGUROS | ARX71: RIMAC SEGUROS | ARZ71: 1086478942 | ASC71: 45341 | ASF71: 218.95 | ASK71: =+ASG71-ASI71-ASK71 | ASM71: SEGUROS | ASN71: RIMAC SEGUROS | ASP71: 1086478942 | ASS71: 45341 | ASV71: 218.95 | ATA71: =+ASW71-ASY71-ATA71 | ATC71: SEGUROS | ATD71: RIMAC SEGUROS | ATF71: 1086478942 | ATI71: 45341 | ATL71: 218.95 | ATQ71: =+ATM71-ATO71-ATQ71 | ATS71: SEGUROS | ATT71: RIMAC SEGUROS | ATV71: 1086478942 | ATY71: 45341 | AUB71: 218.95 | AUG71: =+AUC71-AUE71-AUG71 | AUI71: SEGUROS | AUJ71: RIMAC SEGUROS | AUL71: 1086478942 | AUO71: 45341 | AUR71: 218.95 | AUW71: =+AUS71-AUU71-AUW71 | AUY71: SEGUROS | AUZ71: RIMAC SEGUROS | AVB71: 1086478942 | AVE71: 45341 | AVH71: 218.95 | AVM71: =+AVI71-AVK71-AVM71 | AVO71: SEGUROS | AVP71: RIMAC SEGUROS | AVR71: 1086478942 | AVU71: 45341 | AVX71: 218.95 | AWC71: =+AVY71-AWA71-AWC71 | AWE71: SEGUROS | AWF71: RIMAC SEGUROS | AWH71: 1086478942 | AWK71: 45341 | AWN71: 218.95 | AWS71: =+AWO71-AWQ71-AWS71 | AWU71: SEGUROS | AWV71: RIMAC SEGUROS | AWX71: 1086478942 | AXA71: 45341 | AXD71: 218.95 | AXI71: =+AXE71-AXG71-AXI71 | AXK71: SEGUROS | AXL71: RIMAC SEGUROS | AXN71: 1086478942 | AXQ71: 45341 | AXT71: 218.95 | AXY71: =+AXU71-AXW71-AXY71 | AYA71: SEGUROS | AYB71: RIMAC SEGUROS | AYD71: 1086478942 | AYG71: 45341 | AYJ71: 218.95 | AYO71: =+AYK71-AYM71-AYO71 | AYQ71: SEGUROS | AYR71: RIMAC SEGUROS | AYT71: 1086478942 | AYW71: 45341 | AYZ71: 218.95 | AZE71: =+AZA71-AZC71-AZE71 | AZG71: SEGUROS | AZH71: RIMAC SEGUROS | AZJ71: 1086478942 | AZM71: 45341 | AZP71: 218.95 | AZU71: =+AZQ71-AZS71-AZU71 | AZW71: SEGUROS | AZX71: RIMAC SEGUROS | AZZ71: 1086478942 | BAC71: 45341 | BAF71: 218.95 | BAK71: =+BAG71-BAI71-BAK71 | BAM71: SEGUROS | BAN71: RIMAC SEGUROS | BAP71: 1086478942 | BAS71: 45341 | BAV71: 218.95 | BBA71: =+BAW71-BAY71-BBA71 | BBC71: SEGUROS | BBD71: RIMAC SEGUROS | BBF71: 1086478942 | BBI71: 45341 | BBL71: 218.95 | BBQ71: =+BBM71-BBO71-BBQ71 | BBS71: SEGUROS | BBT71: RIMAC SEGUROS | BBV71: 1086478942 | BBY71: 45341 | BCB71: 218.95 | BCG71: =+BCC71-BCE71-BCG71 | BCI71: SEGUROS | BCJ71: RIMAC SEGUROS | BCL71: 1086478942 | BCO71: 45341 | BCR71: 218.95 | BCW71: =+BCS71-BCU71-BCW71 | BCY71: SEGUROS | BCZ71: RIMAC SEGUROS | BDB71: 1086478942 | BDE71: 45341 | BDH71: 218.95 | BDM71: =+BDI71-BDK71-BDM71 | BDO71: SEGUROS | BDP71: RIMAC SEGUROS | BDR71: 1086478942 | BDU71: 45341 | BDX71: 218.95 | BEC71: =+BDY71-BEA71-BEC71 | BEE71: SEGUROS | BEF71: RIMAC SEGUROS | BEH71: 1086478942 | BEK71: 45341 | BEN71: 218.95 | BES71: =+BEO71-BEQ71-BES71 | BEU71: SEGUROS | BEV71: RIMAC SEGUROS | BEX71: 1086478942 | BFA71: 45341 | BFD71: 218.95 | BFI71: =+BFE71-BFG71-BFI71 | BFK71: SEGUROS | BFL71: RIMAC SEGUROS | BFN71: 1086478942 | BFQ71: 45341 | BFT71: 218.95 | BFY71: =+BFU71-BFW71-BFY71 | BGA71: SEGUROS | BGB71: RIMAC SEGUROS | BGD71: 1086478942 | BGG71: 45341 | BGJ71: 218.95 | BGO71: =+BGK71-BGM71-BGO71 | BGQ71: SEGUROS | BGR71: RIMAC SEGUROS | BGT71: 1086478942 | BGW71: 45341 | BGZ71: 218.95 | BHE71: =+BHA71-BHC71-BHE71 | BHG71: SEGUROS | BHH71: RIMAC SEGUROS | BHJ71: 1086478942 | BHM71: 45341 | BHP71: 218.95 | BHU71: =+BHQ71-BHS71-BHU71 | BHW71: SEGUROS | BHX71: RIMAC SEGUROS | BHZ71: 1086478942 | BIC71: 45341 | BIF71: 218.95 | BIK71: =+BIG71-BII71-BIK71 | BIM71: SEGUROS | BIN71: RIMAC SEGUROS | BIP71: 1086478942 | BIS71: 45341 | BIV71: 218.95 | BJA71: =+BIW71-BIY71-BJA71 | BJC71: SEGUROS | BJD71: RIMAC SEGUROS | BJF71: 1086478942 | BJI71: 45341 | BJL71: 218.95 | BJQ71: =+BJM71-BJO71-BJQ71 | BJS71: SEGUROS | BJT71: RIMAC SEGUROS | BJV71: 1086478942 | BJY71: 45341 | BKB71: 218.95 | BKG71: =+BKC71-BKE71-BKG71 | BKI71: SEGUROS | BKJ71: RIMAC SEGUROS | BKL71: 1086478942 | BKO71: 45341 | BKR71: 218.95 | BKW71: =+BKS71-BKU71-BKW71 | BKY71: SEGUROS | BKZ71: RIMAC SEGUROS | BLB71: 1086478942 | BLE71: 45341 | BLH71: 218.95 | BLM71: =+BLI71-BLK71-BLM71 | BLO71: SEGUROS | BLP71: RIMAC SEGUROS | BLR71: 1086478942 | BLU71: 45341 | BLX71: 218.95 | BMC71: =+BLY71-BMA71-BMC71 | BME71: SEGUROS | BMF71: RIMAC SEGUROS | BMH71: 1086478942 | BMK71: 45341 | BMN71: 218.95 | BMS71: =+BMO71-BMQ71-BMS71 | BMU71: SEGUROS | BMV71: RIMAC SEGUROS | BMX71: 1086478942 | BNA71: 45341 | BND71: 218.95 | BNI71: =+BNE71-BNG71-BNI71 | BNK71: SEGUROS | BNL71: RIMAC SEGUROS | BNN71: 1086478942 | BNQ71: 45341 | BNT71: 218.95 | BNY71: =+BNU71-BNW71-BNY71 | BOA71: SEGUROS | BOB71: RIMAC SEGUROS | BOD71: 1086478942 | BOG71: 45341 | BOJ71: 218.95 | BOO71: =+BOK71-BOM71-BOO71 | BOQ71: SEGUROS | BOR71: RIMAC SEGUROS | BOT71: 1086478942 | BOW71: 45341 | BOZ71: 218.95 | BPE71: =+BPA71-BPC71-BPE71 | BPG71: SEGUROS | BPH71: RIMAC SEGUROS | BPJ71: 1086478942 | BPM71: 45341 | BPP71: 218.95 | BPU71: =+BPQ71-BPS71-BPU71 | BPW71: SEGUROS | BPX71: RIMAC SEGUROS | BPZ71: 1086478942 | BQC71: 45341 | BQF71: 218.95 | BQK71: =+BQG71-BQI71-BQK71 | BQM71: SEGUROS | BQN71: RIMAC SEGUROS | BQP71: 1086478942 | BQS71: 45341 | BQV71: 218.95 | BRA71: =+BQW71-BQY71-BRA71 | BRC71: SEGUROS | BRD71: RIMAC SEGUROS | BRF71: 1086478942 | BRI71: 45341 | BRL71: 218.95 | BRQ71: =+BRM71-BRO71-BRQ71 | BRS71: SEGUROS | BRT71: RIMAC SEGUROS | BRV71: 1086478942 | BRY71: 45341 | BSB71: 218.95 | BSG71: =+BSC71-BSE71-BSG71 | BSI71: SEGUROS | BSJ71: RIMAC SEGUROS | BSL71: 1086478942 | BSO71: 45341 | BSR71: 218.95 | BSW71: =+BSS71-BSU71-BSW71 | BSY71: SEGUROS | BSZ71: RIMAC SEGUROS | BTB71: 1086478942 | BTE71: 45341 | BTH71: 218.95 | BTM71: =+BTI71-BTK71-BTM71 | BTO71: SEGUROS | BTP71: RIMAC SEGUROS | BTR71: 1086478942 | BTU71: 45341 | BTX71: 218.95 | BUC71: =+BTY71-BUA71-BUC71 | BUE71: SEGUROS | BUF71: RIMAC SEGUROS | BUH71: 1086478942 | BUK71: 45341 | BUN71: 218.95 | BUS71: =+BUO71-BUQ71-BUS71 | BUU71: SEGUROS | BUV71: RIMAC SEGUROS | BUX71: 1086478942 | BVA71: 45341 | BVD71: 218.95 | BVI71: =+BVE71-BVG71-BVI71 | BVK71: SEGUROS | BVL71: RIMAC SEGUROS | BVN71: 1086478942 | BVQ71: 45341 | BVT71: 218.95 | BVY71: =+BVU71-BVW71-BVY71 | BWA71: SEGUROS | BWB71: RIMAC SEGUROS | BWD71: 1086478942 | BWG71: 45341 | BWJ71: 218.95 | BWO71: =+BWK71-BWM71-BWO71 | BWQ71: SEGUROS | BWR71: RIMAC SEGUROS | BWT71: 1086478942 | BWW71: 45341 | BWZ71: 218.95 | BXE71: =+BXA71-BXC71-BXE71 | BXG71: SEGUROS | BXH71: RIMAC SEGUROS | BXJ71: 1086478942 | BXM71: 45341 | BXP71: 218.95 | BXU71: =+BXQ71-BXS71-BXU71 | BXW71: SEGUROS | BXX71: RIMAC SEGUROS | BXZ71: 1086478942 | BYC71: 45341 | BYF71: 218.95 | BYK71: =+BYG71-BYI71-BYK71 | BYM71: SEGUROS | BYN71: RIMAC SEGUROS | BYP71: 1086478942 | BYS71: 45341 | BYV71: 218.95 | BZA71: =+BYW71-BYY71-BZA71 | BZC71: SEGUROS | BZD71: RIMAC SEGUROS | BZF71: 1086478942 | BZI71: 45341 | BZL71: 218.95 | BZQ71: =+BZM71-BZO71-BZQ71 | BZS71: SEGUROS | BZT71: RIMAC SEGUROS | BZV71: 1086478942 | BZY71: 45341 | CAB71: 218.95 | CAG71: =+CAC71-CAE71-CAG71 | CAI71: SEGUROS | CAJ71: RIMAC SEGUROS | CAL71: 1086478942 | CAO71: 45341 | CAR71: 218.95 | CAW71: =+CAS71-CAU71-CAW71 | CAY71: SEGUROS | CAZ71: RIMAC SEGUROS | CBB71: 1086478942 | CBE71: 45341 | CBH71: 218.95 | CBM71: =+CBI71-CBK71-CBM71 | CBO71: SEGUROS | CBP71: RIMAC SEGUROS | CBR71: 1086478942 | CBU71: 45341 | CBX71: 218.95 | CCC71: =+CBY71-CCA71-CCC71 | CCE71: SEGUROS | CCF71: RIMAC SEGUROS | CCH71: 1086478942 | CCK71: 45341 | CCN71: 218.95 | CCS71: =+CCO71-CCQ71-CCS71 | CCU71: SEGUROS | CCV71: RIMAC SEGUROS | CCX71: 1086478942 | CDA71: 45341 | CDD71: 218.95 | CDI71: =+CDE71-CDG71-CDI71 | CDK71: SEGUROS | CDL71: RIMAC SEGUROS | CDN71: 1086478942 | CDQ71: 45341 | CDT71: 218.95 | CDY71: =+CDU71-CDW71-CDY71 | CEA71: SEGUROS | CEB71: RIMAC SEGUROS | CED71: 1086478942 | CEG71: 45341 | CEJ71: 218.95 | CEO71: =+CEK71-CEM71-CEO71 | CEQ71: SEGUROS | CER71: RIMAC SEGUROS | CET71: 1086478942 | CEW71: 45341 | CEZ71: 218.95 | CFE71: =+CFA71-CFC71-CFE71 | CFG71: SEGUROS | CFH71: RIMAC SEGUROS | CFJ71: 1086478942 | CFM71: 45341 | CFP71: 218.95 | CFU71: =+CFQ71-CFS71-CFU71 | CFW71: SEGUROS | CFX71: RIMAC SEGUROS | CFZ71: 1086478942 | CGC71: 45341 | CGF71: 218.95 | CGK71: =+CGG71-CGI71-CGK71 | CGM71: SEGUROS | CGN71: RIMAC SEGUROS | CGP71: 1086478942 | CGS71: 45341 | CGV71: 218.95 | CHA71: =+CGW71-CGY71-CHA71 | CHC71: SEGUROS | CHD71: RIMAC SEGUROS | CHF71: 1086478942 | CHI71: 45341 | CHL71: 218.95 | CHQ71: =+CHM71-CHO71-CHQ71 | CHS71: SEGUROS | CHT71: RIMAC SEGUROS | CHV71: 1086478942 | CHY71: 45341 | CIB71: 218.95 | CIG71: =+CIC71-CIE71-CIG71 | CII71: SEGUROS | CIJ71: RIMAC SEGUROS | CIL71: 1086478942 | CIO71: 45341 | CIR71: 218.95 | CIW71: =+CIS71-CIU71-CIW71 | CIY71: SEGUROS | CIZ71: RIMAC SEGUROS | CJB71: 1086478942 | CJE71: 45341 | CJH71: 218.95 | CJM71: =+CJI71-CJK71-CJM71 | CJO71: SEGUROS | CJP71: RIMAC SEGUROS | CJR71: 1086478942 | CJU71: 45341 | CJX71: 218.95 | CKC71: =+CJY71-CKA71-CKC71 | CKE71: SEGUROS | CKF71: RIMAC SEGUROS | CKH71: 1086478942 | CKK71: 45341 | CKN71: 218.95 | CKS71: =+CKO71-CKQ71-CKS71 | CKU71: SEGUROS | CKV71: RIMAC SEGUROS | CKX71: 1086478942 | CLA71: 45341 | CLD71: 218.95 | CLI71: =+CLE71-CLG71-CLI71 | CLK71: SEGUROS | CLL71: RIMAC SEGUROS | CLN71: 1086478942 | CLQ71: 45341 | CLT71: 218.95 | CLY71: =+CLU71-CLW71-CLY71 | CMA71: SEGUROS | CMB71: RIMAC SEGUROS | CMD71: 1086478942 | CMG71: 45341 | CMJ71: 218.95 | CMO71: =+CMK71-CMM71-CMO71 | CMQ71: SEGUROS | CMR71: RIMAC SEGUROS | CMT71: 1086478942 | CMW71: 45341 | CMZ71: 218.95 | CNE71: =+CNA71-CNC71-CNE71 | CNG71: SEGUROS | CNH71: RIMAC SEGUROS | CNJ71: 1086478942 | CNM71: 45341 | CNP71: 218.95 | CNU71: =+CNQ71-CNS71-CNU71 | CNW71: SEGUROS | CNX71: RIMAC SEGUROS | CNZ71: 1086478942 | COC71: 45341 | COF71: 218.95 | COK71: =+COG71-COI71-COK71 | COM71: SEGUROS | CON71: RIMAC SEGUROS | COP71: 1086478942 | COS71: 45341 | COV71: 218.95 | CPA71: =+COW71-COY71-CPA71 | CPC71: SEGUROS | CPD71: RIMAC SEGUROS | CPF71: 1086478942 | CPI71: 45341 | CPL71: 218.95 | CPQ71: =+CPM71-CPO71-CPQ71 | CPS71: SEGUROS | CPT71: RIMAC SEGUROS | CPV71: 1086478942 | CPY71: 45341 | CQB71: 218.95 | CQG71: =+CQC71-CQE71-CQG71 | CQI71: SEGUROS | CQJ71: RIMAC SEGUROS | CQL71: 1086478942 | CQO71: 45341 | CQR71: 218.95 | CQW71: =+CQS71-CQU71-CQW71 | CQY71: SEGUROS | CQZ71: RIMAC SEGUROS | CRB71: 1086478942 | CRE71: 45341 | CRH71: 218.95 | CRM71: =+CRI71-CRK71-CRM71 | CRO71: SEGUROS | CRP71: RIMAC SEGUROS | CRR71: 1086478942 | CRU71: 45341 | CRX71: 218.95 | CSC71: =+CRY71-CSA71-CSC71 | CSE71: SEGUROS | CSF71: RIMAC SEGUROS | CSH71: 1086478942 | CSK71: 45341 | CSN71: 218.95 | CSS71: =+CSO71-CSQ71-CSS71 | CSU71: SEGUROS | CSV71: RIMAC SEGUROS | CSX71: 1086478942 | CTA71: 45341 | CTD71: 218.95 | CTI71: =+CTE71-CTG71-CTI71 | CTK71: SEGUROS | CTL71: RIMAC SEGUROS | CTN71: 1086478942 | CTQ71: 45341 | CTT71: 218.95 | CTY71: =+CTU71-CTW71-CTY71 | CUA71: SEGUROS | CUB71: RIMAC SEGUROS | CUD71: 1086478942 | CUG71: 45341 | CUJ71: 218.95 | CUO71: =+CUK71-CUM71-CUO71 | CUQ71: SEGUROS | CUR71: RIMAC SEGUROS | CUT71: 1086478942 | CUW71: 45341 | CUZ71: 218.95 | CVE71: =+CVA71-CVC71-CVE71 | CVG71: SEGUROS | CVH71: RIMAC SEGUROS | CVJ71: 1086478942 | CVM71: 45341 | CVP71: 218.95 | CVU71: =+CVQ71-CVS71-CVU71 | CVW71: SEGUROS | CVX71: RIMAC SEGUROS | CVZ71: 1086478942 | CWC71: 45341 | CWF71: 218.95 | CWK71: =+CWG71-CWI71-CWK71 | CWM71: SEGUROS | CWN71: RIMAC SEGUROS | CWP71: 1086478942 | CWS71: 45341 | CWV71: 218.95 | CXA71: =+CWW71-CWY71-CXA71 | CXC71: SEGUROS | CXD71: RIMAC SEGUROS | CXF71: 1086478942 | CXI71: 45341 | CXL71: 218.95 | CXQ71: =+CXM71-CXO71-CXQ71 | CXS71: SEGUROS | CXT71: RIMAC SEGUROS | CXV71: 1086478942 | CXY71: 45341 | CYB71: 218.95 | CYG71: =+CYC71-CYE71-CYG71 | CYI71: SEGUROS | CYJ71: RIMAC SEGUROS | CYL71: 1086478942 | CYO71: 45341 | CYR71: 218.95 | CYW71: =+CYS71-CYU71-CYW71 | CYY71: SEGUROS | CYZ71: RIMAC SEGUROS | CZB71: 1086478942 | CZE71: 45341 | CZH71: 218.95 | CZM71: =+CZI71-CZK71-CZM71 | CZO71: SEGUROS | CZP71: RIMAC SEGUROS | CZR71: 1086478942 | CZU71: 45341 | CZX71: 218.95 | DAC71: =+CZY71-DAA71-DAC71 | DAE71: SEGUROS | DAF71: RIMAC SEGUROS | DAH71: 1086478942 | DAK71: 45341 | DAN71: 218.95 | DAS71: =+DAO71-DAQ71-DAS71 | DAU71: SEGUROS | DAV71: RIMAC SEGUROS | DAX71: 1086478942 | DBA71: 45341 | DBD71: 218.95 | DBI71: =+DBE71-DBG71-DBI71 | DBK71: SEGUROS | DBL71: RIMAC SEGUROS | DBN71: 1086478942 | DBQ71: 45341 | DBT71: 218.95 | DBY71: =+DBU71-DBW71-DBY71 | DCA71: SEGUROS | DCB71: RIMAC SEGUROS | DCD71: 1086478942 | DCG71: 45341 | DCJ71: 218.95 | DCO71: =+DCK71-DCM71-DCO71 | DCQ71: SEGUROS | DCR71: RIMAC SEGUROS | DCT71: 1086478942 | DCW71: 45341 | DCZ71: 218.95 | DDE71: =+DDA71-DDC71-DDE71 | DDG71: SEGUROS | DDH71: RIMAC SEGUROS | DDJ71: 1086478942 | DDM71: 45341 | DDP71: 218.95 | DDU71: =+DDQ71-DDS71-DDU71 | DDW71: SEGUROS | DDX71: RIMAC SEGUROS | DDZ71: 1086478942 | DEC71: 45341 | DEF71: 218.95 | DEK71: =+DEG71-DEI71-DEK71 | DEM71: SEGUROS | DEN71: RIMAC SEGUROS | DEP71: 1086478942 | DES71: 45341 | DEV71: 218.95 | DFA71: =+DEW71-DEY71-DFA71 | DFC71: SEGUROS | DFD71: RIMAC SEGUROS | DFF71: 1086478942 | DFI71: 45341 | DFL71: 218.95 | DFQ71: =+DFM71-DFO71-DFQ71 | DFS71: SEGUROS | DFT71: RIMAC SEGUROS | DFV71: 1086478942 | DFY71: 45341 | DGB71: 218.95 | DGG71: =+DGC71-DGE71-DGG71 | DGI71: SEGUROS | DGJ71: RIMAC SEGUROS | DGL71: 1086478942 | DGO71: 45341 | DGR71: 218.95 | DGW71: =+DGS71-DGU71-DGW71 | DGY71: SEGUROS | DGZ71: RIMAC SEGUROS | DHB71: 1086478942 | DHE71: 45341 | DHH71: 218.95 | DHM71: =+DHI71-DHK71-DHM71 | DHO71: SEGUROS | DHP71: RIMAC SEGUROS | DHR71: 1086478942 | DHU71: 45341 | DHX71: 218.95 | DIC71: =+DHY71-DIA71-DIC71 | DIE71: SEGUROS | DIF71: RIMAC SEGUROS | DIH71: 1086478942 | DIK71: 45341 | DIN71: 218.95 | DIS71: =+DIO71-DIQ71-DIS71 | DIU71: SEGUROS | DIV71: RIMAC SEGUROS | DIX71: 1086478942 | DJA71: 45341 | DJD71: 218.95 | DJI71: =+DJE71-DJG71-DJI71 | DJK71: SEGUROS | DJL71: RIMAC SEGUROS | DJN71: 1086478942 | DJQ71: 45341 | DJT71: 218.95 | DJY71: =+DJU71-DJW71-DJY71 | DKA71: SEGUROS | DKB71: RIMAC SEGUROS | DKD71: 1086478942 | DKG71: 45341 | DKJ71: 218.95 | DKO71: =+DKK71-DKM71-DKO71 | DKQ71: SEGUROS | DKR71: RIMAC SEGUROS | DKT71: 1086478942 | DKW71: 45341 | DKZ71: 218.95 | DLE71: =+DLA71-DLC71-DLE71 | DLG71: SEGUROS | DLH71: RIMAC SEGUROS | DLJ71: 1086478942 | DLM71: 45341 | DLP71: 218.95 | DLU71: =+DLQ71-DLS71-DLU71 | DLW71: SEGUROS | DLX71: RIMAC SEGUROS | DLZ71: 1086478942 | DMC71: 45341 | DMF71: 218.95 | DMK71: =+DMG71-DMI71-DMK71 | DMM71: SEGUROS | DMN71: RIMAC SEGUROS | DMP71: 1086478942 | DMS71: 45341 | DMV71: 218.95 | DNA71: =+DMW71-DMY71-DNA71 | DNC71: SEGUROS | DND71: RIMAC SEGUROS | DNF71: 1086478942 | DNI71: 45341 | DNL71: 218.95 | DNQ71: =+DNM71-DNO71-DNQ71 | DNS71: SEGUROS | DNT71: RIMAC SEGUROS | DNV71: 1086478942 | DNY71: 45341 | DOB71: 218.95 | DOG71: =+DOC71-DOE71-DOG71 | DOI71: SEGUROS | DOJ71: RIMAC SEGUROS | DOL71: 1086478942 | DOO71: 45341 | DOR71: 218.95 | DOW71: =+DOS71-DOU71-DOW71 | DOY71: SEGUROS | DOZ71: RIMAC SEGUROS | DPB71: 1086478942 | DPE71: 45341 | DPH71: 218.95 | DPM71: =+DPI71-DPK71-DPM71 | DPO71: SEGUROS | DPP71: RIMAC SEGUROS | DPR71: 1086478942 | DPU71: 45341 | DPX71: 218.95 | DQC71: =+DPY71-DQA71-DQC71 | DQE71: SEGUROS | DQF71: RIMAC SEGUROS | DQH71: 1086478942 | DQK71: 45341 | DQN71: 218.95 | DQS71: =+DQO71-DQQ71-DQS71 | DQU71: SEGUROS | DQV71: RIMAC SEGUROS | DQX71: 1086478942 | DRA71: 45341 | DRD71: 218.95 | DRI71: =+DRE71-DRG71-DRI71 | DRK71: SEGUROS | DRL71: RIMAC SEGUROS | DRN71: 1086478942 | DRQ71: 45341 | DRT71: 218.95 | DRY71: =+DRU71-DRW71-DRY71 | DSA71: SEGUROS | DSB71: RIMAC SEGUROS | DSD71: 1086478942 | DSG71: 45341 | DSJ71: 218.95 | DSO71: =+DSK71-DSM71-DSO71 | DSQ71: SEGUROS | DSR71: RIMAC SEGUROS | DST71: 1086478942 | DSW71: 45341 | DSZ71: 218.95 | DTE71: =+DTA71-DTC71-DTE71 | DTG71: SEGUROS | DTH71: RIMAC SEGUROS | DTJ71: 1086478942 | DTM71: 45341 | DTP71: 218.95 | DTU71: =+DTQ71-DTS71-DTU71 | DTW71: SEGUROS | DTX71: RIMAC SEGUROS | DTZ71: 1086478942 | DUC71: 45341 | DUF71: 218.95 | DUK71: =+DUG71-DUI71-DUK71 | DUM71: SEGUROS | DUN71: RIMAC SEGUROS | DUP71: 1086478942 | DUS71: 45341 | DUV71: 218.95 | DVA71: =+DUW71-DUY71-DVA71 | DVC71: SEGUROS | DVD71: RIMAC SEGUROS | DVF71: 1086478942 | DVI71: 45341 | DVL71: 218.95 | DVQ71: =+DVM71-DVO71-DVQ71 | DVS71: SEGUROS | DVT71: RIMAC SEGUROS | DVV71: 1086478942 | DVY71: 45341 | DWB71: 218.95 | DWG71: =+DWC71-DWE71-DWG71 | DWI71: SEGUROS | DWJ71: RIMAC SEGUROS | DWL71: 1086478942 | DWO71: 45341 | DWR71: 218.95 | DWW71: =+DWS71-DWU71-DWW71 | DWY71: SEGUROS | DWZ71: RIMAC SEGUROS | DXB71: 1086478942 | DXE71: 45341 | DXH71: 218.95 | DXM71: =+DXI71-DXK71-DXM71 | DXO71: SEGUROS | DXP71: RIMAC SEGUROS | DXR71: 1086478942 | DXU71: 45341 | DXX71: 218.95 | DYC71: =+DXY71-DYA71-DYC71 | DYE71: SEGUROS | DYF71: RIMAC SEGUROS | DYH71: 1086478942 | DYK71: 45341 | DYN71: 218.95 | DYS71: =+DYO71-DYQ71-DYS71 | DYU71: SEGUROS | DYV71: RIMAC SEGUROS | DYX71: 1086478942 | DZA71: 45341 | DZD71: 218.95 | DZI71: =+DZE71-DZG71-DZI71 | DZK71: SEGUROS | DZL71: RIMAC SEGUROS | DZN71: 1086478942 | DZQ71: 45341 | DZT71: 218.95 | DZY71: =+DZU71-DZW71-DZY71 | EAA71: SEGUROS | EAB71: RIMAC SEGUROS | EAD71: 1086478942 | EAG71: 45341 | EAJ71: 218.95 | EAO71: =+EAK71-EAM71-EAO71 | EAQ71: SEGUROS | EAR71: RIMAC SEGUROS | EAT71: 1086478942 | EAW71: 45341 | EAZ71: 218.95 | EBE71: =+EBA71-EBC71-EBE71 | EBG71: SEGUROS | EBH71: RIMAC SEGUROS | EBJ71: 1086478942 | EBM71: 45341 | EBP71: 218.95 | EBU71: =+EBQ71-EBS71-EBU71 | EBW71: SEGUROS | EBX71: RIMAC SEGUROS | EBZ71: 1086478942 | ECC71: 45341 | ECF71: 218.95 | ECK71: =+ECG71-ECI71-ECK71 | ECM71: SEGUROS | ECN71: RIMAC SEGUROS | ECP71: 1086478942 | ECS71: 45341 | ECV71: 218.95 | EDA71: =+ECW71-ECY71-EDA71 | EDC71: SEGUROS | EDD71: RIMAC SEGUROS | EDF71: 1086478942 | EDI71: 45341 | EDL71: 218.95 | EDQ71: =+EDM71-EDO71-EDQ71 | EDS71: SEGUROS | EDT71: RIMAC SEGUROS | EDV71: 1086478942 | EDY71: 45341 | EEB71: 218.95 | EEG71: =+EEC71-EEE71-EEG71 | EEI71: SEGUROS | EEJ71: RIMAC SEGUROS | EEL71: 1086478942 | EEO71: 45341 | EER71: 218.95 | EEW71: =+EES71-EEU71-EEW71 | EEY71: SEGUROS | EEZ71: RIMAC SEGUROS | EFB71: 1086478942 | EFE71: 45341 | EFH71: 218.95 | EFM71: =+EFI71-EFK71-EFM71 | EFO71: SEGUROS | EFP71: RIMAC SEGUROS | EFR71: 1086478942 | EFU71: 45341 | EFX71: 218.95 | EGC71: =+EFY71-EGA71-EGC71 | EGE71: SEGUROS | EGF71: RIMAC SEGUROS | EGH71: 1086478942 | EGK71: 45341 | EGN71: 218.95 | EGS71: =+EGO71-EGQ71-EGS71 | EGU71: SEGUROS | EGV71: RIMAC SEGUROS | EGX71: 1086478942 | EHA71: 45341 | EHD71: 218.95 | EHI71: =+EHE71-EHG71-EHI71 | EHK71: SEGUROS | EHL71: RIMAC SEGUROS | EHN71: 1086478942 | EHQ71: 45341 | EHT71: 218.95 | EHY71: =+EHU71-EHW71-EHY71 | EIA71: SEGUROS | EIB71: RIMAC SEGUROS | EID71: 1086478942 | EIG71: 45341 | EIJ71: 218.95 | EIO71: =+EIK71-EIM71-EIO71 | EIQ71: SEGUROS | EIR71: RIMAC SEGUROS | EIT71: 1086478942 | EIW71: 45341 | EIZ71: 218.95 | EJE71: =+EJA71-EJC71-EJE71 | EJG71: SEGUROS | EJH71: RIMAC SEGUROS | EJJ71: 1086478942 | EJM71: 45341 | EJP71: 218.95 | EJU71: =+EJQ71-EJS71-EJU71 | EJW71: SEGUROS | EJX71: RIMAC SEGUROS | EJZ71: 1086478942 | EKC71: 45341 | EKF71: 218.95 | EKK71: =+EKG71-EKI71-EKK71 | EKM71: SEGUROS | EKN71: RIMAC SEGUROS | EKP71: 1086478942 | EKS71: 45341 | EKV71: 218.95 | ELA71: =+EKW71-EKY71-ELA71 | ELC71: SEGUROS | ELD71: RIMAC SEGUROS | ELF71: 1086478942 | ELI71: 45341 | ELL71: 218.95 | ELQ71: =+ELM71-ELO71-ELQ71 | ELS71: SEGUROS | ELT71: RIMAC SEGUROS | ELV71: 1086478942 | ELY71: 45341 | EMB71: 218.95 | EMG71: =+EMC71-EME71-EMG71 | EMI71: SEGUROS | EMJ71: RIMAC SEGUROS | EML71: 1086478942 | EMO71: 45341 | EMR71: 218.95 | EMW71: =+EMS71-EMU71-EMW71 | EMY71: SEGUROS | EMZ71: RIMAC SEGUROS | ENB71: 1086478942 | ENE71: 45341 | ENH71: 218.95 | ENM71: =+ENI71-ENK71-ENM71 | ENO71: SEGUROS | ENP71: RIMAC SEGUROS | ENR71: 1086478942 | ENU71: 45341 | ENX71: 218.95 | EOC71: =+ENY71-EOA71-EOC71 | EOE71: SEGUROS | EOF71: RIMAC SEGUROS | EOH71: 1086478942 | EOK71: 45341 | EON71: 218.95 | EOS71: =+EOO71-EOQ71-EOS71 | EOU71: SEGUROS | EOV71: RIMAC SEGUROS | EOX71: 1086478942 | EPA71: 45341 | EPD71: 218.95 | EPI71: =+EPE71-EPG71-EPI71 | EPK71: SEGUROS | EPL71: RIMAC SEGUROS | EPN71: 1086478942 | EPQ71: 45341 | EPT71: 218.95 | EPY71: =+EPU71-EPW71-EPY71 | EQA71: SEGUROS | EQB71: RIMAC SEGUROS | EQD71: 1086478942 | EQG71: 45341 | EQJ71: 218.95 | EQO71: =+EQK71-EQM71-EQO71 | EQQ71: SEGUROS | EQR71: RIMAC SEGUROS | EQT71: 1086478942 | EQW71: 45341 | EQZ71: 218.95 | ERE71: =+ERA71-ERC71-ERE71 | ERG71: SEGUROS | ERH71: RIMAC SEGUROS | ERJ71: 1086478942 | ERM71: 45341 | ERP71: 218.95 | ERU71: =+ERQ71-ERS71-ERU71 | ERW71: SEGUROS | ERX71: RIMAC SEGUROS | ERZ71: 1086478942 | ESC71: 45341 | ESF71: 218.95 | ESK71: =+ESG71-ESI71-ESK71 | ESM71: SEGUROS | ESN71: RIMAC SEGUROS | ESP71: 1086478942 | ESS71: 45341 | ESV71: 218.95 | ETA71: =+ESW71-ESY71-ETA71 | ETC71: SEGUROS | ETD71: RIMAC SEGUROS | ETF71: 1086478942 | ETI71: 45341 | ETL71: 218.95 | ETQ71: =+ETM71-ETO71-ETQ71 | ETS71: SEGUROS | ETT71: RIMAC SEGUROS | ETV71: 1086478942 | ETY71: 45341 | EUB71: 218.95 | EUG71: =+EUC71-EUE71-EUG71 | EUI71: SEGUROS | EUJ71: RIMAC SEGUROS | EUL71: 1086478942 | EUO71: 45341 | EUR71: 218.95 | EUW71: =+EUS71-EUU71-EUW71 | EUY71: SEGUROS | EUZ71: RIMAC SEGUROS | EVB71: 1086478942 | EVE71: 45341 | EVH71: 218.95 | EVM71: =+EVI71-EVK71-EVM71 | EVO71: SEGUROS | EVP71: RIMAC SEGUROS | EVR71: 1086478942 | EVU71: 45341 | EVX71: 218.95 | EWC71: =+EVY71-EWA71-EWC71 | EWE71: SEGUROS | EWF71: RIMAC SEGUROS | EWH71: 1086478942 | EWK71: 45341 | EWN71: 218.95 | EWS71: =+EWO71-EWQ71-EWS71 | EWU71: SEGUROS | EWV71: RIMAC SEGUROS | EWX71: 1086478942 | EXA71: 45341 | EXD71: 218.95 | EXI71: =+EXE71-EXG71-EXI71 | EXK71: SEGUROS | EXL71: RIMAC SEGUROS | EXN71: 1086478942 | EXQ71: 45341 | EXT71: 218.95 | EXY71: =+EXU71-EXW71-EXY71 | EYA71: SEGUROS | EYB71: RIMAC SEGUROS | EYD71: 1086478942 | EYG71: 45341 | EYJ71: 218.95 | EYO71: =+EYK71-EYM71-EYO71 | EYQ71: SEGUROS | EYR71: RIMAC SEGUROS | EYT71: 1086478942 | EYW71: 45341 | EYZ71: 218.95 | EZE71: =+EZA71-EZC71-EZE71 | EZG71: SEGUROS | EZH71: RIMAC SEGUROS | EZJ71: 1086478942 | EZM71: 45341 | EZP71: 218.95 | EZU71: =+EZQ71-EZS71-EZU71 | EZW71: SEGUROS | EZX71: RIMAC SEGUROS | EZZ71: 1086478942 | FAC71: 45341 | FAF71: 218.95 | FAK71: =+FAG71-FAI71-FAK71 | FAM71: SEGUROS | FAN71: RIMAC SEGUROS | FAP71: 1086478942 | FAS71: 45341 | FAV71: 218.95 | FBA71: =+FAW71-FAY71-FBA71 | FBC71: SEGUROS | FBD71: RIMAC SEGUROS | FBF71: 1086478942 | FBI71: 45341 | FBL71: 218.95 | FBQ71: =+FBM71-FBO71-FBQ71 | FBS71: SEGUROS | FBT71: RIMAC SEGUROS | FBV71: 1086478942 | FBY71: 45341 | FCB71: 218.95 | FCG71: =+FCC71-FCE71-FCG71 | FCI71: SEGUROS | FCJ71: RIMAC SEGUROS | FCL71: 1086478942 | FCO71: 45341 | FCR71: 218.95 | FCW71: =+FCS71-FCU71-FCW71 | FCY71: SEGUROS | FCZ71: RIMAC SEGUROS | FDB71: 1086478942 | FDE71: 45341 | FDH71: 218.95 | FDM71: =+FDI71-FDK71-FDM71 | FDO71: SEGUROS | FDP71: RIMAC SEGUROS | FDR71: 1086478942 | FDU71: 45341 | FDX71: 218.95 | FEC71: =+FDY71-FEA71-FEC71 | FEE71: SEGUROS | FEF71: RIMAC SEGUROS | FEH71: 1086478942 | FEK71: 45341 | FEN71: 218.95 | FES71: =+FEO71-FEQ71-FES71 | FEU71: SEGUROS | FEV71: RIMAC SEGUROS | FEX71: 1086478942 | FFA71: 45341 | FFD71: 218.95 | FFI71: =+FFE71-FFG71-FFI71 | FFK71: SEGUROS | FFL71: RIMAC SEGUROS | FFN71: 1086478942 | FFQ71: 45341 | FFT71: 218.95 | FFY71: =+FFU71-FFW71-FFY71 | FGA71: SEGUROS | FGB71: RIMAC SEGUROS | FGD71: 1086478942 | FGG71: 45341 | FGJ71: 218.95 | FGO71: =+FGK71-FGM71-FGO71 | FGQ71: SEGUROS | FGR71: RIMAC SEGUROS | FGT71: 1086478942 | FGW71: 45341 | FGZ71: 218.95 | FHE71: =+FHA71-FHC71-FHE71 | FHG71: SEGUROS | FHH71: RIMAC SEGUROS | FHJ71: 1086478942 | FHM71: 45341 | FHP71: 218.95 | FHU71: =+FHQ71-FHS71-FHU71 | FHW71: SEGUROS | FHX71: RIMAC SEGUROS | FHZ71: 1086478942 | FIC71: 45341 | FIF71: 218.95 | FIK71: =+FIG71-FII71-FIK71 | FIM71: SEGUROS | FIN71: RIMAC SEGUROS | FIP71: 1086478942 | FIS71: 45341 | FIV71: 218.95 | FJA71: =+FIW71-FIY71-FJA71 | FJC71: SEGUROS | FJD71: RIMAC SEGUROS | FJF71: 1086478942 | FJI71: 45341 | FJL71: 218.95 | FJQ71: =+FJM71-FJO71-FJQ71 | FJS71: SEGUROS | FJT71: RIMAC SEGUROS | FJV71: 1086478942 | FJY71: 45341 | FKB71: 218.95 | FKG71: =+FKC71-FKE71-FKG71 | FKI71: SEGUROS | FKJ71: RIMAC SEGUROS | FKL71: 1086478942 | FKO71: 45341 | FKR71: 218.95 | FKW71: =+FKS71-FKU71-FKW71 | FKY71: SEGUROS | FKZ71: RIMAC SEGUROS | FLB71: 1086478942 | FLE71: 45341 | FLH71: 218.95 | FLM71: =+FLI71-FLK71-FLM71 | FLO71: SEGUROS | FLP71: RIMAC SEGUROS | FLR71: 1086478942 | FLU71: 45341 | FLX71: 218.95 | FMC71: =+FLY71-FMA71-FMC71 | FME71: SEGUROS | FMF71: RIMAC SEGUROS | FMH71: 1086478942 | FMK71: 45341 | FMN71: 218.95 | FMS71: =+FMO71-FMQ71-FMS71 | FMU71: SEGUROS | FMV71: RIMAC SEGUROS | FMX71: 1086478942 | FNA71: 45341 | FND71: 218.95 | FNI71: =+FNE71-FNG71-FNI71 | FNK71: SEGUROS | FNL71: RIMAC SEGUROS | FNN71: 1086478942 | FNQ71: 45341 | FNT71: 218.95 | FNY71: =+FNU71-FNW71-FNY71 | FOA71: SEGUROS | FOB71: RIMAC SEGUROS | FOD71: 1086478942 | FOG71: 45341 | FOJ71: 218.95 | FOO71: =+FOK71-FOM71-FOO71 | FOQ71: SEGUROS | FOR71: RIMAC SEGUROS | FOT71: 1086478942 | FOW71: 45341 | FOZ71: 218.95 | FPE71: =+FPA71-FPC71-FPE71 | FPG71: SEGUROS | FPH71: RIMAC SEGUROS | FPJ71: 1086478942 | FPM71: 45341 | FPP71: 218.95 | FPU71: =+FPQ71-FPS71-FPU71 | FPW71: SEGUROS | FPX71: RIMAC SEGUROS | FPZ71: 1086478942 | FQC71: 45341 | FQF71: 218.95 | FQK71: =+FQG71-FQI71-FQK71 | FQM71: SEGUROS | FQN71: RIMAC SEGUROS | FQP71: 1086478942 | FQS71: 45341 | FQV71: 218.95 | FRA71: =+FQW71-FQY71-FRA71 | FRC71: SEGUROS | FRD71: RIMAC SEGUROS | FRF71: 1086478942 | FRI71: 45341 | FRL71: 218.95 | FRQ71: =+FRM71-FRO71-FRQ71 | FRS71: SEGUROS | FRT71: RIMAC SEGUROS | FRV71: 1086478942 | FRY71: 45341 | FSB71: 218.95 | FSG71: =+FSC71-FSE71-FSG71 | FSI71: SEGUROS | FSJ71: RIMAC SEGUROS | FSL71: 1086478942 | FSO71: 45341 | FSR71: 218.95 | FSW71: =+FSS71-FSU71-FSW71 | FSY71: SEGUROS | FSZ71: RIMAC SEGUROS | FTB71: 1086478942 | FTE71: 45341 | FTH71: 218.95 | FTM71: =+FTI71-FTK71-FTM71 | FTO71: SEGUROS | FTP71: RIMAC SEGUROS | FTR71: 1086478942 | FTU71: 45341 | FTX71: 218.95 | FUC71: =+FTY71-FUA71-FUC71 | FUE71: SEGUROS | FUF71: RIMAC SEGUROS | FUH71: 1086478942 | FUK71: 45341 | FUN71: 218.95 | FUS71: =+FUO71-FUQ71-FUS71 | FUU71: SEGUROS | FUV71: RIMAC SEGUROS | FUX71: 1086478942 | FVA71: 45341 | FVD71: 218.95 | FVI71: =+FVE71-FVG71-FVI71 | FVK71: SEGUROS | FVL71: RIMAC SEGUROS | FVN71: 1086478942 | FVQ71: 45341 | FVT71: 218.95 | FVY71: =+FVU71-FVW71-FVY71 | FWA71: SEGUROS | FWB71: RIMAC SEGUROS | FWD71: 1086478942 | FWG71: 45341 | FWJ71: 218.95 | FWO71: =+FWK71-FWM71-FWO71 | FWQ71: SEGUROS | FWR71: RIMAC SEGUROS | FWT71: 1086478942 | FWW71: 45341 | FWZ71: 218.95 | FXE71: =+FXA71-FXC71-FXE71 | FXG71: SEGUROS | FXH71: RIMAC SEGUROS | FXJ71: 1086478942 | FXM71: 45341 | FXP71: 218.95 | FXU71: =+FXQ71-FXS71-FXU71 | FXW71: SEGUROS | FXX71: RIMAC SEGUROS | FXZ71: 1086478942 | FYC71: 45341 | FYF71: 218.95 | FYK71: =+FYG71-FYI71-FYK71 | FYM71: SEGUROS | FYN71: RIMAC SEGUROS | FYP71: 1086478942 | FYS71: 45341 | FYV71: 218.95 | FZA71: =+FYW71-FYY71-FZA71 | FZC71: SEGUROS | FZD71: RIMAC SEGUROS | FZF71: 1086478942 | FZI71: 45341 | FZL71: 218.95 | FZQ71: =+FZM71-FZO71-FZQ71 | FZS71: SEGUROS | FZT71: RIMAC SEGUROS | FZV71: 1086478942 | FZY71: 45341 | GAB71: 218.95 | GAG71: =+GAC71-GAE71-GAG71 | GAI71: SEGUROS | GAJ71: RIMAC SEGUROS | GAL71: 1086478942 | GAO71: 45341 | GAR71: 218.95 | GAW71: =+GAS71-GAU71-GAW71 | GAY71: SEGUROS | GAZ71: RIMAC SEGUROS | GBB71: 1086478942 | GBE71: 45341 | GBH71: 218.95 | GBM71: =+GBI71-GBK71-GBM71 | GBO71: SEGUROS | GBP71: RIMAC SEGUROS | GBR71: 1086478942 | GBU71: 45341 | GBX71: 218.95 | GCC71: =+GBY71-GCA71-GCC71 | GCE71: SEGUROS | GCF71: RIMAC SEGUROS | GCH71: 1086478942 | GCK71: 45341 | GCN71: 218.95 | GCS71: =+GCO71-GCQ71-GCS71 | GCU71: SEGUROS | GCV71: RIMAC SEGUROS | GCX71: 1086478942 | GDA71: 45341 | GDD71: 218.95 | GDI71: =+GDE71-GDG71-GDI71 | GDK71: SEGUROS | GDL71: RIMAC SEGUROS | GDN71: 1086478942 | GDQ71: 45341 | GDT71: 218.95 | GDY71: =+GDU71-GDW71-GDY71 | GEA71: SEGUROS | GEB71: RIMAC SEGUROS | GED71: 1086478942 | GEG71: 45341 | GEJ71: 218.95 | GEO71: =+GEK71-GEM71-GEO71 | GEQ71: SEGUROS | GER71: RIMAC SEGUROS | GET71: 1086478942 | GEW71: 45341 | GEZ71: 218.95 | GFE71: =+GFA71-GFC71-GFE71 | GFG71: SEGUROS | GFH71: RIMAC SEGUROS | GFJ71: 1086478942 | GFM71: 45341 | GFP71: 218.95 | GFU71: =+GFQ71-GFS71-GFU71 | GFW71: SEGUROS | GFX71: RIMAC SEGUROS | GFZ71: 1086478942 | GGC71: 45341 | GGF71: 218.95 | GGK71: =+GGG71-GGI71-GGK71 | GGM71: SEGUROS | GGN71: RIMAC SEGUROS | GGP71: 1086478942 | GGS71: 45341 | GGV71: 218.95 | GHA71: =+GGW71-GGY71-GHA71 | GHC71: SEGUROS | GHD71: RIMAC SEGUROS | GHF71: 1086478942 | GHI71: 45341 | GHL71: 218.95 | GHQ71: =+GHM71-GHO71-GHQ71 | GHS71: SEGUROS | GHT71: RIMAC SEGUROS | GHV71: 1086478942 | GHY71: 45341 | GIB71: 218.95 | GIG71: =+GIC71-GIE71-GIG71 | GII71: SEGUROS | GIJ71: RIMAC SEGUROS | GIL71: 1086478942 | GIO71: 45341 | GIR71: 218.95 | GIW71: =+GIS71-GIU71-GIW71 | GIY71: SEGUROS | GIZ71: RIMAC SEGUROS | GJB71: 1086478942 | GJE71: 45341 | GJH71: 218.95 | GJM71: =+GJI71-GJK71-GJM71 | GJO71: SEGUROS | GJP71: RIMAC SEGUROS | GJR71: 1086478942 | GJU71: 45341 | GJX71: 218.95 | GKC71: =+GJY71-GKA71-GKC71 | GKE71: SEGUROS | GKF71: RIMAC SEGUROS | GKH71: 1086478942 | GKK71: 45341 | GKN71: 218.95 | GKS71: =+GKO71-GKQ71-GKS71 | GKU71: SEGUROS | GKV71: RIMAC SEGUROS | GKX71: 1086478942 | GLA71: 45341 | GLD71: 218.95 | GLI71: =+GLE71-GLG71-GLI71 | GLK71: SEGUROS | GLL71: RIMAC SEGUROS | GLN71: 1086478942 | GLQ71: 45341 | GLT71: 218.95 | GLY71: =+GLU71-GLW71-GLY71 | GMA71: SEGUROS | GMB71: RIMAC SEGUROS | GMD71: 1086478942 | GMG71: 45341 | GMJ71: 218.95 | GMO71: =+GMK71-GMM71-GMO71 | GMQ71: SEGUROS | GMR71: RIMAC SEGUROS | GMT71: 1086478942 | GMW71: 45341 | GMZ71: 218.95 | GNE71: =+GNA71-GNC71-GNE71 | GNG71: SEGUROS | GNH71: RIMAC SEGUROS | GNJ71: 1086478942 | GNM71: 45341 | GNP71: 218.95 | GNU71: =+GNQ71-GNS71-GNU71 | GNW71: SEGUROS | GNX71: RIMAC SEGUROS | GNZ71: 1086478942 | GOC71: 45341 | GOF71: 218.95 | GOK71: =+GOG71-GOI71-GOK71 | GOM71: SEGUROS | GON71: RIMAC SEGUROS | GOP71: 1086478942 | GOS71: 45341 | GOV71: 218.95 | GPA71: =+GOW71-GOY71-GPA71 | GPC71: SEGUROS | GPD71: RIMAC SEGUROS | GPF71: 1086478942 | GPI71: 45341 | GPL71: 218.95 | GPQ71: =+GPM71-GPO71-GPQ71 | GPS71: SEGUROS | GPT71: RIMAC SEGUROS | GPV71: 1086478942 | GPY71: 45341 | GQB71: 218.95 | GQG71: =+GQC71-GQE71-GQG71 | GQI71: SEGUROS | GQJ71: RIMAC SEGUROS | GQL71: 1086478942 | GQO71: 45341 | GQR71: 218.95 | GQW71: =+GQS71-GQU71-GQW71 | GQY71: SEGUROS | GQZ71: RIMAC SEGUROS | GRB71: 1086478942 | GRE71: 45341 | GRH71: 218.95 | GRM71: =+GRI71-GRK71-GRM71 | GRO71: SEGUROS | GRP71: RIMAC SEGUROS | GRR71: 1086478942 | GRU71: 45341 | GRX71: 218.95 | GSC71: =+GRY71-GSA71-GSC71 | GSE71: SEGUROS | GSF71: RIMAC SEGUROS | GSH71: 1086478942 | GSK71: 45341 | GSN71: 218.95 | GSS71: =+GSO71-GSQ71-GSS71 | GSU71: SEGUROS | GSV71: RIMAC SEGUROS | GSX71: 1086478942 | GTA71: 45341 | GTD71: 218.95 | GTI71: =+GTE71-GTG71-GTI71 | GTK71: SEGUROS | GTL71: RIMAC SEGUROS | GTN71: 1086478942 | GTQ71: 45341 | GTT71: 218.95 | GTY71: =+GTU71-GTW71-GTY71 | GUA71: SEGUROS | GUB71: RIMAC SEGUROS | GUD71: 1086478942 | GUG71: 45341 | GUJ71: 218.95 | GUO71: =+GUK71-GUM71-GUO71 | GUQ71: SEGUROS | GUR71: RIMAC SEGUROS | GUT71: 1086478942 | GUW71: 45341 | GUZ71: 218.95 | GVE71: =+GVA71-GVC71-GVE71 | GVG71: SEGUROS | GVH71: RIMAC SEGUROS | GVJ71: 1086478942 | GVM71: 45341 | GVP71: 218.95 | GVU71: =+GVQ71-GVS71-GVU71 | GVW71: SEGUROS | GVX71: RIMAC SEGUROS | GVZ71: 1086478942 | GWC71: 45341 | GWF71: 218.95 | GWK71: =+GWG71-GWI71-GWK71 | GWM71: SEGUROS | GWN71: RIMAC SEGUROS | GWP71: 1086478942 | GWS71: 45341 | GWV71: 218.95 | GXA71: =+GWW71-GWY71-GXA71 | GXC71: SEGUROS | GXD71: RIMAC SEGUROS | GXF71: 1086478942 | GXI71: 45341 | GXL71: 218.95 | GXQ71: =+GXM71-GXO71-GXQ71 | GXS71: SEGUROS | GXT71: RIMAC SEGUROS | GXV71: 1086478942 | GXY71: 45341 | GYB71: 218.95 | GYG71: =+GYC71-GYE71-GYG71 | GYI71: SEGUROS | GYJ71: RIMAC SEGUROS | GYL71: 1086478942 | GYO71: 45341 | GYR71: 218.95 | GYW71: =+GYS71-GYU71-GYW71 | GYY71: SEGUROS | GYZ71: RIMAC SEGUROS | GZB71: 1086478942 | GZE71: 45341 | GZH71: 218.95 | GZM71: =+GZI71-GZK71-GZM71 | GZO71: SEGUROS | GZP71: RIMAC SEGUROS | GZR71: 1086478942 | GZU71: 45341 | GZX71: 218.95 | HAC71: =+GZY71-HAA71-HAC71 | HAE71: SEGUROS | HAF71: RIMAC SEGUROS | HAH71: 1086478942 | HAK71: 45341 | HAN71: 218.95 | HAS71: =+HAO71-HAQ71-HAS71 | HAU71: SEGUROS | HAV71: RIMAC SEGUROS | HAX71: 1086478942 | HBA71: 45341 | HBD71: 218.95 | HBI71: =+HBE71-HBG71-HBI71 | HBK71: SEGUROS | HBL71: RIMAC SEGUROS | HBN71: 1086478942 | HBQ71: 45341 | HBT71: 218.95 | HBY71: =+HBU71-HBW71-HBY71 | HCA71: SEGUROS | HCB71: RIMAC SEGUROS | HCD71: 1086478942 | HCG71: 45341 | HCJ71: 218.95 | HCO71: =+HCK71-HCM71-HCO71 | HCQ71: SEGUROS | HCR71: RIMAC SEGUROS | HCT71: 1086478942 | HCW71: 45341 | HCZ71: 218.95 | HDE71: =+HDA71-HDC71-HDE71 | HDG71: SEGUROS | HDH71: RIMAC SEGUROS | HDJ71: 1086478942 | HDM71: 45341 | HDP71: 218.95 | HDU71: =+HDQ71-HDS71-HDU71 | HDW71: SEGUROS | HDX71: RIMAC SEGUROS | HDZ71: 1086478942 | HEC71: 45341 | HEF71: 218.95 | HEK71: =+HEG71-HEI71-HEK71 | HEM71: SEGUROS | HEN71: RIMAC SEGUROS | HEP71: 1086478942 | HES71: 45341 | HEV71: 218.95 | HFA71: =+HEW71-HEY71-HFA71 | HFC71: SEGUROS | HFD71: RIMAC SEGUROS | HFF71: 1086478942 | HFI71: 45341 | HFL71: 218.95 | HFQ71: =+HFM71-HFO71-HFQ71 | HFS71: SEGUROS | HFT71: RIMAC SEGUROS | HFV71: 1086478942 | HFY71: 45341 | HGB71: 218.95 | HGG71: =+HGC71-HGE71-HGG71 | HGI71: SEGUROS | HGJ71: RIMAC SEGUROS | HGL71: 1086478942 | HGO71: 45341 | HGR71: 218.95 | HGW71: =+HGS71-HGU71-HGW71 | HGY71: SEGUROS | HGZ71: RIMAC SEGUROS | HHB71: 1086478942 | HHE71: 45341 | HHH71: 218.95 | HHM71: =+HHI71-HHK71-HHM71 | HHO71: SEGUROS | HHP71: RIMAC SEGUROS | HHR71: 1086478942 | HHU71: 45341 | HHX71: 218.95 | HIC71: =+HHY71-HIA71-HIC71 | HIE71: SEGUROS | HIF71: RIMAC SEGUROS | HIH71: 1086478942 | HIK71: 45341 | HIN71: 218.95 | HIS71: =+HIO71-HIQ71-HIS71 | HIU71: SEGUROS | HIV71: RIMAC SEGUROS | HIX71: 1086478942 | HJA71: 45341 | HJD71: 218.95 | HJI71: =+HJE71-HJG71-HJI71 | HJK71: SEGUROS | HJL71: RIMAC SEGUROS | HJN71: 1086478942 | HJQ71: 45341 | HJT71: 218.95 | HJY71: =+HJU71-HJW71-HJY71 | HKA71: SEGUROS | HKB71: RIMAC SEGUROS | HKD71: 1086478942 | HKG71: 45341 | HKJ71: 218.95 | HKO71: =+HKK71-HKM71-HKO71 | HKQ71: SEGUROS | HKR71: RIMAC SEGUROS | HKT71: 1086478942 | HKW71: 45341 | HKZ71: 218.95 | HLE71: =+HLA71-HLC71-HLE71 | HLG71: SEGUROS | HLH71: RIMAC SEGUROS | HLJ71: 1086478942 | HLM71: 45341 | HLP71: 218.95 | HLU71: =+HLQ71-HLS71-HLU71 | HLW71: SEGUROS | HLX71: RIMAC SEGUROS | HLZ71: 1086478942 | HMC71: 45341 | HMF71: 218.95 | HMK71: =+HMG71-HMI71-HMK71 | HMM71: SEGUROS | HMN71: RIMAC SEGUROS | HMP71: 1086478942 | HMS71: 45341 | HMV71: 218.95 | HNA71: =+HMW71-HMY71-HNA71 | HNC71: SEGUROS | HND71: RIMAC SEGUROS | HNF71: 1086478942 | HNI71: 45341 | HNL71: 218.95 | HNQ71: =+HNM71-HNO71-HNQ71 | HNS71: SEGUROS | HNT71: RIMAC SEGUROS | HNV71: 1086478942 | HNY71: 45341 | HOB71: 218.95 | HOG71: =+HOC71-HOE71-HOG71 | HOI71: SEGUROS | HOJ71: RIMAC SEGUROS | HOL71: 1086478942 | HOO71: 45341 | HOR71: 218.95 | HOW71: =+HOS71-HOU71-HOW71 | HOY71: SEGUROS | HOZ71: RIMAC SEGUROS | HPB71: 1086478942 | HPE71: 45341 | HPH71: 218.95 | HPM71: =+HPI71-HPK71-HPM71 | HPO71: SEGUROS | HPP71: RIMAC SEGUROS | HPR71: 1086478942 | HPU71: 45341 | HPX71: 218.95 | HQC71: =+HPY71-HQA71-HQC71 | HQE71: SEGUROS | HQF71: RIMAC SEGUROS | HQH71: 1086478942 | HQK71: 45341 | HQN71: 218.95 | HQS71: =+HQO71-HQQ71-HQS71 | HQU71: SEGUROS | HQV71: RIMAC SEGUROS | HQX71: 1086478942 | HRA71: 45341 | HRD71: 218.95 | HRI71: =+HRE71-HRG71-HRI71 | HRK71: SEGUROS | HRL71: RIMAC SEGUROS | HRN71: 1086478942 | HRQ71: 45341 | HRT71: 218.95 | HRY71: =+HRU71-HRW71-HRY71 | HSA71: SEGUROS | HSB71: RIMAC SEGUROS | HSD71: 1086478942 | HSG71: 45341 | HSJ71: 218.95 | HSO71: =+HSK71-HSM71-HSO71 | HSQ71: SEGUROS | HSR71: RIMAC SEGUROS | HST71: 1086478942 | HSW71: 45341 | HSZ71: 218.95 | HTE71: =+HTA71-HTC71-HTE71 | HTG71: SEGUROS | HTH71: RIMAC SEGUROS | HTJ71: 1086478942 | HTM71: 45341 | HTP71: 218.95 | HTU71: =+HTQ71-HTS71-HTU71 | HTW71: SEGUROS | HTX71: RIMAC SEGUROS | HTZ71: 1086478942 | HUC71: 45341 | HUF71: 218.95 | HUK71: =+HUG71-HUI71-HUK71 | HUM71: SEGUROS | HUN71: RIMAC SEGUROS | HUP71: 1086478942 | HUS71: 45341 | HUV71: 218.95 | HVA71: =+HUW71-HUY71-HVA71 | HVC71: SEGUROS | HVD71: RIMAC SEGUROS | HVF71: 1086478942 | HVI71: 45341 | HVL71: 218.95 | HVQ71: =+HVM71-HVO71-HVQ71 | HVS71: SEGUROS | HVT71: RIMAC SEGUROS | HVV71: 1086478942 | HVY71: 45341 | HWB71: 218.95 | HWG71: =+HWC71-HWE71-HWG71 | HWI71: SEGUROS | HWJ71: RIMAC SEGUROS | HWL71: 1086478942 | HWO71: 45341 | HWR71: 218.95 | HWW71: =+HWS71-HWU71-HWW71 | HWY71: SEGUROS | HWZ71: RIMAC SEGUROS | HXB71: 1086478942 | HXE71: 45341 | HXH71: 218.95 | HXM71: =+HXI71-HXK71-HXM71 | HXO71: SEGUROS | HXP71: RIMAC SEGUROS | HXR71: 1086478942 | HXU71: 45341 | HXX71: 218.95 | HYC71: =+HXY71-HYA71-HYC71 | HYE71: SEGUROS | HYF71: RIMAC SEGUROS | HYH71: 1086478942 | HYK71: 45341 | HYN71: 218.95 | HYS71: =+HYO71-HYQ71-HYS71 | HYU71: SEGUROS | HYV71: RIMAC SEGUROS | HYX71: 1086478942 | HZA71: 45341 | HZD71: 218.95 | HZI71: =+HZE71-HZG71-HZI71 | HZK71: SEGUROS | HZL71: RIMAC SEGUROS | HZN71: 1086478942 | HZQ71: 45341 | HZT71: 218.95 | HZY71: =+HZU71-HZW71-HZY71 | IAA71: SEGUROS | IAB71: RIMAC SEGUROS | IAD71: 1086478942 | IAG71: 45341 | IAJ71: 218.95 | IAO71: =+IAK71-IAM71-IAO71 | IAQ71: SEGUROS | IAR71: RIMAC SEGUROS | IAT71: 1086478942 | IAW71: 45341 | IAZ71: 218.95 | IBE71: =+IBA71-IBC71-IBE71 | IBG71: SEGUROS | IBH71: RIMAC SEGUROS | IBJ71: 1086478942 | IBM71: 45341 | IBP71: 218.95 | IBU71: =+IBQ71-IBS71-IBU71 | IBW71: SEGUROS | IBX71: RIMAC SEGUROS | IBZ71: 1086478942 | ICC71: 45341 | ICF71: 218.95 | ICK71: =+ICG71-ICI71-ICK71 | ICM71: SEGUROS | ICN71: RIMAC SEGUROS | ICP71: 1086478942 | ICS71: 45341 | ICV71: 218.95 | IDA71: =+ICW71-ICY71-IDA71 | IDC71: SEGUROS | IDD71: RIMAC SEGUROS | IDF71: 1086478942 | IDI71: 45341 | IDL71: 218.95 | IDQ71: =+IDM71-IDO71-IDQ71 | IDS71: SEGUROS | IDT71: RIMAC SEGUROS | IDV71: 1086478942 | IDY71: 45341 | IEB71: 218.95 | IEG71: =+IEC71-IEE71-IEG71 | IEI71: SEGUROS | IEJ71: RIMAC SEGUROS | IEL71: 1086478942 | IEO71: 45341 | IER71: 218.95 | IEW71: =+IES71-IEU71-IEW71 | IEY71: SEGUROS | IEZ71: RIMAC SEGUROS | IFB71: 1086478942 | IFE71: 45341 | IFH71: 218.95 | IFM71: =+IFI71-IFK71-IFM71 | IFO71: SEGUROS | IFP71: RIMAC SEGUROS | IFR71: 1086478942 | IFU71: 45341 | IFX71: 218.95 | IGC71: =+IFY71-IGA71-IGC71 | IGE71: SEGUROS | IGF71: RIMAC SEGUROS | IGH71: 1086478942 | IGK71: 45341 | IGN71: 218.95 | IGS71: =+IGO71-IGQ71-IGS71 | IGU71: SEGUROS | IGV71: RIMAC SEGUROS | IGX71: 1086478942 | IHA71: 45341 | IHD71: 218.95 | IHI71: =+IHE71-IHG71-IHI71 | IHK71: SEGUROS | IHL71: RIMAC SEGUROS | IHN71: 1086478942 | IHQ71: 45341 | IHT71: 218.95 | IHY71: =+IHU71-IHW71-IHY71 | IIA71: SEGUROS | IIB71: RIMAC SEGUROS | IID71: 1086478942 | IIG71: 45341 | IIJ71: 218.95 | IIO71: =+IIK71-IIM71-IIO71 | IIQ71: SEGUROS | IIR71: RIMAC SEGUROS | IIT71: 1086478942 | IIW71: 45341 | IIZ71: 218.95 | IJE71: =+IJA71-IJC71-IJE71 | IJG71: SEGUROS | IJH71: RIMAC SEGUROS | IJJ71: 1086478942 | IJM71: 45341 | IJP71: 218.95 | IJU71: =+IJQ71-IJS71-IJU71 | IJW71: SEGUROS | IJX71: RIMAC SEGUROS | IJZ71: 1086478942 | IKC71: 45341 | IKF71: 218.95 | IKK71: =+IKG71-IKI71-IKK71 | IKM71: SEGUROS | IKN71: RIMAC SEGUROS | IKP71: 1086478942 | IKS71: 45341 | IKV71: 218.95 | ILA71: =+IKW71-IKY71-ILA71 | ILC71: SEGUROS | ILD71: RIMAC SEGUROS | ILF71: 1086478942 | ILI71: 45341 | ILL71: 218.95 | ILQ71: =+ILM71-ILO71-ILQ71 | ILS71: SEGUROS | ILT71: RIMAC SEGUROS | ILV71: 1086478942 | ILY71: 45341 | IMB71: 218.95 | IMG71: =+IMC71-IME71-IMG71 | IMI71: SEGUROS | IMJ71: RIMAC SEGUROS | IML71: 1086478942 | IMO71: 45341 | IMR71: 218.95 | IMW71: =+IMS71-IMU71-IMW71 | IMY71: SEGUROS | IMZ71: RIMAC SEGUROS | INB71: 1086478942 | INE71: 45341 | INH71: 218.95 | INM71: =+INI71-INK71-INM71 | INO71: SEGUROS | INP71: RIMAC SEGUROS | INR71: 1086478942 | INU71: 45341 | INX71: 218.95 | IOC71: =+INY71-IOA71-IOC71 | IOE71: SEGUROS | IOF71: RIMAC SEGUROS | IOH71: 1086478942 | IOK71: 45341 | ION71: 218.95 | IOS71: =+IOO71-IOQ71-IOS71 | IOU71: SEGUROS | IOV71: RIMAC SEGUROS | IOX71: 1086478942 | IPA71: 45341 | IPD71: 218.95 | IPI71: =+IPE71-IPG71-IPI71 | IPK71: SEGUROS | IPL71: RIMAC SEGUROS | IPN71: 1086478942 | IPQ71: 45341 | IPT71: 218.95 | IPY71: =+IPU71-IPW71-IPY71 | IQA71: SEGUROS | IQB71: RIMAC SEGUROS | IQD71: 1086478942 | IQG71: 45341 | IQJ71: 218.95 | IQO71: =+IQK71-IQM71-IQO71 | IQQ71: SEGUROS | IQR71: RIMAC SEGUROS | IQT71: 1086478942 | IQW71: 45341 | IQZ71: 218.95 | IRE71: =+IRA71-IRC71-IRE71 | IRG71: SEGUROS | IRH71: RIMAC SEGUROS | IRJ71: 1086478942 | IRM71: 45341 | IRP71: 218.95 | IRU71: =+IRQ71-IRS71-IRU71 | IRW71: SEGUROS | IRX71: RIMAC SEGUROS | IRZ71: 1086478942 | ISC71: 45341 | ISF71: 218.95 | ISK71: =+ISG71-ISI71-ISK71 | ISM71: SEGUROS | ISN71: RIMAC SEGUROS | ISP71: 1086478942 | ISS71: 45341 | ISV71: 218.95 | ITA71: =+ISW71-ISY71-ITA71 | ITC71: SEGUROS | ITD71: RIMAC SEGUROS | ITF71: 1086478942 | ITI71: 45341 | ITL71: 218.95 | ITQ71: =+ITM71-ITO71-ITQ71 | ITS71: SEGUROS | ITT71: RIMAC SEGUROS | ITV71: 1086478942 | ITY71: 45341 | IUB71: 218.95 | IUG71: =+IUC71-IUE71-IUG71 | IUI71: SEGUROS | IUJ71: RIMAC SEGUROS | IUL71: 1086478942 | IUO71: 45341 | IUR71: 218.95 | IUW71: =+IUS71-IUU71-IUW71 | IUY71: SEGUROS | IUZ71: RIMAC SEGUROS | IVB71: 1086478942 | IVE71: 45341 | IVH71: 218.95 | IVM71: =+IVI71-IVK71-IVM71 | IVO71: SEGUROS | IVP71: RIMAC SEGUROS | IVR71: 1086478942 | IVU71: 45341 | IVX71: 218.95 | IWC71: =+IVY71-IWA71-IWC71 | IWE71: SEGUROS | IWF71: RIMAC SEGUROS | IWH71: 1086478942 | IWK71: 45341 | IWN71: 218.95 | IWS71: =+IWO71-IWQ71-IWS71 | IWU71: SEGUROS | IWV71: RIMAC SEGUROS | IWX71: 1086478942 | IXA71: 45341 | IXD71: 218.95 | IXI71: =+IXE71-IXG71-IXI71 | IXK71: SEGUROS | IXL71: RIMAC SEGUROS | IXN71: 1086478942 | IXQ71: 45341 | IXT71: 218.95 | IXY71: =+IXU71-IXW71-IXY71 | IYA71: SEGUROS | IYB71: RIMAC SEGUROS | IYD71: 1086478942 | IYG71: 45341 | IYJ71: 218.95 | IYO71: =+IYK71-IYM71-IYO71 | IYQ71: SEGUROS | IYR71: RIMAC SEGUROS | IYT71: 1086478942 | IYW71: 45341 | IYZ71: 218.95 | IZE71: =+IZA71-IZC71-IZE71 | IZG71: SEGUROS | IZH71: RIMAC SEGUROS | IZJ71: 1086478942 | IZM71: 45341 | IZP71: 218.95 | IZU71: =+IZQ71-IZS71-IZU71 | IZW71: SEGUROS | IZX71: RIMAC SEGUROS | IZZ71: 1086478942 | JAC71: 45341 | JAF71: 218.95 | JAK71: =+JAG71-JAI71-JAK71 | JAM71: SEGUROS | JAN71: RIMAC SEGUROS | JAP71: 1086478942 | JAS71: 45341 | JAV71: 218.95 | JBA71: =+JAW71-JAY71-JBA71 | JBC71: SEGUROS | JBD71: RIMAC SEGUROS | JBF71: 1086478942 | JBI71: 45341 | JBL71: 218.95 | JBQ71: =+JBM71-JBO71-JBQ71 | JBS71: SEGUROS | JBT71: RIMAC SEGUROS | JBV71: 1086478942 | JBY71: 45341 | JCB71: 218.95 | JCG71: =+JCC71-JCE71-JCG71 | JCI71: SEGUROS | JCJ71: RIMAC SEGUROS | JCL71: 1086478942 | JCO71: 45341 | JCR71: 218.95 | JCW71: =+JCS71-JCU71-JCW71 | JCY71: SEGUROS | JCZ71: RIMAC SEGUROS | JDB71: 1086478942 | JDE71: 45341 | JDH71: 218.95 | JDM71: =+JDI71-JDK71-JDM71 | JDO71: SEGUROS | JDP71: RIMAC SEGUROS | JDR71: 1086478942 | JDU71: 45341 | JDX71: 218.95 | JEC71: =+JDY71-JEA71-JEC71 | JEE71: SEGUROS | JEF71: RIMAC SEGUROS | JEH71: 1086478942 | JEK71: 45341 | JEN71: 218.95 | JES71: =+JEO71-JEQ71-JES71 | JEU71: SEGUROS | JEV71: RIMAC SEGUROS | JEX71: 1086478942 | JFA71: 45341 | JFD71: 218.95 | JFI71: =+JFE71-JFG71-JFI71 | JFK71: SEGUROS | JFL71: RIMAC SEGUROS | JFN71: 1086478942 | JFQ71: 45341 | JFT71: 218.95 | JFY71: =+JFU71-JFW71-JFY71 | JGA71: SEGUROS | JGB71: RIMAC SEGUROS | JGD71: 1086478942 | JGG71: 45341 | JGJ71: 218.95 | JGO71: =+JGK71-JGM71-JGO71 | JGQ71: SEGUROS | JGR71: RIMAC SEGUROS | JGT71: 1086478942 | JGW71: 45341 | JGZ71: 218.95 | JHE71: =+JHA71-JHC71-JHE71 | JHG71: SEGUROS | JHH71: RIMAC SEGUROS | JHJ71: 1086478942 | JHM71: 45341 | JHP71: 218.95 | JHU71: =+JHQ71-JHS71-JHU71 | JHW71: SEGUROS | JHX71: RIMAC SEGUROS | JHZ71: 1086478942 | JIC71: 45341 | JIF71: 218.95 | JIK71: =+JIG71-JII71-JIK71 | JIM71: SEGUROS | JIN71: RIMAC SEGUROS | JIP71: 1086478942 | JIS71: 45341 | JIV71: 218.95 | JJA71: =+JIW71-JIY71-JJA71 | JJC71: SEGUROS | JJD71: RIMAC SEGUROS | JJF71: 1086478942 | JJI71: 45341 | JJL71: 218.95 | JJQ71: =+JJM71-JJO71-JJQ71 | JJS71: SEGUROS | JJT71: RIMAC SEGUROS | JJV71: 1086478942 | JJY71: 45341 | JKB71: 218.95 | JKG71: =+JKC71-JKE71-JKG71 | JKI71: SEGUROS | JKJ71: RIMAC SEGUROS | JKL71: 1086478942 | JKO71: 45341 | JKR71: 218.95 | JKW71: =+JKS71-JKU71-JKW71 | JKY71: SEGUROS | JKZ71: RIMAC SEGUROS | JLB71: 1086478942 | JLE71: 45341 | JLH71: 218.95 | JLM71: =+JLI71-JLK71-JLM71 | JLO71: SEGUROS | JLP71: RIMAC SEGUROS | JLR71: 1086478942 | JLU71: 45341 | JLX71: 218.95 | JMC71: =+JLY71-JMA71-JMC71 | JME71: SEGUROS | JMF71: RIMAC SEGUROS | JMH71: 1086478942 | JMK71: 45341 | JMN71: 218.95 | JMS71: =+JMO71-JMQ71-JMS71 | JMU71: SEGUROS | JMV71: RIMAC SEGUROS | JMX71: 1086478942 | JNA71: 45341 | JND71: 218.95 | JNI71: =+JNE71-JNG71-JNI71 | JNK71: SEGUROS | JNL71: RIMAC SEGUROS | JNN71: 1086478942 | JNQ71: 45341 | JNT71: 218.95 | JNY71: =+JNU71-JNW71-JNY71 | JOA71: SEGUROS | JOB71: RIMAC SEGUROS | JOD71: 1086478942 | JOG71: 45341 | JOJ71: 218.95 | JOO71: =+JOK71-JOM71-JOO71 | JOQ71: SEGUROS | JOR71: RIMAC SEGUROS | JOT71: 1086478942 | JOW71: 45341 | JOZ71: 218.95 | JPE71: =+JPA71-JPC71-JPE71 | JPG71: SEGUROS | JPH71: RIMAC SEGUROS | JPJ71: 1086478942 | JPM71: 45341 | JPP71: 218.95 | JPU71: =+JPQ71-JPS71-JPU71 | JPW71: SEGUROS | JPX71: RIMAC SEGUROS | JPZ71: 1086478942 | JQC71: 45341 | JQF71: 218.95 | JQK71: =+JQG71-JQI71-JQK71 | JQM71: SEGUROS | JQN71: RIMAC SEGUROS | JQP71: 1086478942 | JQS71: 45341 | JQV71: 218.95 | JRA71: =+JQW71-JQY71-JRA71 | JRC71: SEGUROS | JRD71: RIMAC SEGUROS | JRF71: 1086478942 | JRI71: 45341 | JRL71: 218.95 | JRQ71: =+JRM71-JRO71-JRQ71 | JRS71: SEGUROS | JRT71: RIMAC SEGUROS | JRV71: 1086478942 | JRY71: 45341 | JSB71: 218.95 | JSG71: =+JSC71-JSE71-JSG71 | JSI71: SEGUROS | JSJ71: RIMAC SEGUROS | JSL71: 1086478942 | JSO71: 45341 | JSR71: 218.95 | JSW71: =+JSS71-JSU71-JSW71 | JSY71: SEGUROS | JSZ71: RIMAC SEGUROS | JTB71: 1086478942 | JTE71: 45341 | JTH71: 218.95 | JTM71: =+JTI71-JTK71-JTM71 | JTO71: SEGUROS | JTP71: RIMAC SEGUROS | JTR71: 1086478942 | JTU71: 45341 | JTX71: 218.95 | JUC71: =+JTY71-JUA71-JUC71 | JUE71: SEGUROS | JUF71: RIMAC SEGUROS | JUH71: 1086478942 | JUK71: 45341 | JUN71: 218.95 | JUS71: =+JUO71-JUQ71-JUS71 | JUU71: SEGUROS | JUV71: RIMAC SEGUROS | JUX71: 1086478942 | JVA71: 45341 | JVD71: 218.95 | JVI71: =+JVE71-JVG71-JVI71 | JVK71: SEGUROS | JVL71: RIMAC SEGUROS | JVN71: 1086478942 | JVQ71: 45341 | JVT71: 218.95 | JVY71: =+JVU71-JVW71-JVY71 | JWA71: SEGUROS | JWB71: RIMAC SEGUROS | JWD71: 1086478942 | JWG71: 45341 | JWJ71: 218.95 | JWO71: =+JWK71-JWM71-JWO71 | JWQ71: SEGUROS | JWR71: RIMAC SEGUROS | JWT71: 1086478942 | JWW71: 45341 | JWZ71: 218.95 | JXE71: =+JXA71-JXC71-JXE71 | JXG71: SEGUROS | JXH71: RIMAC SEGUROS | JXJ71: 1086478942 | JXM71: 45341 | JXP71: 218.95 | JXU71: =+JXQ71-JXS71-JXU71 | JXW71: SEGUROS | JXX71: RIMAC SEGUROS | JXZ71: 1086478942 | JYC71: 45341 | JYF71: 218.95 | JYK71: =+JYG71-JYI71-JYK71 | JYM71: SEGUROS | JYN71: RIMAC SEGUROS | JYP71: 1086478942 | JYS71: 45341 | JYV71: 218.95 | JZA71: =+JYW71-JYY71-JZA71 | JZC71: SEGUROS | JZD71: RIMAC SEGUROS | JZF71: 1086478942 | JZI71: 45341 | JZL71: 218.95 | JZQ71: =+JZM71-JZO71-JZQ71 | JZS71: SEGUROS | JZT71: RIMAC SEGUROS | JZV71: 1086478942 | JZY71: 45341 | KAB71: 218.95 | KAG71: =+KAC71-KAE71-KAG71 | KAI71: SEGUROS | KAJ71: RIMAC SEGUROS | KAL71: 1086478942 | KAO71: 45341 | KAR71: 218.95 | KAW71: =+KAS71-KAU71-KAW71 | KAY71: SEGUROS | KAZ71: RIMAC SEGUROS | KBB71: 1086478942 | KBE71: 45341 | KBH71: 218.95 | KBM71: =+KBI71-KBK71-KBM71 | KBO71: SEGUROS | KBP71: RIMAC SEGUROS | KBR71: 1086478942 | KBU71: 45341 | KBX71: 218.95 | KCC71: =+KBY71-KCA71-KCC71 | KCE71: SEGUROS | KCF71: RIMAC SEGUROS | KCH71: 1086478942 | KCK71: 45341 | KCN71: 218.95 | KCS71: =+KCO71-KCQ71-KCS71 | KCU71: SEGUROS | KCV71: RIMAC SEGUROS | KCX71: 1086478942 | KDA71: 45341 | KDD71: 218.95 | KDI71: =+KDE71-KDG71-KDI71 | KDK71: SEGUROS | KDL71: RIMAC SEGUROS | KDN71: 1086478942 | KDQ71: 45341 | KDT71: 218.95 | KDY71: =+KDU71-KDW71-KDY71 | KEA71: SEGUROS | KEB71: RIMAC SEGUROS | KED71: 1086478942 | KEG71: 45341 | KEJ71: 218.95 | KEO71: =+KEK71-KEM71-KEO71 | KEQ71: SEGUROS | KER71: RIMAC SEGUROS | KET71: 1086478942 | KEW71: 45341 | KEZ71: 218.95 | KFE71: =+KFA71-KFC71-KFE71 | KFG71: SEGUROS | KFH71: RIMAC SEGUROS | KFJ71: 1086478942 | KFM71: 45341 | KFP71: 218.95 | KFU71: =+KFQ71-KFS71-KFU71 | KFW71: SEGUROS | KFX71: RIMAC SEGUROS | KFZ71: 1086478942 | KGC71: 45341 | KGF71: 218.95 | KGK71: =+KGG71-KGI71-KGK71 | KGM71: SEGUROS | KGN71: RIMAC SEGUROS | KGP71: 1086478942 | KGS71: 45341 | KGV71: 218.95 | KHA71: =+KGW71-KGY71-KHA71 | KHC71: SEGUROS | KHD71: RIMAC SEGUROS | KHF71: 1086478942 | KHI71: 45341 | KHL71: 218.95 | KHQ71: =+KHM71-KHO71-KHQ71 | KHS71: SEGUROS | KHT71: RIMAC SEGUROS | KHV71: 1086478942 | KHY71: 45341 | KIB71: 218.95 | KIG71: =+KIC71-KIE71-KIG71 | KII71: SEGUROS | KIJ71: RIMAC SEGUROS | KIL71: 1086478942 | KIO71: 45341 | KIR71: 218.95 | KIW71: =+KIS71-KIU71-KIW71 | KIY71: SEGUROS | KIZ71: RIMAC SEGUROS | KJB71: 1086478942 | KJE71: 45341 | KJH71: 218.95 | KJM71: =+KJI71-KJK71-KJM71 | KJO71: SEGUROS | KJP71: RIMAC SEGUROS | KJR71: 1086478942 | KJU71: 45341 | KJX71: 218.95 | KKC71: =+KJY71-KKA71-KKC71 | KKE71: SEGUROS | KKF71: RIMAC SEGUROS | KKH71: 1086478942 | KKK71: 45341 | KKN71: 218.95 | KKS71: =+KKO71-KKQ71-KKS71 | KKU71: SEGUROS | KKV71: RIMAC SEGUROS | KKX71: 1086478942 | KLA71: 45341 | KLD71: 218.95 | KLI71: =+KLE71-KLG71-KLI71 | KLK71: SEGUROS | KLL71: RIMAC SEGUROS | KLN71: 1086478942 | KLQ71: 45341 | KLT71: 218.95 | KLY71: =+KLU71-KLW71-KLY71 | KMA71: SEGUROS | KMB71: RIMAC SEGUROS | KMD71: 1086478942 | KMG71: 45341 | KMJ71: 218.95 | KMO71: =+KMK71-KMM71-KMO71 | KMQ71: SEGUROS | KMR71: RIMAC SEGUROS | KMT71: 1086478942 | KMW71: 45341 | KMZ71: 218.95 | KNE71: =+KNA71-KNC71-KNE71 | KNG71: SEGUROS | KNH71: RIMAC SEGUROS | KNJ71: 1086478942 | KNM71: 45341 | KNP71: 218.95 | KNU71: =+KNQ71-KNS71-KNU71 | KNW71: SEGUROS | KNX71: RIMAC SEGUROS | KNZ71: 1086478942 | KOC71: 45341 | KOF71: 218.95 | KOK71: =+KOG71-KOI71-KOK71 | KOM71: SEGUROS | KON71: RIMAC SEGUROS | KOP71: 1086478942 | KOS71: 45341 | KOV71: 218.95 | KPA71: =+KOW71-KOY71-KPA71 | KPC71: SEGUROS | KPD71: RIMAC SEGUROS | KPF71: 1086478942 | KPI71: 45341 | KPL71: 218.95 | KPQ71: =+KPM71-KPO71-KPQ71 | KPS71: SEGUROS | KPT71: RIMAC SEGUROS | KPV71: 1086478942 | KPY71: 45341 | KQB71: 218.95 | KQG71: =+KQC71-KQE71-KQG71 | KQI71: SEGUROS | KQJ71: RIMAC SEGUROS | KQL71: 1086478942 | KQO71: 45341 | KQR71: 218.95 | KQW71: =+KQS71-KQU71-KQW71 | KQY71: SEGUROS | KQZ71: RIMAC SEGUROS | KRB71: 1086478942 | KRE71: 45341 | KRH71: 218.95 | KRM71: =+KRI71-KRK71-KRM71 | KRO71: SEGUROS | KRP71: RIMAC SEGUROS | KRR71: 1086478942 | KRU71: 45341 | KRX71: 218.95 | KSC71: =+KRY71-KSA71-KSC71 | KSE71: SEGUROS | KSF71: RIMAC SEGUROS | KSH71: 1086478942 | KSK71: 45341 | KSN71: 218.95 | KSS71: =+KSO71-KSQ71-KSS71 | KSU71: SEGUROS | KSV71: RIMAC SEGUROS | KSX71: 1086478942 | KTA71: 45341 | KTD71: 218.95 | KTI71: =+KTE71-KTG71-KTI71 | KTK71: SEGUROS | KTL71: RIMAC SEGUROS | KTN71: 1086478942 | KTQ71: 45341 | KTT71: 218.95 | KTY71: =+KTU71-KTW71-KTY71 | KUA71: SEGUROS | KUB71: RIMAC SEGUROS | KUD71: 1086478942 | KUG71: 45341 | KUJ71: 218.95 | KUO71: =+KUK71-KUM71-KUO71 | KUQ71: SEGUROS | KUR71: RIMAC SEGUROS | KUT71: 1086478942 | KUW71: 45341 | KUZ71: 218.95 | KVE71: =+KVA71-KVC71-KVE71 | KVG71: SEGUROS | KVH71: RIMAC SEGUROS | KVJ71: 1086478942 | KVM71: 45341 | KVP71: 218.95 | KVU71: =+KVQ71-KVS71-KVU71 | KVW71: SEGUROS | KVX71: RIMAC SEGUROS | KVZ71: 1086478942 | KWC71: 45341 | KWF71: 218.95 | KWK71: =+KWG71-KWI71-KWK71 | KWM71: SEGUROS | KWN71: RIMAC SEGUROS | KWP71: 1086478942 | KWS71: 45341 | KWV71: 218.95 | KXA71: =+KWW71-KWY71-KXA71 | KXC71: SEGUROS | KXD71: RIMAC SEGUROS | KXF71: 1086478942 | KXI71: 45341 | KXL71: 218.95 | KXQ71: =+KXM71-KXO71-KXQ71 | KXS71: SEGUROS | KXT71: RIMAC SEGUROS | KXV71: 1086478942 | KXY71: 45341 | KYB71: 218.95 | KYG71: =+KYC71-KYE71-KYG71 | KYI71: SEGUROS | KYJ71: RIMAC SEGUROS | KYL71: 1086478942 | KYO71: 45341 | KYR71: 218.95 | KYW71: =+KYS71-KYU71-KYW71 | KYY71: SEGUROS | KYZ71: RIMAC SEGUROS | KZB71: 1086478942 | KZE71: 45341 | KZH71: 218.95 | KZM71: =+KZI71-KZK71-KZM71 | KZO71: SEGUROS | KZP71: RIMAC SEGUROS | KZR71: 1086478942 | KZU71: 45341 | KZX71: 218.95 | LAC71: =+KZY71-LAA71-LAC71 | LAE71: SEGUROS | LAF71: RIMAC SEGUROS | LAH71: 1086478942 | LAK71: 45341 | LAN71: 218.95 | LAS71: =+LAO71-LAQ71-LAS71 | LAU71: SEGUROS | LAV71: RIMAC SEGUROS | LAX71: 1086478942 | LBA71: 45341 | LBD71: 218.95 | LBI71: =+LBE71-LBG71-LBI71 | LBK71: SEGUROS | LBL71: RIMAC SEGUROS | LBN71: 1086478942 | LBQ71: 45341 | LBT71: 218.95 | LBY71: =+LBU71-LBW71-LBY71 | LCA71: SEGUROS | LCB71: RIMAC SEGUROS | LCD71: 1086478942 | LCG71: 45341 | LCJ71: 218.95 | LCO71: =+LCK71-LCM71-LCO71 | LCQ71: SEGUROS | LCR71: RIMAC SEGUROS | LCT71: 1086478942 | LCW71: 45341 | LCZ71: 218.95 | LDE71: =+LDA71-LDC71-LDE71 | LDG71: SEGUROS | LDH71: RIMAC SEGUROS | LDJ71: 1086478942 | LDM71: 45341 | LDP71: 218.95 | LDU71: =+LDQ71-LDS71-LDU71 | LDW71: SEGUROS | LDX71: RIMAC SEGUROS | LDZ71: 1086478942 | LEC71: 45341 | LEF71: 218.95 | LEK71: =+LEG71-LEI71-LEK71 | LEM71: SEGUROS | LEN71: RIMAC SEGUROS | LEP71: 1086478942 | LES71: 45341 | LEV71: 218.95 | LFA71: =+LEW71-LEY71-LFA71 | LFC71: SEGUROS | LFD71: RIMAC SEGUROS | LFF71: 1086478942 | LFI71: 45341 | LFL71: 218.95 | LFQ71: =+LFM71-LFO71-LFQ71 | LFS71: SEGUROS | LFT71: RIMAC SEGUROS | LFV71: 1086478942 | LFY71: 45341 | LGB71: 218.95 | LGG71: =+LGC71-LGE71-LGG71 | LGI71: SEGUROS | LGJ71: RIMAC SEGUROS | LGL71: 1086478942 | LGO71: 45341 | LGR71: 218.95 | LGW71: =+LGS71-LGU71-LGW71 | LGY71: SEGUROS | LGZ71: RIMAC SEGUROS | LHB71: 1086478942 | LHE71: 45341 | LHH71: 218.95 | LHM71: =+LHI71-LHK71-LHM71 | LHO71: SEGUROS | LHP71: RIMAC SEGUROS | LHR71: 1086478942 | LHU71: 45341 | LHX71: 218.95 | LIC71: =+LHY71-LIA71-LIC71 | LIE71: SEGUROS | LIF71: RIMAC SEGUROS | LIH71: 1086478942 | LIK71: 45341 | LIN71: 218.95 | LIS71: =+LIO71-LIQ71-LIS71 | LIU71: SEGUROS | LIV71: RIMAC SEGUROS | LIX71: 1086478942 | LJA71: 45341 | LJD71: 218.95 | LJI71: =+LJE71-LJG71-LJI71 | LJK71: SEGUROS | LJL71: RIMAC SEGUROS | LJN71: 1086478942 | LJQ71: 45341 | LJT71: 218.95 | LJY71: =+LJU71-LJW71-LJY71 | LKA71: SEGUROS | LKB71: RIMAC SEGUROS | LKD71: 1086478942 | LKG71: 45341 | LKJ71: 218.95 | LKO71: =+LKK71-LKM71-LKO71 | LKQ71: SEGUROS | LKR71: RIMAC SEGUROS | LKT71: 1086478942 | LKW71: 45341 | LKZ71: 218.95 | LLE71: =+LLA71-LLC71-LLE71 | LLG71: SEGUROS | LLH71: RIMAC SEGUROS | LLJ71: 1086478942 | LLM71: 45341 | LLP71: 218.95 | LLU71: =+LLQ71-LLS71-LLU71 | LLW71: SEGUROS | LLX71: RIMAC SEGUROS | LLZ71: 1086478942 | LMC71: 45341 | LMF71: 218.95 | LMK71: =+LMG71-LMI71-LMK71 | LMM71: SEGUROS | LMN71: RIMAC SEGUROS | LMP71: 1086478942 | LMS71: 45341 | LMV71: 218.95 | LNA71: =+LMW71-LMY71-LNA71 | LNC71: SEGUROS | LND71: RIMAC SEGUROS | LNF71: 1086478942 | LNI71: 45341 | LNL71: 218.95 | LNQ71: =+LNM71-LNO71-LNQ71 | LNS71: SEGUROS | LNT71: RIMAC SEGUROS | LNV71: 1086478942 | LNY71: 45341 | LOB71: 218.95 | LOG71: =+LOC71-LOE71-LOG71 | LOI71: SEGUROS | LOJ71: RIMAC SEGUROS | LOL71: 1086478942 | LOO71: 45341 | LOR71: 218.95 | LOW71: =+LOS71-LOU71-LOW71 | LOY71: SEGUROS | LOZ71: RIMAC SEGUROS | LPB71: 1086478942 | LPE71: 45341 | LPH71: 218.95 | LPM71: =+LPI71-LPK71-LPM71 | LPO71: SEGUROS | LPP71: RIMAC SEGUROS | LPR71: 1086478942 | LPU71: 45341 | LPX71: 218.95 | LQC71: =+LPY71-LQA71-LQC71 | LQE71: SEGUROS | LQF71: RIMAC SEGUROS | LQH71: 1086478942 | LQK71: 45341 | LQN71: 218.95 | LQS71: =+LQO71-LQQ71-LQS71 | LQU71: SEGUROS | LQV71: RIMAC SEGUROS | LQX71: 1086478942 | LRA71: 45341 | LRD71: 218.95 | LRI71: =+LRE71-LRG71-LRI71 | LRK71: SEGUROS | LRL71: RIMAC SEGUROS | LRN71: 1086478942 | LRQ71: 45341 | LRT71: 218.95 | LRY71: =+LRU71-LRW71-LRY71 | LSA71: SEGUROS | LSB71: RIMAC SEGUROS | LSD71: 1086478942 | LSG71: 45341 | LSJ71: 218.95 | LSO71: =+LSK71-LSM71-LSO71 | LSQ71: SEGUROS | LSR71: RIMAC SEGUROS | LST71: 1086478942 | LSW71: 45341 | LSZ71: 218.95 | LTE71: =+LTA71-LTC71-LTE71 | LTG71: SEGUROS | LTH71: RIMAC SEGUROS | LTJ71: 1086478942 | LTM71: 45341 | LTP71: 218.95 | LTU71: =+LTQ71-LTS71-LTU71 | LTW71: SEGUROS | LTX71: RIMAC SEGUROS | LTZ71: 1086478942 | LUC71: 45341 | LUF71: 218.95 | LUK71: =+LUG71-LUI71-LUK71 | LUM71: SEGUROS | LUN71: RIMAC SEGUROS | LUP71: 1086478942 | LUS71: 45341 | LUV71: 218.95 | LVA71: =+LUW71-LUY71-LVA71 | LVC71: SEGUROS | LVD71: RIMAC SEGUROS | LVF71: 1086478942 | LVI71: 45341 | LVL71: 218.95 | LVQ71: =+LVM71-LVO71-LVQ71 | LVS71: SEGUROS | LVT71: RIMAC SEGUROS | LVV71: 1086478942 | LVY71: 45341 | LWB71: 218.95 | LWG71: =+LWC71-LWE71-LWG71 | LWI71: SEGUROS | LWJ71: RIMAC SEGUROS | LWL71: 1086478942 | LWO71: 45341 | LWR71: 218.95 | LWW71: =+LWS71-LWU71-LWW71 | LWY71: SEGUROS | LWZ71: RIMAC SEGUROS | LXB71: 1086478942 | LXE71: 45341 | LXH71: 218.95 | LXM71: =+LXI71-LXK71-LXM71 | LXO71: SEGUROS | LXP71: RIMAC SEGUROS | LXR71: 1086478942 | LXU71: 45341 | LXX71: 218.95 | LYC71: =+LXY71-LYA71-LYC71 | LYE71: SEGUROS | LYF71: RIMAC SEGUROS | LYH71: 1086478942 | LYK71: 45341 | LYN71: 218.95 | LYS71: =+LYO71-LYQ71-LYS71 | LYU71: SEGUROS | LYV71: RIMAC SEGUROS | LYX71: 1086478942 | LZA71: 45341 | LZD71: 218.95 | LZI71: =+LZE71-LZG71-LZI71 | LZK71: SEGUROS | LZL71: RIMAC SEGUROS | LZN71: 1086478942 | LZQ71: 45341 | LZT71: 218.95 | LZY71: =+LZU71-LZW71-LZY71 | MAA71: SEGUROS | MAB71: RIMAC SEGUROS | MAD71: 1086478942 | MAG71: 45341 | MAJ71: 218.95 | MAO71: =+MAK71-MAM71-MAO71 | MAQ71: SEGUROS | MAR71: RIMAC SEGUROS | MAT71: 1086478942 | MAW71: 45341 | MAZ71: 218.95 | MBE71: =+MBA71-MBC71-MBE71 | MBG71: SEGUROS | MBH71: RIMAC SEGUROS | MBJ71: 1086478942 | MBM71: 45341 | MBP71: 218.95 | MBU71: =+MBQ71-MBS71-MBU71 | MBW71: SEGUROS | MBX71: RIMAC SEGUROS | MBZ71: 1086478942 | MCC71: 45341 | MCF71: 218.95 | MCK71: =+MCG71-MCI71-MCK71 | MCM71: SEGUROS | MCN71: RIMAC SEGUROS | MCP71: 1086478942 | MCS71: 45341 | MCV71: 218.95 | MDA71: =+MCW71-MCY71-MDA71 | MDC71: SEGUROS | MDD71: RIMAC SEGUROS | MDF71: 1086478942 | MDI71: 45341 | MDL71: 218.95 | MDQ71: =+MDM71-MDO71-MDQ71 | MDS71: SEGUROS | MDT71: RIMAC SEGUROS | MDV71: 1086478942 | MDY71: 45341 | MEB71: 218.95 | MEG71: =+MEC71-MEE71-MEG71 | MEI71: SEGUROS | MEJ71: RIMAC SEGUROS | MEL71: 1086478942 | MEO71: 45341 | MER71: 218.95 | MEW71: =+MES71-MEU71-MEW71 | MEY71: SEGUROS | MEZ71: RIMAC SEGUROS | MFB71: 1086478942 | MFE71: 45341 | MFH71: 218.95 | MFM71: =+MFI71-MFK71-MFM71 | MFO71: SEGUROS | MFP71: RIMAC SEGUROS | MFR71: 1086478942 | MFU71: 45341 | MFX71: 218.95 | MGC71: =+MFY71-MGA71-MGC71 | MGE71: SEGUROS | MGF71: RIMAC SEGUROS | MGH71: 1086478942 | MGK71: 45341 | MGN71: 218.95 | MGS71: =+MGO71-MGQ71-MGS71 | MGU71: SEGUROS | MGV71: RIMAC SEGUROS | MGX71: 1086478942 | MHA71: 45341 | MHD71: 218.95 | MHI71: =+MHE71-MHG71-MHI71 | MHK71: SEGUROS | MHL71: RIMAC SEGUROS | MHN71: 1086478942 | MHQ71: 45341 | MHT71: 218.95 | MHY71: =+MHU71-MHW71-MHY71 | MIA71: SEGUROS | MIB71: RIMAC SEGUROS | MID71: 1086478942 | MIG71: 45341 | MIJ71: 218.95 | MIO71: =+MIK71-MIM71-MIO71 | MIQ71: SEGUROS | MIR71: RIMAC SEGUROS | MIT71: 1086478942 | MIW71: 45341 | MIZ71: 218.95 | MJE71: =+MJA71-MJC71-MJE71 | MJG71: SEGUROS | MJH71: RIMAC SEGUROS | MJJ71: 1086478942 | MJM71: 45341 | MJP71: 218.95 | MJU71: =+MJQ71-MJS71-MJU71 | MJW71: SEGUROS | MJX71: RIMAC SEGUROS | MJZ71: 1086478942 | MKC71: 45341 | MKF71: 218.95 | MKK71: =+MKG71-MKI71-MKK71 | MKM71: SEGUROS | MKN71: RIMAC SEGUROS | MKP71: 1086478942 | MKS71: 45341 | MKV71: 218.95 | MLA71: =+MKW71-MKY71-MLA71 | MLC71: SEGUROS | MLD71: RIMAC SEGUROS | MLF71: 1086478942 | MLI71: 45341 | MLL71: 218.95 | MLQ71: =+MLM71-MLO71-MLQ71 | MLS71: SEGUROS | MLT71: RIMAC SEGUROS | MLV71: 1086478942 | MLY71: 45341 | MMB71: 218.95 | MMG71: =+MMC71-MME71-MMG71 | MMI71: SEGUROS | MMJ71: RIMAC SEGUROS | MML71: 1086478942 | MMO71: 45341 | MMR71: 218.95 | MMW71: =+MMS71-MMU71-MMW71 | MMY71: SEGUROS | MMZ71: RIMAC SEGUROS | MNB71: 1086478942 | MNE71: 45341 | MNH71: 218.95 | MNM71: =+MNI71-MNK71-MNM71 | MNO71: SEGUROS | MNP71: RIMAC SEGUROS | MNR71: 1086478942 | MNU71: 45341 | MNX71: 218.95 | MOC71: =+MNY71-MOA71-MOC71 | MOE71: SEGUROS | MOF71: RIMAC SEGUROS | MOH71: 1086478942 | MOK71: 45341 | MON71: 218.95 | MOS71: =+MOO71-MOQ71-MOS71 | MOU71: SEGUROS | MOV71: RIMAC SEGUROS | MOX71: 1086478942 | MPA71: 45341 | MPD71: 218.95 | MPI71: =+MPE71-MPG71-MPI71 | MPK71: SEGUROS | MPL71: RIMAC SEGUROS | MPN71: 1086478942 | MPQ71: 45341 | MPT71: 218.95 | MPY71: =+MPU71-MPW71-MPY71 | MQA71: SEGUROS | MQB71: RIMAC SEGUROS | MQD71: 1086478942 | MQG71: 45341 | MQJ71: 218.95 | MQO71: =+MQK71-MQM71-MQO71 | MQQ71: SEGUROS | MQR71: RIMAC SEGUROS | MQT71: 1086478942 | MQW71: 45341 | MQZ71: 218.95 | MRE71: =+MRA71-MRC71-MRE71 | MRG71: SEGUROS | MRH71: RIMAC SEGUROS | MRJ71: 1086478942 | MRM71: 45341 | MRP71: 218.95 | MRU71: =+MRQ71-MRS71-MRU71 | MRW71: SEGUROS | MRX71: RIMAC SEGUROS | MRZ71: 1086478942 | MSC71: 45341 | MSF71: 218.95 | MSK71: =+MSG71-MSI71-MSK71 | MSM71: SEGUROS | MSN71: RIMAC SEGUROS | MSP71: 1086478942 | MSS71: 45341 | MSV71: 218.95 | MTA71: =+MSW71-MSY71-MTA71 | MTC71: SEGUROS | MTD71: RIMAC SEGUROS | MTF71: 1086478942 | MTI71: 45341 | MTL71: 218.95 | MTQ71: =+MTM71-MTO71-MTQ71 | MTS71: SEGUROS | MTT71: RIMAC SEGUROS | MTV71: 1086478942 | MTY71: 45341 | MUB71: 218.95 | MUG71: =+MUC71-MUE71-MUG71 | MUI71: SEGUROS | MUJ71: RIMAC SEGUROS | MUL71: 1086478942 | MUO71: 45341 | MUR71: 218.95 | MUW71: =+MUS71-MUU71-MUW71 | MUY71: SEGUROS | MUZ71: RIMAC SEGUROS | MVB71: 1086478942 | MVE71: 45341 | MVH71: 218.95 | MVM71: =+MVI71-MVK71-MVM71 | MVO71: SEGUROS | MVP71: RIMAC SEGUROS | MVR71: 1086478942 | MVU71: 45341 | MVX71: 218.95 | MWC71: =+MVY71-MWA71-MWC71 | MWE71: SEGUROS | MWF71: RIMAC SEGUROS | MWH71: 1086478942 | MWK71: 45341 | MWN71: 218.95 | MWS71: =+MWO71-MWQ71-MWS71 | MWU71: SEGUROS | MWV71: RIMAC SEGUROS | MWX71: 1086478942 | MXA71: 45341 | MXD71: 218.95 | MXI71: =+MXE71-MXG71-MXI71 | MXK71: SEGUROS | MXL71: RIMAC SEGUROS | MXN71: 1086478942 | MXQ71: 45341 | MXT71: 218.95 | MXY71: =+MXU71-MXW71-MXY71 | MYA71: SEGUROS | MYB71: RIMAC SEGUROS | MYD71: 1086478942 | MYG71: 45341 | MYJ71: 218.95 | MYO71: =+MYK71-MYM71-MYO71 | MYQ71: SEGUROS | MYR71: RIMAC SEGUROS | MYT71: 1086478942 | MYW71: 45341 | MYZ71: 218.95 | MZE71: =+MZA71-MZC71-MZE71 | MZG71: SEGUROS | MZH71: RIMAC SEGUROS | MZJ71: 1086478942 | MZM71: 45341 | MZP71: 218.95 | MZU71: =+MZQ71-MZS71-MZU71 | MZW71: SEGUROS | MZX71: RIMAC SEGUROS | MZZ71: 1086478942 | NAC71: 45341 | NAF71: 218.95 | NAK71: =+NAG71-NAI71-NAK71 | NAM71: SEGUROS | NAN71: RIMAC SEGUROS | NAP71: 1086478942 | NAS71: 45341 | NAV71: 218.95 | NBA71: =+NAW71-NAY71-NBA71 | NBC71: SEGUROS | NBD71: RIMAC SEGUROS | NBF71: 1086478942 | NBI71: 45341 | NBL71: 218.95 | NBQ71: =+NBM71-NBO71-NBQ71 | NBS71: SEGUROS | NBT71: RIMAC SEGUROS | NBV71: 1086478942 | NBY71: 45341 | NCB71: 218.95 | NCG71: =+NCC71-NCE71-NCG71 | NCI71: SEGUROS | NCJ71: RIMAC SEGUROS | NCL71: 1086478942 | NCO71: 45341 | NCR71: 218.95 | NCW71: =+NCS71-NCU71-NCW71 | NCY71: SEGUROS | NCZ71: RIMAC SEGUROS | NDB71: 1086478942 | NDE71: 45341 | NDH71: 218.95 | NDM71: =+NDI71-NDK71-NDM71 | NDO71: SEGUROS | NDP71: RIMAC SEGUROS | NDR71: 1086478942 | NDU71: 45341 | NDX71: 218.95 | NEC71: =+NDY71-NEA71-NEC71 | NEE71: SEGUROS | NEF71: RIMAC SEGUROS | NEH71: 1086478942 | NEK71: 45341 | NEN71: 218.95 | NES71: =+NEO71-NEQ71-NES71 | NEU71: SEGUROS | NEV71: RIMAC SEGUROS | NEX71: 1086478942 | NFA71: 45341 | NFD71: 218.95 | NFI71: =+NFE71-NFG71-NFI71 | NFK71: SEGUROS | NFL71: RIMAC SEGUROS | NFN71: 1086478942 | NFQ71: 45341 | NFT71: 218.95 | NFY71: =+NFU71-NFW71-NFY71 | NGA71: SEGUROS | NGB71: RIMAC SEGUROS | NGD71: 1086478942 | NGG71: 45341 | NGJ71: 218.95 | NGO71: =+NGK71-NGM71-NGO71 | NGQ71: SEGUROS | NGR71: RIMAC SEGUROS | NGT71: 1086478942 | NGW71: 45341 | NGZ71: 218.95 | NHE71: =+NHA71-NHC71-NHE71 | NHG71: SEGUROS | NHH71: RIMAC SEGUROS | NHJ71: 1086478942 | NHM71: 45341 | NHP71: 218.95 | NHU71: =+NHQ71-NHS71-NHU71 | NHW71: SEGUROS | NHX71: RIMAC SEGUROS | NHZ71: 1086478942 | NIC71: 45341 | NIF71: 218.95 | NIK71: =+NIG71-NII71-NIK71 | NIM71: SEGUROS | NIN71: RIMAC SEGUROS | NIP71: 1086478942 | NIS71: 45341 | NIV71: 218.95 | NJA71: =+NIW71-NIY71-NJA71 | NJC71: SEGUROS | NJD71: RIMAC SEGUROS | NJF71: 1086478942 | NJI71: 45341 | NJL71: 218.95 | NJQ71: =+NJM71-NJO71-NJQ71 | NJS71: SEGUROS | NJT71: RIMAC SEGUROS | NJV71: 1086478942 | NJY71: 45341 | NKB71: 218.95 | NKG71: =+NKC71-NKE71-NKG71 | NKI71: SEGUROS | NKJ71: RIMAC SEGUROS | NKL71: 1086478942 | NKO71: 45341 | NKR71: 218.95 | NKW71: =+NKS71-NKU71-NKW71 | NKY71: SEGUROS | NKZ71: RIMAC SEGUROS | NLB71: 1086478942 | NLE71: 45341 | NLH71: 218.95 | NLM71: =+NLI71-NLK71-NLM71 | NLO71: SEGUROS | NLP71: RIMAC SEGUROS | NLR71: 1086478942 | NLU71: 45341 | NLX71: 218.95 | NMC71: =+NLY71-NMA71-NMC71 | NME71: SEGUROS | NMF71: RIMAC SEGUROS | NMH71: 1086478942 | NMK71: 45341 | NMN71: 218.95 | NMS71: =+NMO71-NMQ71-NMS71 | NMU71: SEGUROS | NMV71: RIMAC SEGUROS | NMX71: 1086478942 | NNA71: 45341 | NND71: 218.95 | NNI71: =+NNE71-NNG71-NNI71 | NNK71: SEGUROS | NNL71: RIMAC SEGUROS | NNN71: 1086478942 | NNQ71: 45341 | NNT71: 218.95 | NNY71: =+NNU71-NNW71-NNY71 | NOA71: SEGUROS | NOB71: RIMAC SEGUROS | NOD71: 1086478942 | NOG71: 45341 | NOJ71: 218.95 | NOO71: =+NOK71-NOM71-NOO71 | NOQ71: SEGUROS | NOR71: RIMAC SEGUROS | NOT71: 1086478942 | NOW71: 45341 | NOZ71: 218.95 | NPE71: =+NPA71-NPC71-NPE71 | NPG71: SEGUROS | NPH71: RIMAC SEGUROS | NPJ71: 1086478942 | NPM71: 45341 | NPP71: 218.95 | NPU71: =+NPQ71-NPS71-NPU71 | NPW71: SEGUROS | NPX71: RIMAC SEGUROS | NPZ71: 1086478942 | NQC71: 45341 | NQF71: 218.95 | NQK71: =+NQG71-NQI71-NQK71 | NQM71: SEGUROS | NQN71: RIMAC SEGUROS | NQP71: 1086478942 | NQS71: 45341 | NQV71: 218.95 | NRA71: =+NQW71-NQY71-NRA71 | NRC71: SEGUROS | NRD71: RIMAC SEGUROS | NRF71: 1086478942 | NRI71: 45341 | NRL71: 218.95 | NRQ71: =+NRM71-NRO71-NRQ71 | NRS71: SEGUROS | NRT71: RIMAC SEGUROS | NRV71: 1086478942 | NRY71: 45341 | NSB71: 218.95 | NSG71: =+NSC71-NSE71-NSG71 | NSI71: SEGUROS | NSJ71: RIMAC SEGUROS | NSL71: 1086478942 | NSO71: 45341 | NSR71: 218.95 | NSW71: =+NSS71-NSU71-NSW71 | NSY71: SEGUROS | NSZ71: RIMAC SEGUROS | NTB71: 1086478942 | NTE71: 45341 | NTH71: 218.95 | NTM71: =+NTI71-NTK71-NTM71 | NTO71: SEGUROS | NTP71: RIMAC SEGUROS | NTR71: 1086478942 | NTU71: 45341 | NTX71: 218.95 | NUC71: =+NTY71-NUA71-NUC71 | NUE71: SEGUROS | NUF71: RIMAC SEGUROS | NUH71: 1086478942 | NUK71: 45341 | NUN71: 218.95 | NUS71: =+NUO71-NUQ71-NUS71 | NUU71: SEGUROS | NUV71: RIMAC SEGUROS | NUX71: 1086478942 | NVA71: 45341 | NVD71: 218.95 | NVI71: =+NVE71-NVG71-NVI71 | NVK71: SEGUROS | NVL71: RIMAC SEGUROS | NVN71: 1086478942 | NVQ71: 45341 | NVT71: 218.95 | NVY71: =+NVU71-NVW71-NVY71 | NWA71: SEGUROS | NWB71: RIMAC SEGUROS | NWD71: 1086478942 | NWG71: 45341 | NWJ71: 218.95 | NWO71: =+NWK71-NWM71-NWO71 | NWQ71: SEGUROS | NWR71: RIMAC SEGUROS | NWT71: 1086478942 | NWW71: 45341 | NWZ71: 218.95 | NXE71: =+NXA71-NXC71-NXE71 | NXG71: SEGUROS | NXH71: RIMAC SEGUROS | NXJ71: 1086478942 | NXM71: 45341 | NXP71: 218.95 | NXU71: =+NXQ71-NXS71-NXU71 | NXW71: SEGUROS | NXX71: RIMAC SEGUROS | NXZ71: 1086478942 | NYC71: 45341 | NYF71: 218.95 | NYK71: =+NYG71-NYI71-NYK71 | NYM71: SEGUROS | NYN71: RIMAC SEGUROS | NYP71: 1086478942 | NYS71: 45341 | NYV71: 218.95 | NZA71: =+NYW71-NYY71-NZA71 | NZC71: SEGUROS | NZD71: RIMAC SEGUROS | NZF71: 1086478942 | NZI71: 45341 | NZL71: 218.95 | NZQ71: =+NZM71-NZO71-NZQ71 | NZS71: SEGUROS | NZT71: RIMAC SEGUROS | NZV71: 1086478942 | NZY71: 45341 | OAB71: 218.95 | OAG71: =+OAC71-OAE71-OAG71 | OAI71: SEGUROS | OAJ71: RIMAC SEGUROS | OAL71: 1086478942 | OAO71: 45341 | OAR71: 218.95 | OAW71: =+OAS71-OAU71-OAW71 | OAY71: SEGUROS | OAZ71: RIMAC SEGUROS | OBB71: 1086478942 | OBE71: 45341 | OBH71: 218.95 | OBM71: =+OBI71-OBK71-OBM71 | OBO71: SEGUROS | OBP71: RIMAC SEGUROS | OBR71: 1086478942 | OBU71: 45341 | OBX71: 218.95 | OCC71: =+OBY71-OCA71-OCC71 | OCE71: SEGUROS | OCF71: RIMAC SEGUROS | OCH71: 1086478942 | OCK71: 45341 | OCN71: 218.95 | OCS71: =+OCO71-OCQ71-OCS71 | OCU71: SEGUROS | OCV71: RIMAC SEGUROS | OCX71: 1086478942 | ODA71: 45341 | ODD71: 218.95 | ODI71: =+ODE71-ODG71-ODI71 | ODK71: SEGUROS | ODL71: RIMAC SEGUROS | ODN71: 1086478942 | ODQ71: 45341 | ODT71: 218.95 | ODY71: =+ODU71-ODW71-ODY71 | OEA71: SEGUROS | OEB71: RIMAC SEGUROS | OED71: 1086478942 | OEG71: 45341 | OEJ71: 218.95 | OEO71: =+OEK71-OEM71-OEO71 | OEQ71: SEGUROS | OER71: RIMAC SEGUROS | OET71: 1086478942 | OEW71: 45341 | OEZ71: 218.95 | OFE71: =+OFA71-OFC71-OFE71 | OFG71: SEGUROS | OFH71: RIMAC SEGUROS | OFJ71: 1086478942 | OFM71: 45341 | OFP71: 218.95 | OFU71: =+OFQ71-OFS71-OFU71 | OFW71: SEGUROS | OFX71: RIMAC SEGUROS | OFZ71: 1086478942 | OGC71: 45341 | OGF71: 218.95 | OGK71: =+OGG71-OGI71-OGK71 | OGM71: SEGUROS | OGN71: RIMAC SEGUROS | OGP71: 1086478942 | OGS71: 45341 | OGV71: 218.95 | OHA71: =+OGW71-OGY71-OHA71 | OHC71: SEGUROS | OHD71: RIMAC SEGUROS | OHF71: 1086478942 | OHI71: 45341 | OHL71: 218.95 | OHQ71: =+OHM71-OHO71-OHQ71 | OHS71: SEGUROS | OHT71: RIMAC SEGUROS | OHV71: 1086478942 | OHY71: 45341 | OIB71: 218.95 | OIG71: =+OIC71-OIE71-OIG71 | OII71: SEGUROS | OIJ71: RIMAC SEGUROS | OIL71: 1086478942 | OIO71: 45341 | OIR71: 218.95 | OIW71: =+OIS71-OIU71-OIW71 | OIY71: SEGUROS | OIZ71: RIMAC SEGUROS | OJB71: 1086478942 | OJE71: 45341 | OJH71: 218.95 | OJM71: =+OJI71-OJK71-OJM71 | OJO71: SEGUROS | OJP71: RIMAC SEGUROS | OJR71: 1086478942 | OJU71: 45341 | OJX71: 218.95 | OKC71: =+OJY71-OKA71-OKC71 | OKE71: SEGUROS | OKF71: RIMAC SEGUROS | OKH71: 1086478942 | OKK71: 45341 | OKN71: 218.95 | OKS71: =+OKO71-OKQ71-OKS71 | OKU71: SEGUROS | OKV71: RIMAC SEGUROS | OKX71: 1086478942 | OLA71: 45341 | OLD71: 218.95 | OLI71: =+OLE71-OLG71-OLI71 | OLK71: SEGUROS | OLL71: RIMAC SEGUROS | OLN71: 1086478942 | OLQ71: 45341 | OLT71: 218.95 | OLY71: =+OLU71-OLW71-OLY71 | OMA71: SEGUROS | OMB71: RIMAC SEGUROS | OMD71: 1086478942 | OMG71: 45341 | OMJ71: 218.95 | OMO71: =+OMK71-OMM71-OMO71 | OMQ71: SEGUROS | OMR71: RIMAC SEGUROS | OMT71: 1086478942 | OMW71: 45341 | OMZ71: 218.95 | ONE71: =+ONA71-ONC71-ONE71 | ONG71: SEGUROS | ONH71: RIMAC SEGUROS | ONJ71: 1086478942 | ONM71: 45341 | ONP71: 218.95 | ONU71: =+ONQ71-ONS71-ONU71 | ONW71: SEGUROS | ONX71: RIMAC SEGUROS | ONZ71: 1086478942 | OOC71: 45341 | OOF71: 218.95 | OOK71: =+OOG71-OOI71-OOK71 | OOM71: SEGUROS | OON71: RIMAC SEGUROS | OOP71: 1086478942 | OOS71: 45341 | OOV71: 218.95 | OPA71: =+OOW71-OOY71-OPA71 | OPC71: SEGUROS | OPD71: RIMAC SEGUROS | OPF71: 1086478942 | OPI71: 45341 | OPL71: 218.95 | OPQ71: =+OPM71-OPO71-OPQ71 | OPS71: SEGUROS | OPT71: RIMAC SEGUROS | OPV71: 1086478942 | OPY71: 45341 | OQB71: 218.95 | OQG71: =+OQC71-OQE71-OQG71 | OQI71: SEGUROS | OQJ71: RIMAC SEGUROS | OQL71: 1086478942 | OQO71: 45341 | OQR71: 218.95 | OQW71: =+OQS71-OQU71-OQW71 | OQY71: SEGUROS | OQZ71: RIMAC SEGUROS | ORB71: 1086478942 | ORE71: 45341 | ORH71: 218.95 | ORM71: =+ORI71-ORK71-ORM71 | ORO71: SEGUROS | ORP71: RIMAC SEGUROS | ORR71: 1086478942 | ORU71: 45341 | ORX71: 218.95 | OSC71: =+ORY71-OSA71-OSC71 | OSE71: SEGUROS | OSF71: RIMAC SEGUROS | OSH71: 1086478942 | OSK71: 45341 | OSN71: 218.95 | OSS71: =+OSO71-OSQ71-OSS71 | OSU71: SEGUROS | OSV71: RIMAC SEGUROS | OSX71: 1086478942 | OTA71: 45341 | OTD71: 218.95 | OTI71: =+OTE71-OTG71-OTI71 | OTK71: SEGUROS | OTL71: RIMAC SEGUROS | OTN71: 1086478942 | OTQ71: 45341 | OTT71: 218.95 | OTY71: =+OTU71-OTW71-OTY71 | OUA71: SEGUROS | OUB71: RIMAC SEGUROS | OUD71: 1086478942 | OUG71: 45341 | OUJ71: 218.95 | OUO71: =+OUK71-OUM71-OUO71 | OUQ71: SEGUROS | OUR71: RIMAC SEGUROS | OUT71: 1086478942 | OUW71: 45341 | OUZ71: 218.95 | OVE71: =+OVA71-OVC71-OVE71 | OVG71: SEGUROS | OVH71: RIMAC SEGUROS | OVJ71: 1086478942 | OVM71: 45341 | OVP71: 218.95 | OVU71: =+OVQ71-OVS71-OVU71 | OVW71: SEGUROS | OVX71: RIMAC SEGUROS | OVZ71: 1086478942 | OWC71: 45341 | OWF71: 218.95 | OWK71: =+OWG71-OWI71-OWK71 | OWM71: SEGUROS | OWN71: RIMAC SEGUROS | OWP71: 1086478942 | OWS71: 45341 | OWV71: 218.95 | OXA71: =+OWW71-OWY71-OXA71 | OXC71: SEGUROS | OXD71: RIMAC SEGUROS | OXF71: 1086478942 | OXI71: 45341 | OXL71: 218.95 | OXQ71: =+OXM71-OXO71-OXQ71 | OXS71: SEGUROS | OXT71: RIMAC SEGUROS | OXV71: 1086478942 | OXY71: 45341 | OYB71: 218.95 | OYG71: =+OYC71-OYE71-OYG71 | OYI71: SEGUROS | OYJ71: RIMAC SEGUROS | OYL71: 1086478942 | OYO71: 45341 | OYR71: 218.95 | OYW71: =+OYS71-OYU71-OYW71 | OYY71: SEGUROS | OYZ71: RIMAC SEGUROS | OZB71: 1086478942 | OZE71: 45341 | OZH71: 218.95 | OZM71: =+OZI71-OZK71-OZM71 | OZO71: SEGUROS | OZP71: RIMAC SEGUROS | OZR71: 1086478942 | OZU71: 45341 | OZX71: 218.95 | PAC71: =+OZY71-PAA71-PAC71 | PAE71: SEGUROS | PAF71: RIMAC SEGUROS | PAH71: 1086478942 | PAK71: 45341 | PAN71: 218.95 | PAS71: =+PAO71-PAQ71-PAS71 | PAU71: SEGUROS | PAV71: RIMAC SEGUROS | PAX71: 1086478942 | PBA71: 45341 | PBD71: 218.95 | PBI71: =+PBE71-PBG71-PBI71 | PBK71: SEGUROS | PBL71: RIMAC SEGUROS | PBN71: 1086478942 | PBQ71: 45341 | PBT71: 218.95 | PBY71: =+PBU71-PBW71-PBY71 | PCA71: SEGUROS | PCB71: RIMAC SEGUROS | PCD71: 1086478942 | PCG71: 45341 | PCJ71: 218.95 | PCO71: =+PCK71-PCM71-PCO71 | PCQ71: SEGUROS | PCR71: RIMAC SEGUROS | PCT71: 1086478942 | PCW71: 45341 | PCZ71: 218.95 | PDE71: =+PDA71-PDC71-PDE71 | PDG71: SEGUROS | PDH71: RIMAC SEGUROS | PDJ71: 1086478942 | PDM71: 45341 | PDP71: 218.95 | PDU71: =+PDQ71-PDS71-PDU71 | PDW71: SEGUROS | PDX71: RIMAC SEGUROS | PDZ71: 1086478942 | PEC71: 45341 | PEF71: 218.95 | PEK71: =+PEG71-PEI71-PEK71 | PEM71: SEGUROS | PEN71: RIMAC SEGUROS | PEP71: 1086478942 | PES71: 45341 | PEV71: 218.95 | PFA71: =+PEW71-PEY71-PFA71 | PFC71: SEGUROS | PFD71: RIMAC SEGUROS | PFF71: 1086478942 | PFI71: 45341 | PFL71: 218.95 | PFQ71: =+PFM71-PFO71-PFQ71 | PFS71: SEGUROS | PFT71: RIMAC SEGUROS | PFV71: 1086478942 | PFY71: 45341 | PGB71: 218.95 | PGG71: =+PGC71-PGE71-PGG71 | PGI71: SEGUROS | PGJ71: RIMAC SEGUROS | PGL71: 1086478942 | PGO71: 45341 | PGR71: 218.95 | PGW71: =+PGS71-PGU71-PGW71 | PGY71: SEGUROS | PGZ71: RIMAC SEGUROS | PHB71: 1086478942 | PHE71: 45341 | PHH71: 218.95 | PHM71: =+PHI71-PHK71-PHM71 | PHO71: SEGUROS | PHP71: RIMAC SEGUROS | PHR71: 1086478942 | PHU71: 45341 | PHX71: 218.95 | PIC71: =+PHY71-PIA71-PIC71 | PIE71: SEGUROS | PIF71: RIMAC SEGUROS | PIH71: 1086478942 | PIK71: 45341 | PIN71: 218.95 | PIS71: =+PIO71-PIQ71-PIS71 | PIU71: SEGUROS | PIV71: RIMAC SEGUROS | PIX71: 1086478942 | PJA71: 45341 | PJD71: 218.95 | PJI71: =+PJE71-PJG71-PJI71 | PJK71: SEGUROS | PJL71: RIMAC SEGUROS | PJN71: 1086478942 | PJQ71: 45341 | PJT71: 218.95 | PJY71: =+PJU71-PJW71-PJY71 | PKA71: SEGUROS | PKB71: RIMAC SEGUROS | PKD71: 1086478942 | PKG71: 45341 | PKJ71: 218.95 | PKO71: =+PKK71-PKM71-PKO71 | PKQ71: SEGUROS | PKR71: RIMAC SEGUROS | PKT71: 1086478942 | PKW71: 45341 | PKZ71: 218.95 | PLE71: =+PLA71-PLC71-PLE71 | PLG71: SEGUROS | PLH71: RIMAC SEGUROS | PLJ71: 1086478942 | PLM71: 45341 | PLP71: 218.95 | PLU71: =+PLQ71-PLS71-PLU71 | PLW71: SEGUROS | PLX71: RIMAC SEGUROS | PLZ71: 1086478942 | PMC71: 45341 | PMF71: 218.95 | PMK71: =+PMG71-PMI71-PMK71 | PMM71: SEGUROS | PMN71: RIMAC SEGUROS | PMP71: 1086478942 | PMS71: 45341 | PMV71: 218.95 | PNA71: =+PMW71-PMY71-PNA71 | PNC71: SEGUROS | PND71: RIMAC SEGUROS | PNF71: 1086478942 | PNI71: 45341 | PNL71: 218.95 | PNQ71: =+PNM71-PNO71-PNQ71 | PNS71: SEGUROS | PNT71: RIMAC SEGUROS | PNV71: 1086478942 | PNY71: 45341 | POB71: 218.95 | POG71: =+POC71-POE71-POG71 | POI71: SEGUROS | POJ71: RIMAC SEGUROS | POL71: 1086478942 | POO71: 45341 | POR71: 218.95 | POW71: =+POS71-POU71-POW71 | POY71: SEGUROS | POZ71: RIMAC SEGUROS | PPB71: 1086478942 | PPE71: 45341 | PPH71: 218.95 | PPM71: =+PPI71-PPK71-PPM71 | PPO71: SEGUROS | PPP71: RIMAC SEGUROS | PPR71: 1086478942 | PPU71: 45341 | PPX71: 218.95 | PQC71: =+PPY71-PQA71-PQC71 | PQE71: SEGUROS | PQF71: RIMAC SEGUROS | PQH71: 1086478942 | PQK71: 45341 | PQN71: 218.95 | PQS71: =+PQO71-PQQ71-PQS71 | PQU71: SEGUROS | PQV71: RIMAC SEGUROS | PQX71: 1086478942 | PRA71: 45341 | PRD71: 218.95 | PRI71: =+PRE71-PRG71-PRI71 | PRK71: SEGUROS | PRL71: RIMAC SEGUROS | PRN71: 1086478942 | PRQ71: 45341 | PRT71: 218.95 | PRY71: =+PRU71-PRW71-PRY71 | PSA71: SEGUROS | PSB71: RIMAC SEGUROS | PSD71: 1086478942 | PSG71: 45341 | PSJ71: 218.95 | PSO71: =+PSK71-PSM71-PSO71 | PSQ71: SEGUROS | PSR71: RIMAC SEGUROS | PST71: 1086478942 | PSW71: 45341 | PSZ71: 218.95 | PTE71: =+PTA71-PTC71-PTE71 | PTG71: SEGUROS | PTH71: RIMAC SEGUROS | PTJ71: 1086478942 | PTM71: 45341 | PTP71: 218.95 | PTU71: =+PTQ71-PTS71-PTU71 | PTW71: SEGUROS | PTX71: RIMAC SEGUROS | PTZ71: 1086478942 | PUC71: 45341 | PUF71: 218.95 | PUK71: =+PUG71-PUI71-PUK71 | PUM71: SEGUROS | PUN71: RIMAC SEGUROS | PUP71: 1086478942 | PUS71: 45341 | PUV71: 218.95 | PVA71: =+PUW71-PUY71-PVA71 | PVC71: SEGUROS | PVD71: RIMAC SEGUROS | PVF71: 1086478942 | PVI71: 45341 | PVL71: 218.95 | PVQ71: =+PVM71-PVO71-PVQ71 | PVS71: SEGUROS | PVT71: RIMAC SEGUROS | PVV71: 1086478942 | PVY71: 45341 | PWB71: 218.95 | PWG71: =+PWC71-PWE71-PWG71 | PWI71: SEGUROS | PWJ71: RIMAC SEGUROS | PWL71: 1086478942 | PWO71: 45341 | PWR71: 218.95 | PWW71: =+PWS71-PWU71-PWW71 | PWY71: SEGUROS | PWZ71: RIMAC SEGUROS | PXB71: 1086478942 | PXE71: 45341 | PXH71: 218.95 | PXM71: =+PXI71-PXK71-PXM71 | PXO71: SEGUROS | PXP71: RIMAC SEGUROS | PXR71: 1086478942 | PXU71: 45341 | PXX71: 218.95 | PYC71: =+PXY71-PYA71-PYC71 | PYE71: SEGUROS | PYF71: RIMAC SEGUROS | PYH71: 1086478942 | PYK71: 45341 | PYN71: 218.95 | PYS71: =+PYO71-PYQ71-PYS71 | PYU71: SEGUROS | PYV71: RIMAC SEGUROS | PYX71: 1086478942 | PZA71: 45341 | PZD71: 218.95 | PZI71: =+PZE71-PZG71-PZI71 | PZK71: SEGUROS | PZL71: RIMAC SEGUROS | PZN71: 1086478942 | PZQ71: 45341 | PZT71: 218.95 | PZY71: =+PZU71-PZW71-PZY71 | QAA71: SEGUROS | QAB71: RIMAC SEGUROS | QAD71: 1086478942 | QAG71: 45341 | QAJ71: 218.95 | QAO71: =+QAK71-QAM71-QAO71 | QAQ71: SEGUROS | QAR71: RIMAC SEGUROS | QAT71: 1086478942 | QAW71: 45341 | QAZ71: 218.95 | QBE71: =+QBA71-QBC71-QBE71 | QBG71: SEGUROS | QBH71: RIMAC SEGUROS | QBJ71: 1086478942 | QBM71: 45341 | QBP71: 218.95 | QBU71: =+QBQ71-QBS71-QBU71 | QBW71: SEGUROS | QBX71: RIMAC SEGUROS | QBZ71: 1086478942 | QCC71: 45341 | QCF71: 218.95 | QCK71: =+QCG71-QCI71-QCK71 | QCM71: SEGUROS | QCN71: RIMAC SEGUROS | QCP71: 1086478942 | QCS71: 45341 | QCV71: 218.95 | QDA71: =+QCW71-QCY71-QDA71 | QDC71: SEGUROS | QDD71: RIMAC SEGUROS | QDF71: 1086478942 | QDI71: 45341 | QDL71: 218.95 | QDQ71: =+QDM71-QDO71-QDQ71 | QDS71: SEGUROS | QDT71: RIMAC SEGUROS | QDV71: 1086478942 | QDY71: 45341 | QEB71: 218.95 | QEG71: =+QEC71-QEE71-QEG71 | QEI71: SEGUROS | QEJ71: RIMAC SEGUROS | QEL71: 1086478942 | QEO71: 45341 | QER71: 218.95 | QEW71: =+QES71-QEU71-QEW71 | QEY71: SEGUROS | QEZ71: RIMAC SEGUROS | QFB71: 1086478942 | QFE71: 45341 | QFH71: 218.95 | QFM71: =+QFI71-QFK71-QFM71 | QFO71: SEGUROS | QFP71: RIMAC SEGUROS | QFR71: 1086478942 | QFU71: 45341 | QFX71: 218.95 | QGC71: =+QFY71-QGA71-QGC71 | QGE71: SEGUROS | QGF71: RIMAC SEGUROS | QGH71: 1086478942 | QGK71: 45341 | QGN71: 218.95 | QGS71: =+QGO71-QGQ71-QGS71 | QGU71: SEGUROS | QGV71: RIMAC SEGUROS | QGX71: 1086478942 | QHA71: 45341 | QHD71: 218.95 | QHI71: =+QHE71-QHG71-QHI71 | QHK71: SEGUROS | QHL71: RIMAC SEGUROS | QHN71: 1086478942 | QHQ71: 45341 | QHT71: 218.95 | QHY71: =+QHU71-QHW71-QHY71 | QIA71: SEGUROS | QIB71: RIMAC SEGUROS | QID71: 1086478942 | QIG71: 45341 | QIJ71: 218.95 | QIO71: =+QIK71-QIM71-QIO71 | QIQ71: SEGUROS | QIR71: RIMAC SEGUROS | QIT71: 1086478942 | QIW71: 45341 | QIZ71: 218.95 | QJE71: =+QJA71-QJC71-QJE71 | QJG71: SEGUROS | QJH71: RIMAC SEGUROS | QJJ71: 1086478942 | QJM71: 45341 | QJP71: 218.95 | QJU71: =+QJQ71-QJS71-QJU71 | QJW71: SEGUROS | QJX71: RIMAC SEGUROS | QJZ71: 1086478942 | QKC71: 45341 | QKF71: 218.95 | QKK71: =+QKG71-QKI71-QKK71 | QKM71: SEGUROS | QKN71: RIMAC SEGUROS | QKP71: 1086478942 | QKS71: 45341 | QKV71: 218.95 | QLA71: =+QKW71-QKY71-QLA71 | QLC71: SEGUROS | QLD71: RIMAC SEGUROS | QLF71: 1086478942 | QLI71: 45341 | QLL71: 218.95 | QLQ71: =+QLM71-QLO71-QLQ71 | QLS71: SEGUROS | QLT71: RIMAC SEGUROS | QLV71: 1086478942 | QLY71: 45341 | QMB71: 218.95 | QMG71: =+QMC71-QME71-QMG71 | QMI71: SEGUROS | QMJ71: RIMAC SEGUROS | QML71: 1086478942 | QMO71: 45341 | QMR71: 218.95 | QMW71: =+QMS71-QMU71-QMW71 | QMY71: SEGUROS | QMZ71: RIMAC SEGUROS | QNB71: 1086478942 | QNE71: 45341 | QNH71: 218.95 | QNM71: =+QNI71-QNK71-QNM71 | QNO71: SEGUROS | QNP71: RIMAC SEGUROS | QNR71: 1086478942 | QNU71: 45341 | QNX71: 218.95 | QOC71: =+QNY71-QOA71-QOC71 | QOE71: SEGUROS | QOF71: RIMAC SEGUROS | QOH71: 1086478942 | QOK71: 45341 | QON71: 218.95 | QOS71: =+QOO71-QOQ71-QOS71 | QOU71: SEGUROS | QOV71: RIMAC SEGUROS | QOX71: 1086478942 | QPA71: 45341 | QPD71: 218.95 | QPI71: =+QPE71-QPG71-QPI71 | QPK71: SEGUROS | QPL71: RIMAC SEGUROS | QPN71: 1086478942 | QPQ71: 45341 | QPT71: 218.95 | QPY71: =+QPU71-QPW71-QPY71 | QQA71: SEGUROS | QQB71: RIMAC SEGUROS | QQD71: 1086478942 | QQG71: 45341 | QQJ71: 218.95 | QQO71: =+QQK71-QQM71-QQO71 | QQQ71: SEGUROS | QQR71: RIMAC SEGUROS | QQT71: 1086478942 | QQW71: 45341 | QQZ71: 218.95 | QRE71: =+QRA71-QRC71-QRE71 | QRG71: SEGUROS | QRH71: RIMAC SEGUROS | QRJ71: 1086478942 | QRM71: 45341 | QRP71: 218.95 | QRU71: =+QRQ71-QRS71-QRU71 | QRW71: SEGUROS | QRX71: RIMAC SEGUROS | QRZ71: 1086478942 | QSC71: 45341 | QSF71: 218.95 | QSK71: =+QSG71-QSI71-QSK71 | QSM71: SEGUROS | QSN71: RIMAC SEGUROS | QSP71: 1086478942 | QSS71: 45341 | QSV71: 218.95 | QTA71: =+QSW71-QSY71-QTA71 | QTC71: SEGUROS | QTD71: RIMAC SEGUROS | QTF71: 1086478942 | QTI71: 45341 | QTL71: 218.95 | QTQ71: =+QTM71-QTO71-QTQ71 | QTS71: SEGUROS | QTT71: RIMAC SEGUROS | QTV71: 1086478942 | QTY71: 45341 | QUB71: 218.95 | QUG71: =+QUC71-QUE71-QUG71 | QUI71: SEGUROS | QUJ71: RIMAC SEGUROS | QUL71: 1086478942 | QUO71: 45341 | QUR71: 218.95 | QUW71: =+QUS71-QUU71-QUW71 | QUY71: SEGUROS | QUZ71: RIMAC SEGUROS | QVB71: 1086478942 | QVE71: 45341 | QVH71: 218.95 | QVM71: =+QVI71-QVK71-QVM71 | QVO71: SEGUROS | QVP71: RIMAC SEGUROS | QVR71: 1086478942 | QVU71: 45341 | QVX71: 218.95 | QWC71: =+QVY71-QWA71-QWC71 | QWE71: SEGUROS | QWF71: RIMAC SEGUROS | QWH71: 1086478942 | QWK71: 45341 | QWN71: 218.95 | QWS71: =+QWO71-QWQ71-QWS71 | QWU71: SEGUROS | QWV71: RIMAC SEGUROS | QWX71: 1086478942 | QXA71: 45341 | QXD71: 218.95 | QXI71: =+QXE71-QXG71-QXI71 | QXK71: SEGUROS | QXL71: RIMAC SEGUROS | QXN71: 1086478942 | QXQ71: 45341 | QXT71: 218.95 | QXY71: =+QXU71-QXW71-QXY71 | QYA71: SEGUROS | QYB71: RIMAC SEGUROS | QYD71: 1086478942 | QYG71: 45341 | QYJ71: 218.95 | QYO71: =+QYK71-QYM71-QYO71 | QYQ71: SEGUROS | QYR71: RIMAC SEGUROS | QYT71: 1086478942 | QYW71: 45341 | QYZ71: 218.95 | QZE71: =+QZA71-QZC71-QZE71 | QZG71: SEGUROS | QZH71: RIMAC SEGUROS | QZJ71: 1086478942 | QZM71: 45341 | QZP71: 218.95 | QZU71: =+QZQ71-QZS71-QZU71 | QZW71: SEGUROS | QZX71: RIMAC SEGUROS | QZZ71: 1086478942 | RAC71: 45341 | RAF71: 218.95 | RAK71: =+RAG71-RAI71-RAK71 | RAM71: SEGUROS | RAN71: RIMAC SEGUROS | RAP71: 1086478942 | RAS71: 45341 | RAV71: 218.95 | RBA71: =+RAW71-RAY71-RBA71 | RBC71: SEGUROS | RBD71: RIMAC SEGUROS | RBF71: 1086478942 | RBI71: 45341 | RBL71: 218.95 | RBQ71: =+RBM71-RBO71-RBQ71 | RBS71: SEGUROS | RBT71: RIMAC SEGUROS | RBV71: 1086478942 | RBY71: 45341 | RCB71: 218.95 | RCG71: =+RCC71-RCE71-RCG71 | RCI71: SEGUROS | RCJ71: RIMAC SEGUROS | RCL71: 1086478942 | RCO71: 45341 | RCR71: 218.95 | RCW71: =+RCS71-RCU71-RCW71 | RCY71: SEGUROS | RCZ71: RIMAC SEGUROS | RDB71: 1086478942 | RDE71: 45341 | RDH71: 218.95 | RDM71: =+RDI71-RDK71-RDM71 | RDO71: SEGUROS | RDP71: RIMAC SEGUROS | RDR71: 1086478942 | RDU71: 45341 | RDX71: 218.95 | REC71: =+RDY71-REA71-REC71 | REE71: SEGUROS | REF71: RIMAC SEGUROS | REH71: 1086478942 | REK71: 45341 | REN71: 218.95 | RES71: =+REO71-REQ71-RES71 | REU71: SEGUROS | REV71: RIMAC SEGUROS | REX71: 1086478942 | RFA71: 45341 | RFD71: 218.95 | RFI71: =+RFE71-RFG71-RFI71 | RFK71: SEGUROS | RFL71: RIMAC SEGUROS | RFN71: 1086478942 | RFQ71: 45341 | RFT71: 218.95 | RFY71: =+RFU71-RFW71-RFY71 | RGA71: SEGUROS | RGB71: RIMAC SEGUROS | RGD71: 1086478942 | RGG71: 45341 | RGJ71: 218.95 | RGO71: =+RGK71-RGM71-RGO71 | RGQ71: SEGUROS | RGR71: RIMAC SEGUROS | RGT71: 1086478942 | RGW71: 45341 | RGZ71: 218.95 | RHE71: =+RHA71-RHC71-RHE71 | RHG71: SEGUROS | RHH71: RIMAC SEGUROS | RHJ71: 1086478942 | RHM71: 45341 | RHP71: 218.95 | RHU71: =+RHQ71-RHS71-RHU71 | RHW71: SEGUROS | RHX71: RIMAC SEGUROS | RHZ71: 1086478942 | RIC71: 45341 | RIF71: 218.95 | RIK71: =+RIG71-RII71-RIK71 | RIM71: SEGUROS | RIN71: RIMAC SEGUROS | RIP71: 1086478942 | RIS71: 45341 | RIV71: 218.95 | RJA71: =+RIW71-RIY71-RJA71 | RJC71: SEGUROS | RJD71: RIMAC SEGUROS | RJF71: 1086478942 | RJI71: 45341 | RJL71: 218.95 | RJQ71: =+RJM71-RJO71-RJQ71 | RJS71: SEGUROS | RJT71: RIMAC SEGUROS | RJV71: 1086478942 | RJY71: 45341 | RKB71: 218.95 | RKG71: =+RKC71-RKE71-RKG71 | RKI71: SEGUROS | RKJ71: RIMAC SEGUROS | RKL71: 1086478942 | RKO71: 45341 | RKR71: 218.95 | RKW71: =+RKS71-RKU71-RKW71 | RKY71: SEGUROS | RKZ71: RIMAC SEGUROS | RLB71: 1086478942 | RLE71: 45341 | RLH71: 218.95 | RLM71: =+RLI71-RLK71-RLM71 | RLO71: SEGUROS | RLP71: RIMAC SEGUROS | RLR71: 1086478942 | RLU71: 45341 | RLX71: 218.95 | RMC71: =+RLY71-RMA71-RMC71 | RME71: SEGUROS | RMF71: RIMAC SEGUROS | RMH71: 1086478942 | RMK71: 45341 | RMN71: 218.95 | RMS71: =+RMO71-RMQ71-RMS71 | RMU71: SEGUROS | RMV71: RIMAC SEGUROS | RMX71: 1086478942 | RNA71: 45341 | RND71: 218.95 | RNI71: =+RNE71-RNG71-RNI71 | RNK71: SEGUROS | RNL71: RIMAC SEGUROS | RNN71: 1086478942 | RNQ71: 45341 | RNT71: 218.95 | RNY71: =+RNU71-RNW71-RNY71 | ROA71: SEGUROS | ROB71: RIMAC SEGUROS | ROD71: 1086478942 | ROG71: 45341 | ROJ71: 218.95 | ROO71: =+ROK71-ROM71-ROO71 | ROQ71: SEGUROS | ROR71: RIMAC SEGUROS | ROT71: 1086478942 | ROW71: 45341 | ROZ71: 218.95 | RPE71: =+RPA71-RPC71-RPE71 | RPG71: SEGUROS | RPH71: RIMAC SEGUROS | RPJ71: 1086478942 | RPM71: 45341 | RPP71: 218.95 | RPU71: =+RPQ71-RPS71-RPU71 | RPW71: SEGUROS | RPX71: RIMAC SEGUROS | RPZ71: 1086478942 | RQC71: 45341 | RQF71: 218.95 | RQK71: =+RQG71-RQI71-RQK71 | RQM71: SEGUROS | RQN71: RIMAC SEGUROS | RQP71: 1086478942 | RQS71: 45341 | RQV71: 218.95 | RRA71: =+RQW71-RQY71-RRA71 | RRC71: SEGUROS | RRD71: RIMAC SEGUROS | RRF71: 1086478942 | RRI71: 45341 | RRL71: 218.95 | RRQ71: =+RRM71-RRO71-RRQ71 | RRS71: SEGUROS | RRT71: RIMAC SEGUROS | RRV71: 1086478942 | RRY71: 45341 | RSB71: 218.95 | RSG71: =+RSC71-RSE71-RSG71 | RSI71: SEGUROS | RSJ71: RIMAC SEGUROS | RSL71: 1086478942 | RSO71: 45341 | RSR71: 218.95 | RSW71: =+RSS71-RSU71-RSW71 | RSY71: SEGUROS | RSZ71: RIMAC SEGUROS | RTB71: 1086478942 | RTE71: 45341 | RTH71: 218.95 | RTM71: =+RTI71-RTK71-RTM71 | RTO71: SEGUROS | RTP71: RIMAC SEGUROS | RTR71: 1086478942 | RTU71: 45341 | RTX71: 218.95 | RUC71: =+RTY71-RUA71-RUC71 | RUE71: SEGUROS | RUF71: RIMAC SEGUROS | RUH71: 1086478942 | RUK71: 45341 | RUN71: 218.95 | RUS71: =+RUO71-RUQ71-RUS71 | RUU71: SEGUROS | RUV71: RIMAC SEGUROS | RUX71: 1086478942 | RVA71: 45341 | RVD71: 218.95 | RVI71: =+RVE71-RVG71-RVI71 | RVK71: SEGUROS | RVL71: RIMAC SEGUROS | RVN71: 1086478942 | RVQ71: 45341 | RVT71: 218.95 | RVY71: =+RVU71-RVW71-RVY71 | RWA71: SEGUROS | RWB71: RIMAC SEGUROS | RWD71: 1086478942 | RWG71: 45341 | RWJ71: 218.95 | RWO71: =+RWK71-RWM71-RWO71 | RWQ71: SEGUROS | RWR71: RIMAC SEGUROS | RWT71: 1086478942 | RWW71: 45341 | RWZ71: 218.95 | RXE71: =+RXA71-RXC71-RXE71 | RXG71: SEGUROS | RXH71: RIMAC SEGUROS | RXJ71: 1086478942 | RXM71: 45341 | RXP71: 218.95 | RXU71: =+RXQ71-RXS71-RXU71 | RXW71: SEGUROS | RXX71: RIMAC SEGUROS | RXZ71: 1086478942 | RYC71: 45341 | RYF71: 218.95 | RYK71: =+RYG71-RYI71-RYK71 | RYM71: SEGUROS | RYN71: RIMAC SEGUROS | RYP71: 1086478942 | RYS71: 45341 | RYV71: 218.95 | RZA71: =+RYW71-RYY71-RZA71 | RZC71: SEGUROS | RZD71: RIMAC SEGUROS | RZF71: 1086478942 | RZI71: 45341 | RZL71: 218.95 | RZQ71: =+RZM71-RZO71-RZQ71 | RZS71: SEGUROS | RZT71: RIMAC SEGUROS | RZV71: 1086478942 | RZY71: 45341 | SAB71: 218.95 | SAG71: =+SAC71-SAE71-SAG71 | SAI71: SEGUROS | SAJ71: RIMAC SEGUROS | SAL71: 1086478942 | SAO71: 45341 | SAR71: 218.95 | SAW71: =+SAS71-SAU71-SAW71 | SAY71: SEGUROS | SAZ71: RIMAC SEGUROS | SBB71: 1086478942 | SBE71: 45341 | SBH71: 218.95 | SBM71: =+SBI71-SBK71-SBM71 | SBO71: SEGUROS | SBP71: RIMAC SEGUROS | SBR71: 1086478942 | SBU71: 45341 | SBX71: 218.95 | SCC71: =+SBY71-SCA71-SCC71 | SCE71: SEGUROS | SCF71: RIMAC SEGUROS | SCH71: 1086478942 | SCK71: 45341 | SCN71: 218.95 | SCS71: =+SCO71-SCQ71-SCS71 | SCU71: SEGUROS | SCV71: RIMAC SEGUROS | SCX71: 1086478942 | SDA71: 45341 | SDD71: 218.95 | SDI71: =+SDE71-SDG71-SDI71 | SDK71: SEGUROS | SDL71: RIMAC SEGUROS | SDN71: 1086478942 | SDQ71: 45341 | SDT71: 218.95 | SDY71: =+SDU71-SDW71-SDY71 | SEA71: SEGUROS | SEB71: RIMAC SEGUROS | SED71: 1086478942 | SEG71: 45341 | SEJ71: 218.95 | SEO71: =+SEK71-SEM71-SEO71 | SEQ71: SEGUROS | SER71: RIMAC SEGUROS | SET71: 1086478942 | SEW71: 45341 | SEZ71: 218.95 | SFE71: =+SFA71-SFC71-SFE71 | SFG71: SEGUROS | SFH71: RIMAC SEGUROS | SFJ71: 1086478942 | SFM71: 45341 | SFP71: 218.95 | SFU71: =+SFQ71-SFS71-SFU71 | SFW71: SEGUROS | SFX71: RIMAC SEGUROS | SFZ71: 1086478942 | SGC71: 45341 | SGF71: 218.95 | SGK71: =+SGG71-SGI71-SGK71 | SGM71: SEGUROS | SGN71: RIMAC SEGUROS | SGP71: 1086478942 | SGS71: 45341 | SGV71: 218.95 | SHA71: =+SGW71-SGY71-SHA71 | SHC71: SEGUROS | SHD71: RIMAC SEGUROS | SHF71: 1086478942 | SHI71: 45341 | SHL71: 218.95 | SHQ71: =+SHM71-SHO71-SHQ71 | SHS71: SEGUROS | SHT71: RIMAC SEGUROS | SHV71: 1086478942 | SHY71: 45341 | SIB71: 218.95 | SIG71: =+SIC71-SIE71-SIG71 | SII71: SEGUROS | SIJ71: RIMAC SEGUROS | SIL71: 1086478942 | SIO71: 45341 | SIR71: 218.95 | SIW71: =+SIS71-SIU71-SIW71 | SIY71: SEGUROS | SIZ71: RIMAC SEGUROS | SJB71: 1086478942 | SJE71: 45341 | SJH71: 218.95 | SJM71: =+SJI71-SJK71-SJM71 | SJO71: SEGUROS | SJP71: RIMAC SEGUROS | SJR71: 1086478942 | SJU71: 45341 | SJX71: 218.95 | SKC71: =+SJY71-SKA71-SKC71 | SKE71: SEGUROS | SKF71: RIMAC SEGUROS | SKH71: 1086478942 | SKK71: 45341 | SKN71: 218.95 | SKS71: =+SKO71-SKQ71-SKS71 | SKU71: SEGUROS | SKV71: RIMAC SEGUROS | SKX71: 1086478942 | SLA71: 45341 | SLD71: 218.95 | SLI71: =+SLE71-SLG71-SLI71 | SLK71: SEGUROS | SLL71: RIMAC SEGUROS | SLN71: 1086478942 | SLQ71: 45341 | SLT71: 218.95 | SLY71: =+SLU71-SLW71-SLY71 | SMA71: SEGUROS | SMB71: RIMAC SEGUROS | SMD71: 1086478942 | SMG71: 45341 | SMJ71: 218.95 | SMO71: =+SMK71-SMM71-SMO71 | SMQ71: SEGUROS | SMR71: RIMAC SEGUROS | SMT71: 1086478942 | SMW71: 45341 | SMZ71: 218.95 | SNE71: =+SNA71-SNC71-SNE71 | SNG71: SEGUROS | SNH71: RIMAC SEGUROS | SNJ71: 1086478942 | SNM71: 45341 | SNP71: 218.95 | SNU71: =+SNQ71-SNS71-SNU71 | SNW71: SEGUROS | SNX71: RIMAC SEGUROS | SNZ71: 1086478942 | SOC71: 45341 | SOF71: 218.95 | SOK71: =+SOG71-SOI71-SOK71 | SOM71: SEGUROS | SON71: RIMAC SEGUROS | SOP71: 1086478942 | SOS71: 45341 | SOV71: 218.95 | SPA71: =+SOW71-SOY71-SPA71 | SPC71: SEGUROS | SPD71: RIMAC SEGUROS | SPF71: 1086478942 | SPI71: 45341 | SPL71: 218.95 | SPQ71: =+SPM71-SPO71-SPQ71 | SPS71: SEGUROS | SPT71: RIMAC SEGUROS | SPV71: 1086478942 | SPY71: 45341 | SQB71: 218.95 | SQG71: =+SQC71-SQE71-SQG71 | SQI71: SEGUROS | SQJ71: RIMAC SEGUROS | SQL71: 1086478942 | SQO71: 45341 | SQR71: 218.95 | SQW71: =+SQS71-SQU71-SQW71 | SQY71: SEGUROS | SQZ71: RIMAC SEGUROS | SRB71: 1086478942 | SRE71: 45341 | SRH71: 218.95 | SRM71: =+SRI71-SRK71-SRM71 | SRO71: SEGUROS | SRP71: RIMAC SEGUROS | SRR71: 1086478942 | SRU71: 45341 | SRX71: 218.95 | SSC71: =+SRY71-SSA71-SSC71 | SSE71: SEGUROS | SSF71: RIMAC SEGUROS | SSH71: 1086478942 | SSK71: 45341 | SSN71: 218.95 | SSS71: =+SSO71-SSQ71-SSS71 | SSU71: SEGUROS | SSV71: RIMAC SEGUROS | SSX71: 1086478942 | STA71: 45341 | STD71: 218.95 | STI71: =+STE71-STG71-STI71 | STK71: SEGUROS | STL71: RIMAC SEGUROS | STN71: 1086478942 | STQ71: 45341 | STT71: 218.95 | STY71: =+STU71-STW71-STY71 | SUA71: SEGUROS | SUB71: RIMAC SEGUROS | SUD71: 1086478942 | SUG71: 45341 | SUJ71: 218.95 | SUO71: =+SUK71-SUM71-SUO71 | SUQ71: SEGUROS | SUR71: RIMAC SEGUROS | SUT71: 1086478942 | SUW71: 45341 | SUZ71: 218.95 | SVE71: =+SVA71-SVC71-SVE71 | SVG71: SEGUROS | SVH71: RIMAC SEGUROS | SVJ71: 1086478942 | SVM71: 45341 | SVP71: 218.95 | SVU71: =+SVQ71-SVS71-SVU71 | SVW71: SEGUROS | SVX71: RIMAC SEGUROS | SVZ71: 1086478942 | SWC71: 45341 | SWF71: 218.95 | SWK71: =+SWG71-SWI71-SWK71 | SWM71: SEGUROS | SWN71: RIMAC SEGUROS | SWP71: 1086478942 | SWS71: 45341 | SWV71: 218.95 | SXA71: =+SWW71-SWY71-SXA71 | SXC71: SEGUROS | SXD71: RIMAC SEGUROS | SXF71: 1086478942 | SXI71: 45341 | SXL71: 218.95 | SXQ71: =+SXM71-SXO71-SXQ71 | SXS71: SEGUROS | SXT71: RIMAC SEGUROS | SXV71: 1086478942 | SXY71: 45341 | SYB71: 218.95 | SYG71: =+SYC71-SYE71-SYG71 | SYI71: SEGUROS | SYJ71: RIMAC SEGUROS | SYL71: 1086478942 | SYO71: 45341 | SYR71: 218.95 | SYW71: =+SYS71-SYU71-SYW71 | SYY71: SEGUROS | SYZ71: RIMAC SEGUROS | SZB71: 1086478942 | SZE71: 45341 | SZH71: 218.95 | SZM71: =+SZI71-SZK71-SZM71 | SZO71: SEGUROS | SZP71: RIMAC SEGUROS | SZR71: 1086478942 | SZU71: 45341 | SZX71: 218.95 | TAC71: =+SZY71-TAA71-TAC71 | TAE71: SEGUROS | TAF71: RIMAC SEGUROS | TAH71: 1086478942 | TAK71: 45341 | TAN71: 218.95 | TAS71: =+TAO71-TAQ71-TAS71 | TAU71: SEGUROS | TAV71: RIMAC SEGUROS | TAX71: 1086478942 | TBA71: 45341 | TBD71: 218.95 | TBI71: =+TBE71-TBG71-TBI71 | TBK71: SEGUROS | TBL71: RIMAC SEGUROS | TBN71: 1086478942 | TBQ71: 45341 | TBT71: 218.95 | TBY71: =+TBU71-TBW71-TBY71 | TCA71: SEGUROS | TCB71: RIMAC SEGUROS | TCD71: 1086478942 | TCG71: 45341 | TCJ71: 218.95 | TCO71: =+TCK71-TCM71-TCO71 | TCQ71: SEGUROS | TCR71: RIMAC SEGUROS | TCT71: 1086478942 | TCW71: 45341 | TCZ71: 218.95 | TDE71: =+TDA71-TDC71-TDE71 | TDG71: SEGUROS | TDH71: RIMAC SEGUROS | TDJ71: 1086478942 | TDM71: 45341 | TDP71: 218.95 | TDU71: =+TDQ71-TDS71-TDU71 | TDW71: SEGUROS | TDX71: RIMAC SEGUROS | TDZ71: 1086478942 | TEC71: 45341 | TEF71: 218.95 | TEK71: =+TEG71-TEI71-TEK71 | TEM71: SEGUROS | TEN71: RIMAC SEGUROS | TEP71: 1086478942 | TES71: 45341 | TEV71: 218.95 | TFA71: =+TEW71-TEY71-TFA71 | TFC71: SEGUROS | TFD71: RIMAC SEGUROS | TFF71: 1086478942 | TFI71: 45341 | TFL71: 218.95 | TFQ71: =+TFM71-TFO71-TFQ71 | TFS71: SEGUROS | TFT71: RIMAC SEGUROS | TFV71: 1086478942 | TFY71: 45341 | TGB71: 218.95 | TGG71: =+TGC71-TGE71-TGG71 | TGI71: SEGUROS | TGJ71: RIMAC SEGUROS | TGL71: 1086478942 | TGO71: 45341 | TGR71: 218.95 | TGW71: =+TGS71-TGU71-TGW71 | TGY71: SEGUROS | TGZ71: RIMAC SEGUROS | THB71: 1086478942 | THE71: 45341 | THH71: 218.95 | THM71: =+THI71-THK71-THM71 | THO71: SEGUROS | THP71: RIMAC SEGUROS | THR71: 1086478942 | THU71: 45341 | THX71: 218.95 | TIC71: =+THY71-TIA71-TIC71 | TIE71: SEGUROS | TIF71: RIMAC SEGUROS | TIH71: 1086478942 | TIK71: 45341 | TIN71: 218.95 | TIS71: =+TIO71-TIQ71-TIS71 | TIU71: SEGUROS | TIV71: RIMAC SEGUROS | TIX71: 1086478942 | TJA71: 45341 | TJD71: 218.95 | TJI71: =+TJE71-TJG71-TJI71 | TJK71: SEGUROS | TJL71: RIMAC SEGUROS | TJN71: 1086478942 | TJQ71: 45341 | TJT71: 218.95 | TJY71: =+TJU71-TJW71-TJY71 | TKA71: SEGUROS | TKB71: RIMAC SEGUROS | TKD71: 1086478942 | TKG71: 45341 | TKJ71: 218.95 | TKO71: =+TKK71-TKM71-TKO71 | TKQ71: SEGUROS | TKR71: RIMAC SEGUROS | TKT71: 1086478942 | TKW71: 45341 | TKZ71: 218.95 | TLE71: =+TLA71-TLC71-TLE71 | TLG71: SEGUROS | TLH71: RIMAC SEGUROS | TLJ71: 1086478942 | TLM71: 45341 | TLP71: 218.95 | TLU71: =+TLQ71-TLS71-TLU71 | TLW71: SEGUROS | TLX71: RIMAC SEGUROS | TLZ71: 1086478942 | TMC71: 45341 | TMF71: 218.95 | TMK71: =+TMG71-TMI71-TMK71 | TMM71: SEGUROS | TMN71: RIMAC SEGUROS | TMP71: 1086478942 | TMS71: 45341 | TMV71: 218.95 | TNA71: =+TMW71-TMY71-TNA71 | TNC71: SEGUROS | TND71: RIMAC SEGUROS | TNF71: 1086478942 | TNI71: 45341 | TNL71: 218.95 | TNQ71: =+TNM71-TNO71-TNQ71 | TNS71: SEGUROS | TNT71: RIMAC SEGUROS | TNV71: 1086478942 | TNY71: 45341 | TOB71: 218.95 | TOG71: =+TOC71-TOE71-TOG71 | TOI71: SEGUROS | TOJ71: RIMAC SEGUROS | TOL71: 1086478942 | TOO71: 45341 | TOR71: 218.95 | TOW71: =+TOS71-TOU71-TOW71 | TOY71: SEGUROS | TOZ71: RIMAC SEGUROS | TPB71: 1086478942 | TPE71: 45341 | TPH71: 218.95 | TPM71: =+TPI71-TPK71-TPM71 | TPO71: SEGUROS | TPP71: RIMAC SEGUROS | TPR71: 1086478942 | TPU71: 45341 | TPX71: 218.95 | TQC71: =+TPY71-TQA71-TQC71 | TQE71: SEGUROS | TQF71: RIMAC SEGUROS | TQH71: 1086478942 | TQK71: 45341 | TQN71: 218.95 | TQS71: =+TQO71-TQQ71-TQS71 | TQU71: SEGUROS | TQV71: RIMAC SEGUROS | TQX71: 1086478942 | TRA71: 45341 | TRD71: 218.95 | TRI71: =+TRE71-TRG71-TRI71 | TRK71: SEGUROS | TRL71: RIMAC SEGUROS | TRN71: 1086478942 | TRQ71: 45341 | TRT71: 218.95 | TRY71: =+TRU71-TRW71-TRY71 | TSA71: SEGUROS | TSB71: RIMAC SEGUROS | TSD71: 1086478942 | TSG71: 45341 | TSJ71: 218.95 | TSO71: =+TSK71-TSM71-TSO71 | TSQ71: SEGUROS | TSR71: RIMAC SEGUROS | TST71: 1086478942 | TSW71: 45341 | TSZ71: 218.95 | TTE71: =+TTA71-TTC71-TTE71 | TTG71: SEGUROS | TTH71: RIMAC SEGUROS | TTJ71: 1086478942 | TTM71: 45341 | TTP71: 218.95 | TTU71: =+TTQ71-TTS71-TTU71 | TTW71: SEGUROS | TTX71: RIMAC SEGUROS | TTZ71: 1086478942 | TUC71: 45341 | TUF71: 218.95 | TUK71: =+TUG71-TUI71-TUK71 | TUM71: SEGUROS | TUN71: RIMAC SEGUROS | TUP71: 1086478942 | TUS71: 45341 | TUV71: 218.95 | TVA71: =+TUW71-TUY71-TVA71 | TVC71: SEGUROS | TVD71: RIMAC SEGUROS | TVF71: 1086478942 | TVI71: 45341 | TVL71: 218.95 | TVQ71: =+TVM71-TVO71-TVQ71 | TVS71: SEGUROS | TVT71: RIMAC SEGUROS | TVV71: 1086478942 | TVY71: 45341 | TWB71: 218.95 | TWG71: =+TWC71-TWE71-TWG71 | TWI71: SEGUROS | TWJ71: RIMAC SEGUROS | TWL71: 1086478942 | TWO71: 45341 | TWR71: 218.95 | TWW71: =+TWS71-TWU71-TWW71 | TWY71: SEGUROS | TWZ71: RIMAC SEGUROS | TXB71: 1086478942 | TXE71: 45341 | TXH71: 218.95 | TXM71: =+TXI71-TXK71-TXM71 | TXO71: SEGUROS | TXP71: RIMAC SEGUROS | TXR71: 1086478942 | TXU71: 45341 | TXX71: 218.95 | TYC71: =+TXY71-TYA71-TYC71 | TYE71: SEGUROS | TYF71: RIMAC SEGUROS | TYH71: 1086478942 | TYK71: 45341 | TYN71: 218.95 | TYS71: =+TYO71-TYQ71-TYS71 | TYU71: SEGUROS | TYV71: RIMAC SEGUROS | TYX71: 1086478942 | TZA71: 45341 | TZD71: 218.95 | TZI71: =+TZE71-TZG71-TZI71 | TZK71: SEGUROS | TZL71: RIMAC SEGUROS | TZN71: 1086478942 | TZQ71: 45341 | TZT71: 218.95 | TZY71: =+TZU71-TZW71-TZY71 | UAA71: SEGUROS | UAB71: RIMAC SEGUROS | UAD71: 1086478942 | UAG71: 45341 | UAJ71: 218.95 | UAO71: =+UAK71-UAM71-UAO71 | UAQ71: SEGUROS | UAR71: RIMAC SEGUROS | UAT71: 1086478942 | UAW71: 45341 | UAZ71: 218.95 | UBE71: =+UBA71-UBC71-UBE71 | UBG71: SEGUROS | UBH71: RIMAC SEGUROS | UBJ71: 1086478942 | UBM71: 45341 | UBP71: 218.95 | UBU71: =+UBQ71-UBS71-UBU71 | UBW71: SEGUROS | UBX71: RIMAC SEGUROS | UBZ71: 1086478942 | UCC71: 45341 | UCF71: 218.95 | UCK71: =+UCG71-UCI71-UCK71 | UCM71: SEGUROS | UCN71: RIMAC SEGUROS | UCP71: 1086478942 | UCS71: 45341 | UCV71: 218.95 | UDA71: =+UCW71-UCY71-UDA71 | UDC71: SEGUROS | UDD71: RIMAC SEGUROS | UDF71: 1086478942 | UDI71: 45341 | UDL71: 218.95 | UDQ71: =+UDM71-UDO71-UDQ71 | UDS71: SEGUROS | UDT71: RIMAC SEGUROS | UDV71: 1086478942 | UDY71: 45341 | UEB71: 218.95 | UEG71: =+UEC71-UEE71-UEG71 | UEI71: SEGUROS | UEJ71: RIMAC SEGUROS | UEL71: 1086478942 | UEO71: 45341 | UER71: 218.95 | UEW71: =+UES71-UEU71-UEW71 | UEY71: SEGUROS | UEZ71: RIMAC SEGUROS | UFB71: 1086478942 | UFE71: 45341 | UFH71: 218.95 | UFM71: =+UFI71-UFK71-UFM71 | UFO71: SEGUROS | UFP71: RIMAC SEGUROS | UFR71: 1086478942 | UFU71: 45341 | UFX71: 218.95 | UGC71: =+UFY71-UGA71-UGC71 | UGE71: SEGUROS | UGF71: RIMAC SEGUROS | UGH71: 1086478942 | UGK71: 45341 | UGN71: 218.95 | UGS71: =+UGO71-UGQ71-UGS71 | UGU71: SEGUROS | UGV71: RIMAC SEGUROS | UGX71: 1086478942 | UHA71: 45341 | UHD71: 218.95 | UHI71: =+UHE71-UHG71-UHI71 | UHK71: SEGUROS | UHL71: RIMAC SEGUROS | UHN71: 1086478942 | UHQ71: 45341 | UHT71: 218.95 | UHY71: =+UHU71-UHW71-UHY71 | UIA71: SEGUROS | UIB71: RIMAC SEGUROS | UID71: 1086478942 | UIG71: 45341 | UIJ71: 218.95 | UIO71: =+UIK71-UIM71-UIO71 | UIQ71: SEGUROS | UIR71: RIMAC SEGUROS | UIT71: 1086478942 | UIW71: 45341 | UIZ71: 218.95 | UJE71: =+UJA71-UJC71-UJE71 | UJG71: SEGUROS | UJH71: RIMAC SEGUROS | UJJ71: 1086478942 | UJM71: 45341 | UJP71: 218.95 | UJU71: =+UJQ71-UJS71-UJU71 | UJW71: SEGUROS | UJX71: RIMAC SEGUROS | UJZ71: 1086478942 | UKC71: 45341 | UKF71: 218.95 | UKK71: =+UKG71-UKI71-UKK71 | UKM71: SEGUROS | UKN71: RIMAC SEGUROS | UKP71: 1086478942 | UKS71: 45341 | UKV71: 218.95 | ULA71: =+UKW71-UKY71-ULA71 | ULC71: SEGUROS | ULD71: RIMAC SEGUROS | ULF71: 1086478942 | ULI71: 45341 | ULL71: 218.95 | ULQ71: =+ULM71-ULO71-ULQ71 | ULS71: SEGUROS | ULT71: RIMAC SEGUROS | ULV71: 1086478942 | ULY71: 45341 | UMB71: 218.95 | UMG71: =+UMC71-UME71-UMG71 | UMI71: SEGUROS | UMJ71: RIMAC SEGUROS | UML71: 1086478942 | UMO71: 45341 | UMR71: 218.95 | UMW71: =+UMS71-UMU71-UMW71 | UMY71: SEGUROS | UMZ71: RIMAC SEGUROS | UNB71: 1086478942 | UNE71: 45341 | UNH71: 218.95 | UNM71: =+UNI71-UNK71-UNM71 | UNO71: SEGUROS | UNP71: RIMAC SEGUROS | UNR71: 1086478942 | UNU71: 45341 | UNX71: 218.95 | UOC71: =+UNY71-UOA71-UOC71 | UOE71: SEGUROS | UOF71: RIMAC SEGUROS | UOH71: 1086478942 | UOK71: 45341 | UON71: 218.95 | UOS71: =+UOO71-UOQ71-UOS71 | UOU71: SEGUROS | UOV71: RIMAC SEGUROS | UOX71: 1086478942 | UPA71: 45341 | UPD71: 218.95 | UPI71: =+UPE71-UPG71-UPI71 | UPK71: SEGUROS | UPL71: RIMAC SEGUROS | UPN71: 1086478942 | UPQ71: 45341 | UPT71: 218.95 | UPY71: =+UPU71-UPW71-UPY71 | UQA71: SEGUROS | UQB71: RIMAC SEGUROS | UQD71: 1086478942 | UQG71: 45341 | UQJ71: 218.95 | UQO71: =+UQK71-UQM71-UQO71 | UQQ71: SEGUROS | UQR71: RIMAC SEGUROS | UQT71: 1086478942 | UQW71: 45341 | UQZ71: 218.95 | URE71: =+URA71-URC71-URE71 | URG71: SEGUROS | URH71: RIMAC SEGUROS | URJ71: 1086478942 | URM71: 45341 | URP71: 218.95 | URU71: =+URQ71-URS71-URU71 | URW71: SEGUROS | URX71: RIMAC SEGUROS | URZ71: 1086478942 | USC71: 45341 | USF71: 218.95 | USK71: =+USG71-USI71-USK71 | USM71: SEGUROS | USN71: RIMAC SEGUROS | USP71: 1086478942 | USS71: 45341 | USV71: 218.95 | UTA71: =+USW71-USY71-UTA71 | UTC71: SEGUROS | UTD71: RIMAC SEGUROS | UTF71: 1086478942 | UTI71: 45341 | UTL71: 218.95 | UTQ71: =+UTM71-UTO71-UTQ71 | UTS71: SEGUROS | UTT71: RIMAC SEGUROS | UTV71: 1086478942 | UTY71: 45341 | UUB71: 218.95 | UUG71: =+UUC71-UUE71-UUG71 | UUI71: SEGUROS | UUJ71: RIMAC SEGUROS | UUL71: 1086478942 | UUO71: 45341 | UUR71: 218.95 | UUW71: =+UUS71-UUU71-UUW71 | UUY71: SEGUROS | UUZ71: RIMAC SEGUROS | UVB71: 1086478942 | UVE71: 45341 | UVH71: 218.95 | UVM71: =+UVI71-UVK71-UVM71 | UVO71: SEGUROS | UVP71: RIMAC SEGUROS | UVR71: 1086478942 | UVU71: 45341 | UVX71: 218.95 | UWC71: =+UVY71-UWA71-UWC71 | UWE71: SEGUROS | UWF71: RIMAC SEGUROS | UWH71: 1086478942 | UWK71: 45341 | UWN71: 218.95 | UWS71: =+UWO71-UWQ71-UWS71 | UWU71: SEGUROS | UWV71: RIMAC SEGUROS | UWX71: 1086478942 | UXA71: 45341 | UXD71: 218.95 | UXI71: =+UXE71-UXG71-UXI71 | UXK71: SEGUROS | UXL71: RIMAC SEGUROS | UXN71: 1086478942 | UXQ71: 45341 | UXT71: 218.95 | UXY71: =+UXU71-UXW71-UXY71 | UYA71: SEGUROS | UYB71: RIMAC SEGUROS | UYD71: 1086478942 | UYG71: 45341 | UYJ71: 218.95 | UYO71: =+UYK71-UYM71-UYO71 | UYQ71: SEGUROS | UYR71: RIMAC SEGUROS | UYT71: 1086478942 | UYW71: 45341 | UYZ71: 218.95 | UZE71: =+UZA71-UZC71-UZE71 | UZG71: SEGUROS | UZH71: RIMAC SEGUROS | UZJ71: 1086478942 | UZM71: 45341 | UZP71: 218.95 | UZU71: =+UZQ71-UZS71-UZU71 | UZW71: SEGUROS | UZX71: RIMAC SEGUROS | UZZ71: 1086478942 | VAC71: 45341 | VAF71: 218.95 | VAK71: =+VAG71-VAI71-VAK71 | VAM71: SEGUROS | VAN71: RIMAC SEGUROS | VAP71: 1086478942 | VAS71: 45341 | VAV71: 218.95 | VBA71: =+VAW71-VAY71-VBA71 | VBC71: SEGUROS | VBD71: RIMAC SEGUROS | VBF71: 1086478942 | VBI71: 45341 | VBL71: 218.95 | VBQ71: =+VBM71-VBO71-VBQ71 | VBS71: SEGUROS | VBT71: RIMAC SEGUROS | VBV71: 1086478942 | VBY71: 45341 | VCB71: 218.95 | VCG71: =+VCC71-VCE71-VCG71 | VCI71: SEGUROS | VCJ71: RIMAC SEGUROS | VCL71: 1086478942 | VCO71: 45341 | VCR71: 218.95 | VCW71: =+VCS71-VCU71-VCW71 | VCY71: SEGUROS | VCZ71: RIMAC SEGUROS | VDB71: 1086478942 | VDE71: 45341 | VDH71: 218.95 | VDM71: =+VDI71-VDK71-VDM71 | VDO71: SEGUROS | VDP71: RIMAC SEGUROS | VDR71: 1086478942 | VDU71: 45341 | VDX71: 218.95 | VEC71: =+VDY71-VEA71-VEC71 | VEE71: SEGUROS | VEF71: RIMAC SEGUROS | VEH71: 1086478942 | VEK71: 45341 | VEN71: 218.95 | VES71: =+VEO71-VEQ71-VES71 | VEU71: SEGUROS | VEV71: RIMAC SEGUROS | VEX71: 1086478942 | VFA71: 45341 | VFD71: 218.95 | VFI71: =+VFE71-VFG71-VFI71 | VFK71: SEGUROS | VFL71: RIMAC SEGUROS | VFN71: 1086478942 | VFQ71: 45341 | VFT71: 218.95 | VFY71: =+VFU71-VFW71-VFY71 | VGA71: SEGUROS | VGB71: RIMAC SEGUROS | VGD71: 1086478942 | VGG71: 45341 | VGJ71: 218.95 | VGO71: =+VGK71-VGM71-VGO71 | VGQ71: SEGUROS | VGR71: RIMAC SEGUROS | VGT71: 1086478942 | VGW71: 45341 | VGZ71: 218.95 | VHE71: =+VHA71-VHC71-VHE71 | VHG71: SEGUROS | VHH71: RIMAC SEGUROS | VHJ71: 1086478942 | VHM71: 45341 | VHP71: 218.95 | VHU71: =+VHQ71-VHS71-VHU71 | VHW71: SEGUROS | VHX71: RIMAC SEGUROS | VHZ71: 1086478942 | VIC71: 45341 | VIF71: 218.95 | VIK71: =+VIG71-VII71-VIK71 | VIM71: SEGUROS | VIN71: RIMAC SEGUROS | VIP71: 1086478942 | VIS71: 45341 | VIV71: 218.95 | VJA71: =+VIW71-VIY71-VJA71 | VJC71: SEGUROS | VJD71: RIMAC SEGUROS | VJF71: 1086478942 | VJI71: 45341 | VJL71: 218.95 | VJQ71: =+VJM71-VJO71-VJQ71 | VJS71: SEGUROS | VJT71: RIMAC SEGUROS | VJV71: 1086478942 | VJY71: 45341 | VKB71: 218.95 | VKG71: =+VKC71-VKE71-VKG71 | VKI71: SEGUROS | VKJ71: RIMAC SEGUROS | VKL71: 1086478942 | VKO71: 45341 | VKR71: 218.95 | VKW71: =+VKS71-VKU71-VKW71 | VKY71: SEGUROS | VKZ71: RIMAC SEGUROS | VLB71: 1086478942 | VLE71: 45341 | VLH71: 218.95 | VLM71: =+VLI71-VLK71-VLM71 | VLO71: SEGUROS | VLP71: RIMAC SEGUROS | VLR71: 1086478942 | VLU71: 45341 | VLX71: 218.95 | VMC71: =+VLY71-VMA71-VMC71 | VME71: SEGUROS | VMF71: RIMAC SEGUROS | VMH71: 1086478942 | VMK71: 45341 | VMN71: 218.95 | VMS71: =+VMO71-VMQ71-VMS71 | VMU71: SEGUROS | VMV71: RIMAC SEGUROS | VMX71: 1086478942 | VNA71: 45341 | VND71: 218.95 | VNI71: =+VNE71-VNG71-VNI71 | VNK71: SEGUROS | VNL71: RIMAC SEGUROS | VNN71: 1086478942 | VNQ71: 45341 | VNT71: 218.95 | VNY71: =+VNU71-VNW71-VNY71 | VOA71: SEGUROS | VOB71: RIMAC SEGUROS | VOD71: 1086478942 | VOG71: 45341 | VOJ71: 218.95 | VOO71: =+VOK71-VOM71-VOO71 | VOQ71: SEGUROS | VOR71: RIMAC SEGUROS | VOT71: 1086478942 | VOW71: 45341 | VOZ71: 218.95 | VPE71: =+VPA71-VPC71-VPE71 | VPG71: SEGUROS | VPH71: RIMAC SEGUROS | VPJ71: 1086478942 | VPM71: 45341 | VPP71: 218.95 | VPU71: =+VPQ71-VPS71-VPU71 | VPW71: SEGUROS | VPX71: RIMAC SEGUROS | VPZ71: 1086478942 | VQC71: 45341 | VQF71: 218.95 | VQK71: =+VQG71-VQI71-VQK71 | VQM71: SEGUROS | VQN71: RIMAC SEGUROS | VQP71: 1086478942 | VQS71: 45341 | VQV71: 218.95 | VRA71: =+VQW71-VQY71-VRA71 | VRC71: SEGUROS | VRD71: RIMAC SEGUROS | VRF71: 1086478942 | VRI71: 45341 | VRL71: 218.95 | VRQ71: =+VRM71-VRO71-VRQ71 | VRS71: SEGUROS | VRT71: RIMAC SEGUROS | VRV71: 1086478942 | VRY71: 45341 | VSB71: 218.95 | VSG71: =+VSC71-VSE71-VSG71 | VSI71: SEGUROS | VSJ71: RIMAC SEGUROS | VSL71: 1086478942 | VSO71: 45341 | VSR71: 218.95 | VSW71: =+VSS71-VSU71-VSW71 | VSY71: SEGUROS | VSZ71: RIMAC SEGUROS | VTB71: 1086478942 | VTE71: 45341 | VTH71: 218.95 | VTM71: =+VTI71-VTK71-VTM71 | VTO71: SEGUROS | VTP71: RIMAC SEGUROS | VTR71: 1086478942 | VTU71: 45341 | VTX71: 218.95 | VUC71: =+VTY71-VUA71-VUC71 | VUE71: SEGUROS | VUF71: RIMAC SEGUROS | VUH71: 1086478942 | VUK71: 45341 | VUN71: 218.95 | VUS71: =+VUO71-VUQ71-VUS71 | VUU71: SEGUROS | VUV71: RIMAC SEGUROS | VUX71: 1086478942 | VVA71: 45341 | VVD71: 218.95 | VVI71: =+VVE71-VVG71-VVI71 | VVK71: SEGUROS | VVL71: RIMAC SEGUROS | VVN71: 1086478942 | VVQ71: 45341 | VVT71: 218.95 | VVY71: =+VVU71-VVW71-VVY71 | VWA71: SEGUROS | VWB71: RIMAC SEGUROS | VWD71: 1086478942 | VWG71: 45341 | VWJ71: 218.95 | VWO71: =+VWK71-VWM71-VWO71 | VWQ71: SEGUROS | VWR71: RIMAC SEGUROS | VWT71: 1086478942 | VWW71: 45341 | VWZ71: 218.95 | VXE71: =+VXA71-VXC71-VXE71 | VXG71: SEGUROS | VXH71: RIMAC SEGUROS | VXJ71: 1086478942 | VXM71: 45341 | VXP71: 218.95 | VXU71: =+VXQ71-VXS71-VXU71 | VXW71: SEGUROS | VXX71: RIMAC SEGUROS | VXZ71: 1086478942 | VYC71: 45341 | VYF71: 218.95 | VYK71: =+VYG71-VYI71-VYK71 | VYM71: SEGUROS | VYN71: RIMAC SEGUROS | VYP71: 1086478942 | VYS71: 45341 | VYV71: 218.95 | VZA71: =+VYW71-VYY71-VZA71 | VZC71: SEGUROS | VZD71: RIMAC SEGUROS | VZF71: 1086478942 | VZI71: 45341 | VZL71: 218.95 | VZQ71: =+VZM71-VZO71-VZQ71 | VZS71: SEGUROS | VZT71: RIMAC SEGUROS | VZV71: 1086478942 | VZY71: 45341 | WAB71: 218.95 | WAG71: =+WAC71-WAE71-WAG71 | WAI71: SEGUROS | WAJ71: RIMAC SEGUROS | WAL71: 1086478942 | WAO71: 45341 | WAR71: 218.95 | WAW71: =+WAS71-WAU71-WAW71 | WAY71: SEGUROS | WAZ71: RIMAC SEGUROS | WBB71: 1086478942 | WBE71: 45341 | WBH71: 218.95 | WBM71: =+WBI71-WBK71-WBM71 | WBO71: SEGUROS | WBP71: RIMAC SEGUROS | WBR71: 1086478942 | WBU71: 45341 | WBX71: 218.95 | WCC71: =+WBY71-WCA71-WCC71 | WCE71: SEGUROS | WCF71: RIMAC SEGUROS | WCH71: 1086478942 | WCK71: 45341 | WCN71: 218.95 | WCS71: =+WCO71-WCQ71-WCS71 | WCU71: SEGUROS | WCV71: RIMAC SEGUROS | WCX71: 1086478942 | WDA71: 45341 | WDD71: 218.95 | WDI71: =+WDE71-WDG71-WDI71 | WDK71: SEGUROS | WDL71: RIMAC SEGUROS | WDN71: 1086478942 | WDQ71: 45341 | WDT71: 218.95 | WDY71: =+WDU71-WDW71-WDY71 | WEA71: SEGUROS | WEB71: RIMAC SEGUROS | WED71: 1086478942 | WEG71: 45341 | WEJ71: 218.95 | WEO71: =+WEK71-WEM71-WEO71 | WEQ71: SEGUROS | WER71: RIMAC SEGUROS | WET71: 1086478942 | WEW71: 45341 | WEZ71: 218.95 | WFE71: =+WFA71-WFC71-WFE71 | WFG71: SEGUROS | WFH71: RIMAC SEGUROS | WFJ71: 1086478942 | WFM71: 45341 | WFP71: 218.95 | WFU71: =+WFQ71-WFS71-WFU71 | WFW71: SEGUROS | WFX71: RIMAC SEGUROS | WFZ71: 1086478942 | WGC71: 45341 | WGF71: 218.95 | WGK71: =+WGG71-WGI71-WGK71 | WGM71: SEGUROS | WGN71: RIMAC SEGUROS | WGP71: 1086478942 | WGS71: 45341 | WGV71: 218.95 | WHA71: =+WGW71-WGY71-WHA71 | WHC71: SEGUROS | WHD71: RIMAC SEGUROS | WHF71: 1086478942 | WHI71: 45341 | WHL71: 218.95 | WHQ71: =+WHM71-WHO71-WHQ71 | WHS71: SEGUROS | WHT71: RIMAC SEGUROS | WHV71: 1086478942 | WHY71: 45341 | WIB71: 218.95 | WIG71: =+WIC71-WIE71-WIG71 | WII71: SEGUROS | WIJ71: RIMAC SEGUROS | WIL71: 1086478942 | WIO71: 45341 | WIR71: 218.95 | WIW71: =+WIS71-WIU71-WIW71 | WIY71: SEGUROS | WIZ71: RIMAC SEGUROS | WJB71: 1086478942 | WJE71: 45341 | WJH71: 218.95 | WJM71: =+WJI71-WJK71-WJM71 | WJO71: SEGUROS | WJP71: RIMAC SEGUROS | WJR71: 1086478942 | WJU71: 45341 | WJX71: 218.95 | WKC71: =+WJY71-WKA71-WKC71 | WKE71: SEGUROS | WKF71: RIMAC SEGUROS | WKH71: 1086478942 | WKK71: 45341 | WKN71: 218.95 | WKS71: =+WKO71-WKQ71-WKS71 | WKU71: SEGUROS | WKV71: RIMAC SEGUROS | WKX71: 1086478942 | WLA71: 45341 | WLD71: 218.95 | WLI71: =+WLE71-WLG71-WLI71 | WLK71: SEGUROS | WLL71: RIMAC SEGUROS | WLN71: 1086478942 | WLQ71: 45341 | WLT71: 218.95 | WLY71: =+WLU71-WLW71-WLY71 | WMA71: SEGUROS | WMB71: RIMAC SEGUROS | WMD71: 1086478942 | WMG71: 45341 | WMJ71: 218.95 | WMO71: =+WMK71-WMM71-WMO71 | WMQ71: SEGUROS | WMR71: RIMAC SEGUROS | WMT71: 1086478942 | WMW71: 45341 | WMZ71: 218.95 | WNE71: =+WNA71-WNC71-WNE71 | WNG71: SEGUROS | WNH71: RIMAC SEGUROS | WNJ71: 1086478942 | WNM71: 45341 | WNP71: 218.95 | WNU71: =+WNQ71-WNS71-WNU71 | WNW71: SEGUROS | WNX71: RIMAC SEGUROS | WNZ71: 1086478942 | WOC71: 45341 | WOF71: 218.95 | WOK71: =+WOG71-WOI71-WOK71 | WOM71: SEGUROS | WON71: RIMAC SEGUROS | WOP71: 1086478942 | WOS71: 45341 | WOV71: 218.95 | WPA71: =+WOW71-WOY71-WPA71 | WPC71: SEGUROS | WPD71: RIMAC SEGUROS | WPF71: 1086478942 | WPI71: 45341 | WPL71: 218.95 | WPQ71: =+WPM71-WPO71-WPQ71 | WPS71: SEGUROS | WPT71: RIMAC SEGUROS | WPV71: 1086478942 | WPY71: 45341 | WQB71: 218.95 | WQG71: =+WQC71-WQE71-WQG71 | WQI71: SEGUROS | WQJ71: RIMAC SEGUROS | WQL71: 1086478942 | WQO71: 45341 | WQR71: 218.95 | WQW71: =+WQS71-WQU71-WQW71 | WQY71: SEGUROS | WQZ71: RIMAC SEGUROS | WRB71: 1086478942 | WRE71: 45341 | WRH71: 218.95 | WRM71: =+WRI71-WRK71-WRM71 | WRO71: SEGUROS | WRP71: RIMAC SEGUROS | WRR71: 1086478942 | WRU71: 45341 | WRX71: 218.95 | WSC71: =+WRY71-WSA71-WSC71 | WSE71: SEGUROS | WSF71: RIMAC SEGUROS | WSH71: 1086478942 | WSK71: 45341 | WSN71: 218.95 | WSS71: =+WSO71-WSQ71-WSS71 | WSU71: SEGUROS | WSV71: RIMAC SEGUROS | WSX71: 1086478942 | WTA71: 45341 | WTD71: 218.95 | WTI71: =+WTE71-WTG71-WTI71 | WTK71: SEGUROS | WTL71: RIMAC SEGUROS | WTN71: 1086478942 | WTQ71: 45341 | WTT71: 218.95 | WTY71: =+WTU71-WTW71-WTY71 | WUA71: SEGUROS | WUB71: RIMAC SEGUROS | WUD71: 1086478942 | WUG71: 45341 | WUJ71: 218.95 | WUO71: =+WUK71-WUM71-WUO71 | WUQ71: SEGUROS | WUR71: RIMAC SEGUROS | WUT71: 1086478942 | WUW71: 45341 | WUZ71: 218.95 | WVE71: =+WVA71-WVC71-WVE71 | WVG71: SEGUROS | WVH71: RIMAC SEGUROS | WVJ71: 1086478942 | WVM71: 45341 | WVP71: 218.95 | WVU71: =+WVQ71-WVS71-WVU71 | WVW71: SEGUROS | WVX71: RIMAC SEGUROS | WVZ71: 1086478942 | WWC71: 45341 | WWF71: 218.95 | WWK71: =+WWG71-WWI71-WWK71 | WWM71: SEGUROS | WWN71: RIMAC SEGUROS | WWP71: 1086478942 | WWS71: 45341 | WWV71: 218.95 | WXA71: =+WWW71-WWY71-WXA71 | WXC71: SEGUROS | WXD71: RIMAC SEGUROS | WXF71: 1086478942 | WXI71: 45341 | WXL71: 218.95 | WXQ71: =+WXM71-WXO71-WXQ71 | WXS71: SEGUROS | WXT71: RIMAC SEGUROS | WXV71: 1086478942 | WXY71: 45341 | WYB71: 218.95 | WYG71: =+WYC71-WYE71-WYG71 | WYI71: SEGUROS | WYJ71: RIMAC SEGUROS | WYL71: 1086478942 | WYO71: 45341 | WYR71: 218.95 | WYW71: =+WYS71-WYU71-WYW71 | WYY71: SEGUROS | WYZ71: RIMAC SEGUROS | WZB71: 1086478942 | WZE71: 45341 | WZH71: 218.95 | WZM71: =+WZI71-WZK71-WZM71 | WZO71: SEGUROS | WZP71: RIMAC SEGUROS | WZR71: 1086478942 | WZU71: 45341 | WZX71: 218.95 | XAC71: =+WZY71-XAA71-XAC71 | XAE71: SEGUROS | XAF71: RIMAC SEGUROS | XAH71: 1086478942 | XAK71: 45341 | XAN71: 218.95 | XAS71: =+XAO71-XAQ71-XAS71 | XAU71: SEGUROS | XAV71: RIMAC SEGUROS | XAX71: 1086478942 | XBA71: 45341 | XBD71: 218.95 | XBI71: =+XBE71-XBG71-XBI71 | XBK71: SEGUROS | XBL71: RIMAC SEGUROS | XBN71: 1086478942 | XBQ71: 45341 | XBT71: 218.95 | XBY71: =+XBU71-XBW71-XBY71 | XCA71: SEGUROS | XCB71: RIMAC SEGUROS | XCD71: 1086478942 | XCG71: 45341 | XCJ71: 218.95 | XCO71: =+XCK71-XCM71-XCO71 | XCQ71: SEGUROS | XCR71: RIMAC SEGUROS | XCT71: 1086478942 | XCW71: 45341 | XCZ71: 218.95 | XDE71: =+XDA71-XDC71-XDE71 | XDG71: SEGUROS | XDH71: RIMAC SEGUROS | XDJ71: 1086478942 | XDM71: 45341 | XDP71: 218.95 | XDU71: =+XDQ71-XDS71-XDU71 | XDW71: SEGUROS | XDX71: RIMAC SEGUROS | XDZ71: 1086478942 | XEC71: 45341 | XEF71: 218.95 | XEK71: =+XEG71-XEI71-XEK71 | XEM71: SEGUROS | XEN71: RIMAC SEGUROS | XEP71: 1086478942 | XES71: 45341 | XEV71: 218.95 | XFA71: =+XEW71-XEY71-XFA71 | XFC71: SEGUROS
A72: LA POSITIVA
A73: PACIFICO COMPAÑIA DE SEGUROS Y REASEGUROS
A74: RIMAC SEGUROS
A75: RIMAC SEGUROS
A76: RIMAC SEGUROS
A77: RIMAC SEGUROS
A78: RIMAC EPS
A79: TOTAL
A81: Operación 6 - Materia Prima Exterior
A82: PROVEEDOR | B82: TIPO | C82: N° DOCUMENTO | D82: FEC. REGISTRO | E82: FEC.DOC | F82: FEC.VCTO | G82: IMPORTE | H82: PAGADO | I82: SALDO | J82: PLAZO | K82: % DET | L82: DET | M82: % RET | N82: RET | O82: NETO | P82: DETALLE | Q82: N° O/C-O/S | R82: N° Registro | S82: LINK FACTURA
J83: =F83-E83 | O83: =I83-L83-N83
J84: =F84-E84 | O84: =I84-L84-N84
A85: TOTAL | O85: =SUM(O84)
A87: Operación 7 - Materia Prima Nacional
A88: PROVEEDOR | B88: TIPO | C88: N° DOCUMENTO | D88: FEC. REGISTRO | E88: FEC.DOC | F88: FEC.VCTO | G88: IMPORTE | H88: PAGADO | I88: SALDO | J88: PLAZO | K88: % DET | L88: DET | M88: % RET | N88: RET | O88: NETO | P88: DETALLE | Q88: N° O/C-O/S | R88: N° Registro | S88: LINK FACTURA
J89: =F89-E89 | O89: =I89-L89-N89
J90: =F90-E90 | O90: =I90-L90-N90
A91: TOTAL | O91: =SUM(O90)
A93: Operación 8 - Transferencias entre cuentas
A94: PROVEEDOR | B94: TIPO | C94: N° DOCUMENTO | D94: FEC. REGISTRO | E94: FEC.DOC | F94: FEC.VCTO | G94: IMPORTE | H94: PAGADO | I94: SALDO | J94: PLAZO | K94: % DET | L94: DET | M94: % RET | N94: RET | O94: NETO | P94: DETALLE | Q94: N° O/C-O/S | R94: N° Registro | S94: LINK FACTURA
J95: =F95-E95 | O95: =I95-L95-N95
J96: =F96-E96 | O96: =I96-L96-N96
A97: TOTAL | O97: =SUM(O92:O96)
Q152: 0 | S152: 2024040234 | T152: https://drive.google.com/file/d/1hVOUaNDJzV9Bxg7DP_2hgczSOdJkT-CE/view
Q153: 0 | S153: 2024040233 | T153: https://drive.google.com/file/d/1g6_e82za9104ZYTj1tJObToA4xrnxYRH/view
Q154: 0 | S154: 2024040235 | T154: https://drive.google.com/file/d/1njxe1k4KZjneol1wa_uPqQIulbIqec1D/view

Sheet Detalle de agentes
A2: PROVEEDOR | B2: TIPO | C2: N° DOCUMENTO | D2: FEC. REGISTRO | E2: FEC.DOC | F2: FEC.VCTO | G2: IMPORTE | H2: PAGADO | I2: SALDO | J2: % DET | K2: DET | L2: % RET | M2: RET | N2: Neto | O2: PRODUCTO | P2: AGENTE ADUANERO | Q2: N° O/C-O/S | S2: LINK FACTURA
N3: =I3-K3-M3
N4: =I4-K4-M4
N5: =I5-K5-M5
N6: =SUM(N3:N5)
N7: =I7-K7-M7
N8: =I8-K8-M8
N9: =I9-K9-M9
N10: =SUM(N7:N9)
N11: =I11-K11-M11
N12: =I12-K12-M12
N13: =I13-K13-M13
N14: =SUM(N11:N13)
N15: =I15-K15-M15
N16: =I16-K16-M16
N17: =I17-K17-M17
N18: =SUM(N15:N17)
N19: =I19-K19-M19
N20: =I20-K20-M20
N21: =I21-K21-M21
N22: =SUM(N19:N21)
N23: =+N6+N10+N14+N18+N22
A25: PROVEEDOR | B25: TIPO | C25: N° DOCUMENTO | D25: FEC. REGISTRO | E25: FEC.DOC | F25: FEC.VCTO | G25: IMPORTE | H25: PAGADO | I25: SALDO | J25: % DET | K25: DET | L25: % RET | M25: RET | N25: Neto | O25: PRODUCTO | P25: AGENTE ADUANERO | Q25: N° O/C-O/S | S25: LINK FACTURA
N26: =I26-K26-M26
N27: =I27-K27-M27
N28: =I28-K28-M28
N29: =I29-K29-M29
N30: =I30-K30-M30
N31: =I31-K31-M31
N32: =I32-K32-M32
N33: =SUM(N26:N32)
N34: =I34-K34-M34 | P34: DOGANA S.A. AGENTES AFIANZADOS DE ADUANAS
N35: =I35-K35-M35
N36: =I36-K36-M36
N37: =I37-K37-M37
N38: =I38-K38-M38
N39: =I39-K39-M39
N40: =I40-K40-M40
N41: =I41-K41-M41
N42: =I42-K42-M42
N43: =I43-K43-M43
N44: =SUM(N34:N43)
N45: =I45-K45-M45 | P45: MELKARTH AGENTES ADUANEROS S.A.C.
N46: =I46-K46-M46
N47: =I47-K47-M47
N48: =I48-K48-M48
N49: =I49-K49-M49
N50: =I50-K50-M50
N51: =I51-K51-M51
N52: =I52-K52-M52
N53: =I53-K53-M53
N54: =I54-K54-M54
N55: =SUM(N45:O54)
N56: =I56-K56-M56
N57: =I57-K57-M57
N58: =I58-K58-M58
N59: =I59-K59-M59
N60: =I60-K60-M60
N61: =I61-K61-M61
N62: =I62-K62-M62
N63: =I63-K63-M63
N64: =I64-K64-M64
N65: =I65-K65-M65
N66: =SUM(N56:N65)
N67: =I67-K67-M67
N68: =I68-K68-M68
N69: =I69-K69-M69
N70: =I70-K70-M70
N71: =I71-K71-M71
N72: =I72-K72-M72
N73: =I73-K73-M73
N74: =I74-K74-M74
N75: =I75-K75-M75
N76: =SUM(N67:O75)
N77: =I77-K77-M77
N78: =I78-K78-M78
N79: =I79-K79-M79
N80: =I80-K80-M80
N81: =I81-K81-M81
N82: =I82-K82-M82
N83: =I83-K83-M83
N84: =I84-K84-M84
N85: =I85-K85-M85
N86: =I86-K86-M86
N87: =SUM(N77:N86)
N88: =I88-K88-M88
N89: =I89-K89-M89
N90: =I90-K90-M90
N91: =I91-K91-M91
N92: =I92-K92-M92
N93: =I93-K93-M93
N94: =I94-K94-M94
N95: =I95-K95-M95
N96: =SUM(N88:N95)
N97: =I97-K97-M97
N98: =I98-K98-M98
N99: =I99-K99-M99
N100: =I100-K100-M100
N101: =I101-K101-M101
N102: =I102-K102-M102
...
